Workbook
Name SlicerCache_Table_1_Col_1: #N/A

Sheet Customer_Dim
A1: Customer_ID | B1: Name | C1: Age | D1: Gender | E1: City | F1: State | G1: Country | H1: Loyalty_Level
A2: CUST1464 | B2: David Pierce | C2: 45 | D2: Female | E2: Grayland | F2: Washington | G2: USA | H2: Platinum | I2: =IFS(H2="","",H2="Platinum",1,H2="Bronze",2,H2="Gold",3,H2="Silver",4) -> 1
A3: CUST1486 | B3: Eric Lee | C3: 22 | D3: Female | E3: Lake April | F3: Vermont | G3: USA | H3: Bronze | I3: =IFS(H3="","",H3="Platinum",1,H3="Bronze",2,H3="Gold",3,H3="Silver",4) -> 2
A4: CUST1491 | B4: Kaitlin Brown | C4: 52 | D4: Female | E4: Kellyberg | F4: South Dakota | G4: USA | H4: Gold | I4: =IFS(H4="","",H4="Platinum",1,H4="Bronze",2,H4="Gold",3,H4="Silver",4) -> 3
A5: CUST1499 | B5: Philip Pennington | C5: 27 | D5: Female | E5: East Valerieview | F5: Oregon | G5: USA | H5: Platinum | I5: =IFS(H5="","",H5="Platinum",1,H5="Bronze",2,H5="Gold",3,H5="Silver",4) -> 1
A6: CUST1000 | B6: Sheena Bonilla | C6: 55 | D6: Male | E6: Donaldton | F6: North Carolina | G6: USA | I6: =IFS(H6="","",H6="Platinum",1,H6="Bronze",2,H6="Gold",3,H6="Silver",4)
A7: CUST1001 | B7: Eugene Nelson | C7: 26 | D7: Female | E7: Phillipsmouth | F7: North Dakota | G7: USA | H7: Platinum | I7: =IFS(H7="","",H7="Platinum",1,H7="Bronze",2,H7="Gold",3,H7="Silver",4) -> 1
A8: CUST1002 | B8: Dr. Benjamin Price | C8: 29 | D8: Female | E8: Kylebury | F8: Alabama | G8: USA | H8: Platinum | I8: =IFS(H8="","",H8="Platinum",1,H8="Bronze",2,H8="Gold",3,H8="Silver",4) -> 1
A9: CUST1003 | B9: Jeremy Harris | C9: 59 | D9: Female | E9: Thomastown | F9: Ohio | G9: USA | H9: Bronze | I9: =IFS(H9="","",H9="Platinum",1,H9="Bronze",2,H9="Gold",3,H9="Silver",4) -> 2
A10: CUST1004 | B10: Caroline Collins | C10: 64 | D10: Female | E10: Nicholasshire | F10: California | G10: USA | H10: Silver | I10: =IFS(H10="","",H10="Platinum",1,H10="Bronze",2,H10="Gold",3,H10="Silver",4) -> 4
A11: CUST1005 | B11: Christine Vaughn | C11: 24 | D11: Male | E11: East Amandamouth | F11: Oregon | G11: USA | H11: Bronze | I11: =IFS(H11="","",H11="Platinum",1,H11="Bronze",2,H11="Gold",3,H11="Silver",4) -> 2
A12: CUST1006 | B12: Amber Jackson | C12: 29 | D12: Female | E12: Deborahborough | F12: South Dakota | G12: USA | H12: Platinum | I12: =IFS(H12="","",H12="Platinum",1,H12="Bronze",2,H12="Gold",3,H12="Silver",4) -> 1
A13: CUST1007 | B13: Daniel Boyd | C13: 29 | D13: Female | E13: West Pamelafurt | F13: West Virginia | G13: USA | H13: Bronze | I13: =IFS(H13="","",H13="Platinum",1,H13="Bronze",2,H13="Gold",3,H13="Silver",4) -> 2
A14: CUST1008 | B14: Melissa Howard | C14: 53 | D14: Female | E14: Maynardton | F14: New Hampshire | G14: USA | H14: Gold | I14: =IFS(H14="","",H14="Platinum",1,H14="Bronze",2,H14="Gold",3,H14="Silver",4) -> 3
A15: CUST1009 | B15: Ms. Maria Leach | C15: 64 | D15: Male | E15: Melissashire | F15: Pennsylvania | G15: USA | H15: Platinum | I15: =IFS(H15="","",H15="Platinum",1,H15="Bronze",2,H15="Gold",3,H15="Silver",4) -> 1
A16: CUST1010 | B16: Dominic Page | C16: 53 | D16: Male | E16: Port Michaelburgh | F16: Pennsylvania | G16: USA | H16: Bronze | I16: =IFS(H16="","",H16="Platinum",1,H16="Bronze",2,H16="Gold",3,H16="Silver",4) -> 2
A17: CUST1011 | B17: Brian Lopez | C17: 28 | D17: Female | E17: East Krista | F17: New York | G17: USA | H17: Gold | I17: =IFS(H17="","",H17="Platinum",1,H17="Bronze",2,H17="Gold",3,H17="Silver",4) -> 3
A18: CUST1012 | B18: Kenneth Lambert | C18: 55 | D18: Female | E18: North Kathryn | F18: Kansas | G18: USA | H18: Platinum | I18: =IFS(H18="","",H18="Platinum",1,H18="Bronze",2,H18="Gold",3,H18="Silver",4) -> 1
... A23: CUST1017 | B23: Adam Cruz | C23: 60 | D23: Female | E23: Brandonville | F23: Georgia | G23: USA | H23: Platinum | I23: =IFS(H23="","",H23="Platinum",1,H23="Bronze",2,H23="Gold",3,H23="Silver",4) -> 1
A24: CUST1018 | B24: Rhonda Moss | C24: 43 | D24: Male | E24: South William | F24: Kansas | G24: USA | I24: =IFS(H24="","",H24="Platinum",1,H24="Bronze",2,H24="Gold",3,H24="Silver",4)
A25: CUST1019 | B25: Michael Torres | C25: 46 | D25: Female | E25: Gonzalezfort | F25: New Jersey | G25: USA | H25: Platinum | I25: =IFS(H25="","",H25="Platinum",1,H25="Bronze",2,H25="Gold",3,H25="Silver",4) -> 1
A26: CUST1020 | B26: Bridget Allen | C26: 59 | D26: Male | E26: Lake Shaneburgh | F26: Delaware | G26: USA | H26: Silver | I26: =IFS(H26="","",H26="Platinum",1,H26="Bronze",2,H26="Gold",3,H26="Silver",4) -> 4
A27: CUST1021 | B27: Jeff Martinez | C27: 36 | D27: Female | E27: Smithburgh | F27: Oklahoma | G27: USA | H27: Gold | I27: =IFS(H27="","",H27="Platinum",1,H27="Bronze",2,H27="Gold",3,H27="Silver",4) -> 3
A28: CUST1022 | B28: Paul Fox | C28: 33 | D28: Female | E28: Michaelton | F28: Hawaii | G28: USA | H28: Silver | I28: =IFS(H28="","",H28="Platinum",1,H28="Bronze",2,H28="Gold",3,H28="Silver",4) -> 4
A29: CUST1023 | B29: Jonathan Steele | C29: 52 | D29: Female | E29: Molinabury | F29: Oregon | G29: USA | H29: Silver | I29: =IFS(H29="","",H29="Platinum",1,H29="Bronze",2,H29="Gold",3,H29="Silver",4) -> 4
A30: CUST1024 | B30: Heather Collins | C30: 40 | D30: Male | E30: Rogerschester | F30: Idaho | G30: USA | H30: Platinum | I30: =IFS(H30="","",H30="Platinum",1,H30="Bronze",2,H30="Gold",3,H30="Silver",4) -> 1
A31: CUST1025 | B31: Diana Taylor | C31: 59 | D31: Female | E31: Vasqueztown | F31: California | G31: USA | H31: Bronze | I31: =IFS(H31="","",H31="Platinum",1,H31="Bronze",2,H31="Gold",3,H31="Silver",4) -> 2
A32: CUST1026 | B32: Amber Carlson | C32: 18 | D32: Female | E32: East Michellemouth | F32: Missouri | G32: USA | H32: Gold | I32: =IFS(H32="","",H32="Platinum",1,H32="Bronze",2,H32="Gold",3,H32="Silver",4) -> 3
A33: CUST1027 | B33: Leslie Johnson | C33: 31 | D33: Male | E33: Mollyshire | F33: Utah | G33: USA | I33: =IFS(H33="","",H33="Platinum",1,H33="Bronze",2,H33="Gold",3,H33="Silver",4)
A34: CUST1028 | B34: Joshua Ryan | C34: 27 | D34: Female | E34: New David | F34: New Jersey | G34: USA | H34: Platinum | I34: =IFS(H34="","",H34="Platinum",1,H34="Bronze",2,H34="Gold",3,H34="Silver",4) -> 1
A35: CUST1029 | B35: David Arnold | C35: 54 | D35: Female | E35: East Jennifer | F35: California | G35: USA | H35: Silver | I35: =IFS(H35="","",H35="Platinum",1,H35="Bronze",2,H35="Gold",3,H35="Silver",4) -> 4
A36: CUST1030 | B36: Jessica Acevedo | C36: 64 | D36: Female | E36: Amybury | F36: Pennsylvania | G36: USA | H36: Bronze | I36: =IFS(H36="","",H36="Platinum",1,H36="Bronze",2,H36="Gold",3,H36="Silver",4) -> 2
A37: CUST1031 | B37: Sarah Vance | C37: 41 | D37: Male | E37: Johnsonville | F37: Oregon | G37: USA | H37: Silver | I37: =IFS(H37="","",H37="Platinum",1,H37="Bronze",2,H37="Gold",3,H37="Silver",4) -> 4
A38: CUST1032 | B38: Mike Jennings | C38: 48 | D38: Female | E38: Fostermouth | F38: Arizona | G38: USA | H38: Gold | I38: =IFS(H38="","",H38="Platinum",1,H38="Bronze",2,H38="Gold",3,H38="Silver",4) -> 3
A39: CUST1033 | B39: Robert Jones Dds | C39: 25 | D39: Male | E39: Tristanton | F39: Oklahoma | G39: USA | H39: Platinum | I39: =IFS(H39="","",H39="Platinum",1,H39="Bronze",2,H39="Gold",3,H39="Silver",4) -> 1
A40: CUST1034 | B40: Christopher Olson | C40: 27 | D40: Female | E40: West Richard | F40: Maryland | G40: USA | H40: Platinum | I40: =IFS(H40="","",H40="Platinum",1,H40="Bronze",2,H40="Gold",3,H40="Silver",4) -> 1
A41: CUST1035 | B41: Rachel Myers | C41: 52 | D41: Male | E41: Robertberg | F41: North Dakota | G41: USA | H41: Silver | I41: =IFS(H41="","",H41="Platinum",1,H41="Bronze",2,H41="Gold",3,H41="Silver",4) -> 4
A42: CUST1036 | B42: Thomas Phillips | C42: 20 | D42: Female | E42: Luisfurt | F42: Georgia | G42: USA | H42: Gold | I42: =IFS(H42="","",H42="Platinum",1,H42="Bronze",2,H42="Gold",3,H42="Silver",4) -> 3
A43: CUST1037 | B43: Christopher Carter | C43: 27 | D43: Female | E43: Brendastad | F43: South Dakota | G43: USA | I43: =IFS(H43="","",H43="Platinum",1,H43="Bronze",2,H43="Gold",3,H43="Silver",4)
A44: CUST1038 | B44: Deanna Simpson | C44: 35 | D44: Female | E44: Brownport | F44: North Dakota | G44: USA | H44: Bronze | I44: =IFS(H44="","",H44="Platinum",1,H44="Bronze",2,H44="Gold",3,H44="Silver",4) -> 2
A45: CUST1039 | B45: Tonya Reynolds | C45: 55 | D45: Female | E45: Darleneton | F45: Michigan | G45: USA | H45: Gold | I45: =IFS(H45="","",H45="Platinum",1,H45="Bronze",2,H45="Gold",3,H45="Silver",4) -> 3
A46: CUST1040 | B46: Eric Vega | C46: 50 | D46: Male | E46: Williamsonland | F46: Kansas | G46: USA | H46: Gold | I46: =IFS(H46="","",H46="Platinum",1,H46="Bronze",2,H46="Gold",3,H46="Silver",4) -> 3
A47: CUST1041 | B47: James Gibbs | C47: 21 | D47: Male | E47: Mooneyshire | F47: Alaska | G47: USA | H47: Platinum | I47: =IFS(H47="","",H47="Platinum",1,H47="Bronze",2,H47="Gold",3,H47="Silver",4) -> 1
A48: CUST1042 | B48: William Martin | C48: 19 | D48: Male | E48: Ryanburgh | F48: Connecticut | G48: USA | H48: Platinum | I48: =IFS(H48="","",H48="Platinum",1,H48="Bronze",2,H48="Gold",3,H48="Silver",4) -> 1
A49: CUST1043 | B49: Joseph Snow | C49: 45 | D49: Male | E49: South Michaelfort | F49: Vermont | G49: USA | H49: Gold | I49: =IFS(H49="","",H49="Platinum",1,H49="Bronze",2,H49="Gold",3,H49="Silver",4) -> 3
A50: CUST1044 | B50: Denise Williams | C50: 34 | D50: Male | E50: Christianstad | F50: Hawaii | G50: USA | H50: Bronze | I50: =IFS(H50="","",H50="Platinum",1,H50="Bronze",2,H50="Gold",3,H50="Silver",4) -> 2
A51: CUST1045 | B51: Jordan Jackson Dds | C51: 54 | D51: Male | E51: North Johnview | F51: Arizona | G51: USA | H51: Gold | I51: =IFS(H51="","",H51="Platinum",1,H51="Bronze",2,H51="Gold",3,H51="Silver",4) -> 3
A52: CUST1046 | B52: Michelle Garcia Dds | C52: 55 | D52: Female | E52: Perezbury | F52: Ohio | G52: USA | H52: Platinum | I52: =IFS(H52="","",H52="Platinum",1,H52="Bronze",2,H52="Gold",3,H52="Silver",4) -> 1
A53: CUST1047 | B53: Gina Knight | C53: 54 | D53: Female | E53: Lake Roberthaven | F53: Nevada | G53: USA | H53: Silver | I53: =IFS(H53="","",H53="Platinum",1,H53="Bronze",2,H53="Gold",3,H53="Silver",4) -> 4
A54: CUST1048 | B54: April Mullins | C54: 54 | D54: Male | E54: Dawsonbury | F54: North Carolina | G54: USA | H54: Platinum | I54: =IFS(H54="","",H54="Platinum",1,H54="Bronze",2,H54="Gold",3,H54="Silver",4) -> 1
A55: CUST1049 | B55: Timothy Weaver | C55: 45 | D55: Female | E55: New Amy | F55: Ohio | G55: USA | H55: Gold | I55: =IFS(H55="","",H55="Platinum",1,H55="Bronze",2,H55="Gold",3,H55="Silver",4) -> 3
... A501: CUST1498 | B501: Traci Gonzalez | C501: 35 | D501: Male | E501: Snyderfurt | F501: New Mexico | G501: USA | H501: Silver | I501: =IFS(H501="","",H501="Platinum",1,H501="Bronze",2,H501="Gold",3,H501="Silver",4) -> 4

Sheet Product_Dim
A1: Product_ID | B1: Product_Name | C1: Category | D1: Sub_Category | E1: Brand | F1: Cost | G1: Stock
A2: PROD0 | B2: Brother Laser Printer | C2: Electronics | D2: Computer | E2: Hunt Inc | F2: 112.42 | G2: 416
A3: PROD1 | B3: Men's Graphic T-Shirt | C3: Clothing | D3: Tops | E3: Terry-Moore | F3: 342.56 | G3: 181
A4: PROD2 | B4: Women's Casual Hoodie | C4: Clothing | D4: Outerwear | E4: Sims Inc | G4: 352
A5: PROD3 | B5: Men's Running Jacket | C5: Clothing | D5: Outerwear | E5: Pineda Ltd | F5: 364.67 | G5: 452
A6: PROD4 | B6: Women's Yoga Pants | C6: Clothing | D6: Bottoms | E6: Gonzales-Davis | F6: 306.46 | G6: 487
A7: PROD5 | B7: Men's Leather Belt | C7: Clothing | D7: Accessories | E7: Baldwin, Garza and Gonzalez | F7: 261 | G7: 59
A8: PROD6 | B8: Herbal Face Moisturizer | C8: Beauty | D8: Skincare | E8: Davidson PLC | F8: 312.8 | G8: 350
A9: PROD7 | B9: LED Table Lamp | C9: Home | D9: Lighting | E9: Harrell LLC | F9: 218.86 | G9: 170
A10: PROD8 | B10: Wireless Bluetooth Earbuds | C10: Electronics | D10: Audio | E10: Perez-Johnston | F10: 439.07 | G10: 142
A11: PROD9 | B11: Adjustable Dumbbell Set | C11: Sports | D11: Fitness | E11: Hill PLC | F11: 495.72 | G11: 323
A12: PROD10 | B12: Ceramic Kitchen Bowl Set | C12: Home | D12: Kitchen | E12: Hamilton Group | F12: 298.86 | G12: 308
A13: PROD11 | B13: HD Smart TV Stick | C13: Electronics | D13: Accessories | E13: Gibson, Hobbs and Weaver | F13: 449.4
A14: PROD12 | B14: Hair Strengthening Shampoo | C14: Beauty | D14: Haircare | E14: Rice LLC | F14: 115.82 | G14: 460
A15: PROD13 | B15: USB-C Fast Charger | C15: Electronics | D15: Accessories | E15: Dawson-Perkins | F15: 242.23 | G15: 453
A16: PROD14 | B16: Decorative Wall Mirror | C16: Home | D16: Decor | E16: Luna, Anderson and Bowman | F16: 48.01 | G16: 439
A17: PROD15 | B17: 4K Home Projector | C17: Electronics | D17: Appliances | E17: Thomas LLC | F17: 465.34 | G17: 301
A18: PROD16 | B18: Beard Grooming Kit | C18: Beauty | D18: Grooming | E18: Erickson-Green | F18: 337.42 | G18: 256
A19: PROD17 | B19: Soccer Training Cone Set | C19: Sports | D19: Accessories | E19: Ford, Murphy and Wilson | F19: 144.53 | G19: 367
A20: PROD18 | B20: Women's Denim Jeans | C20: Clothing | D20: Bottoms | E20: Guerra-Hendrix | G20: 343
A21: PROD19 | B21: Knee Support Brace | C21: Sports | D21: Equipment | E21: May-Reese | F21: 21.34 | G21: 65
A22: PROD20 | B22: Outdoor Sports Water Bottle | C22: Sports | D22: Accessories | E22: Soto-Ellis | F22: 131.51
A23: PROD21 | B23: Multi-Purpose Storage Box | C23: Home | D23: Storage | E23: Gardner-Montes | F23: 123.46 | G23: 76
A24: PROD22 | B24: Carbon Fiber Tennis Racket | C24: Sports | D24: Equipment | E24: Flores, Pineda and Rodriguez | F24: 484.62 | G24: 432
A25: PROD23 | B25: Men's Formal Shirt | C25: Clothing | D25: Tops | E25: Moon, Mora and Santos | G25: 360
A26: PROD24 | B26: Foldable Camping Chair | C26: Sports | D26: Outdoor | E26: Cook Ltd | F26: 166.06 | G26: 340
A27: PROD25 | B27: Women's Scarf Set | C27: Clothing | D27: Accessories | E27: Brown and Sons | F27: 174.02 | G27: 268
A28: PROD26 | B28: Wireless Bluetooth Speaker | C28: Electronics | D28: Audio | E28: Reed-Schmidt | F28: 322.41 | G28: 213
A29: PROD27 | B29: Decorative Floor Vase | C29: Home | D29: Decor | E29: Khan, Jones and Paul | G29: 378
A30: PROD28 | B30: Sports Stopwatch Timer | C30: Sports | D30: Accessories | E30: Burns-Hansen | F30: 38.76 | G30: 137
A31: PROD29 | B31: Fabric Sofa Throw Blanket | C31: Home | D31: Decor | E31: Hoffman Group | F31: 218.48 | G31: 276
A32: PROD30 | B32: Stainless Steel Cutlery Set | C32: Home | D32: Kitchen | E32: Stevens, Fernandez and Martin | F32: 19.52 | G32: 57
A33: PROD31 | B33: Basketball | C33: Sports | D33: Team Sports | E33: Nolan-Snow | F33: 204.39 | G33: 281
A34: PROD32 | B34: Vitamin C Face Serum | C34: Beauty | D34: Skincare | E34: Griffin Ltd | F34: 283.83 | G34: 244
A35: PROD33 | B35: Modern Wall Clock | C35: Home | D35: Decor | E35: Weiss-Watson | F35: 179.77 | G35: 305
A36: PROD34 | B36: Gaming Mechanical Keyboard | C36: Electronics | D36: Computer | E36: Lucero LLC | F36: 419.28 | G36: 86
A37: PROD35 | B37: Bedroom Table Lamp | C37: Home | D37: Lighting | E37: Jones LLC | F37: 382.22 | G37: 329
A38: PROD36 | B38: Women's Summer Dress | C38: Clothing | D38: Tops | E38: Smith-Mills | F38: 223.43 | G38: 154
A39: PROD37 | B39: Men's Casual Sneakers | C39: Clothing | D39: Footwear | E39: Hogan-Lee | F39: 353.47 | G39: 214
A40: PROD38 | B40: Sports Water Hydration Pack | C40: Sports | D40: Outdoor | E40: Sims-Smith | F40: 135.61 | G40: 394
A41: PROD39 | B41: Portable Power Bank | C41: Electronics | D41: Mobile | E41: Cummings and Sons | F41: 326.06 | G41: 301
... A48: PROD46 | B48: Men's Winter Jacket | C48: Clothing | D48: Outerwear | E48: Kelly, Smith and Perez | F48: 167.34 | G48: 296
A49: PROD47 | B49: Makeup Brush Set | C49: Beauty | D49: Makeup | E49: Cook Inc | G49: 431
A50: PROD48 | B50: Car Dashboard Phone Holder | C50: Electronics | D50: Accessories | E50: Byrd, Stewart and Valdez | F50: 177.98 | G50: 103
A51: PROD49 | B51: Men's Roll-On Perfume | C51: Beauty | D51: Fragrance | E51: Sullivan and Sons | F51: 43.29 | G51: 267
A52: PROD50 | B52: Boxing Hand Wraps | C52: Sports | D52: Fitness | E52: Smith-King | F52: 190.29 | G52: 260
A53: PROD51 | B53: HDMI Cable – 2m | C53: Electronics | D53: Accessories | E53: Bautista, Green and Hale | F53: 88.49 | G53: 246
A54: PROD52 | B54: Rugby Ball | C54: Sports | D54: Team Sports | E54: Harris Inc | F54: 212.26 | G54: 82
A55: PROD53 | B55: Men's Track Pants | C55: Clothing | D55: Bottoms | E55: Hamilton, Woods and Walker | F55: 386.56 | G55: 125
A56: PROD54 | B56: Sports Stopwatch Pro | C56: Sports | D56: Accessories | E56: Thompson-French | F56: 434.84 | G56: 185
A57: PROD55 | B57: Ceramic Plant Pot | C57: Home | D57: Decor | E57: Hatfield, Baird and Torres | F57: 81.75
A58: PROD56 | B58: Premium Blanket Throw | C58: Home | D58: Decor | E58: Hernandez, Kennedy and Porter | F58: 461.47 | G58: 190
A59: PROD57 | B59: Foam Roller | C59: Sports | D59: Fitness | E59: Atkinson, Camacho and Oliver | F59: 30.62 | G59: 138
A60: PROD58 | B60: Womens Cotton Scarf | C60: Clothing | D60: Accessories | E60: Shepherd-Gould | F60: 113.83 | G60: 485
A61: PROD59 | B61: Men's Hair Styling Gel | C61: Beauty | D61: Haircare | E61: Cline-Mccarthy | F61: 17.31 | G61: 399
A62: PROD60 | B62: Luxury Perfume Spray | C62: Beauty | D62: Fragrance | E62: Gibson, Green and Lopez | F62: 482.75 | G62: 444
A63: PROD61 | B63: Tennis Ball 3-Pack | C63: Sports | D63: Equipment | E63: Lopez LLC | F63: 103.45 | G63: 465
A64: PROD62 | B64: Laptop Cooling Pad | C64: Electronics | D64: Computer | E64: Murray, Gould and Ware | F64: 86.42 | G64: 222
A65: PROD63 | B65: Organic Sunscreen Lotion | C65: Beauty | D65: Skincare | E65: Anderson-Riley | F65: 266.86 | G65: 458
A66: PROD64 | B66: Matte Lipstick Set | C66: Beauty | D66: Makeup | E66: Zhang Inc | F66: 299.11 | G66: 118
A67: PROD65 | B67: Adjustable Dumbbells 20kg | C67: Sports | D67: Fitness | E67: Montgomery, Benton and Miller | F67: 240.63 | G67: 423
A68: PROD66 | B68: Women's Hair Dryer Brush | C68: Beauty | D68: Haircare | E68: Torres, Spencer and Potter | F68: 340.39 | G68: 177
A69: PROD67 | B69: Smart LED Light Strip | C69: Electronics | D69: Accessories | E69: Flores-Davis | F69: 349.17 | G69: 476
... A84: PROD82 | B84: Fitness Resistance Bands | C84: Sports | D84: Fitness | E84: Reese-Watson | F84: 152.92 | G84: 281
A85: PROD83 | B85: Hydrating Face Cleanser | C85: Beauty | D85: Skincare | E85: Butler Group | G85: 159
A86: PROD84 | B86: Wooden Bookshelf | C86: Home | D86: Furniture | E86: Collins-Stephenson | F86: 388.46 | G86: 208
A87: PROD85 | B87: Women's Beanie Hat | C87: Clothing | D87: Accessories | E87: Richardson-Carrillo | F87: 119.57 | G87: 210
A88: PROD86 | B88: Kitchen Cutting Board | C88: Home | D88: Kitchen | E88: Taylor, Dodson and Johnston | F88: 176.07 | G88: 82
A89: PROD87 | B89: LED Bedside Lamp | C89: Home | D89: Lighting | E89: Aguilar, Horton and Lewis | F89: 371.38 | G89: 220
A90: PROD88 | B90: Sports Wrist Sweatbands | C90: Sports | D90: Accessories | E90: Olsen-Daniels | F90: 131.24 | G90: 232
A91: PROD89 | B91: Face Foundation Kit | C91: Beauty | D91: Makeup | E91: Taylor-Elliott | F91: 183.04 | G91: 457
A92: PROD90 | B92: Gaming Mouse Pad XL | C92: Electronics | D92: Accessories | E92: Sharp, Taylor and Rodriguez | F92: 340.14 | G92: 361
A93: PROD91 | B93: Women's High Heels | C93: Clothing | D93: Footwear | E93: Smith-Charles | F93: 438.25 | G93: 496
A94: PROD92 | B94: Microwave Oven | C94: Home | D94: Appliances | E94: Green, Powell and Palmer | F94: 447.43 | G94: 191
A95: PROD93 | B95: USB-C Laptop Charger | C95: Electronics | D95: Computer | E95: Martin LLC | F95: 377.52 | G95: 485
A96: PROD94 | B96: Vitamin E Body Lotion | C96: Beauty | D96: Skincare | E96: Hoffman-Williams | F96: 358.47 | G96: 213
A97: PROD95 | B97: Sports Stopwatch Basic | C97: Sports | D97: Accessories | E97: Wilson Group | F97: 60.65 | G97: 75
... A101: PROD99 | B101: Stainless Steel Cookware Set | C101: Home | D101: Kitchen | E101: Campbell Ltd | F101: 201.41 | G101: 146

Sheet Store_Dim
A1: Store_ID | B1: Store_Name | C1: Region | D1: City | E1: Store_Type
A2: STORE0 | B2: Rivera-Warner | C2: East | D2: Washingtonfurt | E2: Flagship
A3: STORE1 | B3: Martinez, Adkins and Johnson | C3: North | D3: Danielmouth | E3: Flagship
A4: STORE2 | B4: Black-Horn | C4: South | D4: North Nancyview | E4: Outlet
A5: STORE3 | B5: Johnson-Wright | C5: North | D5: Hoodberg | E5: Outlet
A6: STORE4 | B6: Alexander Group | C6: South | D6: Port Sharon | E6: Online
A7: STORE5 | B7: Gray Ltd | C7: North | D7: New Michaelchester | E7: Outlet
A8: STORE6 | B8: Benson-Elliott | C8: East | D8: Port Josephberg | E8: Online
A9: STORE7 | B9: Martinez-Mullins | C9: South | D9: Williamsfurt | E9: Online
A10: STORE8 | B10: Bean, Jones and Park | C10: West | D10: Thompsonborough | E10: Online
A11: STORE9 | B11: Moore, Padilla and Butler | C11: South | D11: East Johnstad | E11: Flagship
A12: STORE10 | B12: Hill, Wagner and Ballard | C12: East | D12: East Davidville | E12: Online
... A21: STORE19 | B21: Mann-Austin | C21: East | D21: Vasquezborough | E21: Online

Sheet Sales_Fact
A1: Sales_ID | B1: Order_Date | C1: Customer_ID | D1: Product_ID | E1: Store_ID | F1: Quantity | G1: Unit_Price | H1: Discount | I1: Payment_Type | J1: Total_Amount
A2: SALE0 | B2: 45480 | C2: CUST1409 | D2: PROD97 | E2: STORE3 | F2: 1 | G2: 218.04 | H2: 0.09 | I2: Credit Card | J2: 198.4164
A3: SALE1 | B3: 45285 | C3: CUST1467 | D3: PROD74 | E3: STORE17 | F3: 3 | G3: 104.47 | H3: 0.27 | I3: PayPal | J3: 228.7893
A4: SALE2 | B4: 45446 | C4: CUST1056 | D4: PROD49 | E4: STORE8 | F4: 4 | G4: 914.05 | H4: 0.25 | I4: Credit Card | J4: 2742.15
A5: SALE3 | B5: 45259 | C5: CUST1346 | D5: PROD76 | E5: STORE8 | F5: 1 | G5: 921.51 | H5: 0.16 | I5: COD | J5: 774.0684
A6: SALE4 | B6: 45297 | C6: CUST1493 | D6: PROD59 | E6: STORE5 | F6: 3 | G6: 745.3 | H6: 0.18 | I6: Credit Card | J6: 1833.438
A7: SALE5 | B7: 45499 | C7: CUST1116 | D7: PROD15 | E7: STORE7 | F7: 3 | G7: 147.01 | H7: 0.19 | I7: COD | J7: 357.2343
A8: SALE6 | B8: 45850 | C8: CUST1016 | D8: PROD56 | E8: STORE4 | F8: 2 | G8: 785.31 | H8: 0.15 | I8: PayPal | J8: 1335.027
A9: SALE7 | B9: 45248 | C9: CUST1152 | D9: PROD70 | E9: STORE8 | F9: 4 | G9: 342.39 | H9: 0.23 | I9: PayPal | J9: 1054.5612
A10: SALE8 | B10: 45781 | C10: CUST1187 | D10: PROD99 | E10: STORE5 | G10: 448.25 | H10: 0.07 | I10: PayPal | J10: 1250.6175
A11: SALE9 | B11: 45869 | C11: CUST1464 | D11: PROD33 | E11: STORE0 | F11: 2 | G11: 873.17 | H11: 0.23 | I11: PayPal | J11: 1344.6818
A12: SALE10 | B12: 45335 | C12: CUST1065 | D12: PROD24 | E12: STORE14 | F12: 1 | G12: 278.63 | H12: 0.07 | I12: Credit Card | J12: 259.1259
A13: SALE11 | B13: 45801 | C13: CUST1320 | D13: PROD39 | E13: STORE1 | F13: 4 | G13: 286.92 | H13: 0.17 | I13: Credit Card | J13: 952.5744
A14: SALE12 | B14: 45528 | C14: CUST1237 | D14: PROD88 | E14: STORE4 | F14: 4 | G14: 644.58 | H14: 0.01 | I14: Credit Card | J14: 2552.5368
A15: SALE13 | B15: 45875 | C15: CUST1443 | D15: PROD34 | E15: STORE16 | F15: 2 | G15: 316.9 | H15: 0.3 | I15: PayPal | J15: 443.66
A16: SALE14 | B16: 45829 | C16: CUST1348 | D16: PROD24 | E16: STORE15 | F16: 4 | G16: 403.47 | H16: 0.29 | I16: PayPal | J16: 1145.8548
A17: SALE15 | B17: 45636 | C17: CUST1435 | D17: PROD36 | E17: STORE9 | G17: 871.34 | H17: 0.04 | I17: COD | J17: 2509.4592
A18: SALE16 | B18: 45913 | C18: CUST1276 | D18: PROD65 | E18: STORE19 | F18: 2 | G18: 451.98 | H18: 0.25 | I18: Credit Card | J18: 677.97
A19: SALE17 | B19: 45637 | C19: CUST1079 | D19: PROD27 | E19: STORE4 | F19: 2 | G19: 502.69 | H19: 0.23 | I19: Credit Card | J19: 774.1426
A20: SALE18 | B20: 45517 | C20: CUST1094 | D20: PROD39 | E20: STORE4 | F20: 2 | G20: 559.23 | H20: 0.25 | I20: COD | J20: 838.845
A21: SALE19 | B21: 45369 | C21: CUST1239 | D21: PROD60 | E21: STORE13 | F21: 4 | H21: 0.04 | I21: COD | J21: 1782.4512
A22: SALE20 | B22: 45843 | C22: CUST1144 | D22: PROD72 | E22: STORE17 | F22: 3 | G22: 986.04 | H22: 0.27 | I22: COD | J22: 2159.4276
A23: SALE21 | B23: 45447 | C23: CUST1396 | D23: PROD43 | E23: STORE18 | F23: 1 | G23: 589.56 | H23: 0.22 | I23: Credit Card | J23: 459.8568
A24: SALE22 | B24: 45394 | C24: CUST1476 | D24: PROD69 | E24: STORE10 | F24: 3 | G24: 979.42 | H24: 0.03 | I24: PayPal | J24: 2850.1122
A25: SALE23 | B25: 45466 | C25: CUST1368 | D25: PROD12 | E25: STORE8 | F25: 1 | G25: 719.28 | H25: 0.08 | I25: Credit Card | J25: 661.7376
A26: SALE24 | B26: 45908 | C26: CUST1186 | D26: PROD67 | E26: STORE6 | F26: 3 | G26: 77.6 | H26: 0.07 | I26: Credit Card | J26: 216.504
A27: SALE25 | B27: 45552 | C27: CUST1381 | D27: PROD5 | E27: STORE3 | F27: 4 | G27: 852.71 | H27: 0.14 | I27: PayPal | J27: 2933.3224
A28: SALE26 | B28: 45294 | C28: CUST1213 | D28: PROD98 | E28: STORE8 | F28: 4 | G28: 156.16 | I28: Credit Card | J28: 599.6544
A29: SALE27 | B29: 45710 | C29: CUST1200 | D29: PROD77 | E29: STORE8 | F29: 3 | G29: 815.49 | H29: 0.17 | I29: Credit Card | J29: 2030.5701
A30: SALE28 | B30: 45923 | C30: CUST1148 | D30: PROD13 | E30: STORE2 | F30: 2 | G30: 74.21 | H30: 0.11 | I30: PayPal | J30: 132.0938
A31: SALE29 | B31: 45302 | C31: CUST1348 | D31: PROD99 | E31: STORE3 | G31: 451.67 | H31: 0.15 | I31: Credit Card | J31: 1535.678
A32: SALE30 | B32: 45217 | C32: CUST1028 | D32: PROD5 | E32: STORE19 | F32: 1 | G32: 429.38 | H32: 0.13 | I32: PayPal | J32: 373.5606
A33: SALE31 | B33: 45593 | C33: CUST1412 | D33: PROD53 | E33: STORE12 | F33: 2 | G33: 148.96 | H33: 0.03 | I33: COD | J33: 288.9824
A34: SALE32 | B34: 45597 | C34: CUST1398 | D34: PROD75 | E34: STORE8 | F34: 4 | G34: 313.83 | H34: 0.08 | I34: Credit Card | J34: 1154.8944
A35: SALE33 | B35: 45620 | C35: CUST1453 | D35: PROD12 | E35: STORE6 | F35: 2 | G35: 717.31 | H35: 0.15 | I35: Credit Card | J35: 1219.427
A36: SALE34 | B36: 45215 | C36: CUST1344 | D36: PROD79 | E36: STORE1 | G36: 873.22 | H36: 0.18 | I36: Credit Card | J36: 2148.1212
A37: SALE35 | B37: 45878 | C37: CUST1218 | D37: PROD16 | E37: STORE3 | F37: 4 | G37: 109.36 | H37: 0.19 | I37: COD | J37: 354.3264
A38: SALE36 | B38: 45635 | C38: CUST1086 | D38: PROD5 | E38: STORE7 | F38: 3 | G38: 559.52 | H38: 0.16 | I38: PayPal | J38: 1409.9904
A39: SALE37 | B39: 45329 | C39: CUST1492 | D39: PROD10 | E39: STORE17 | F39: 3 | G39: 121.76 | H39: 0.27 | I39: PayPal | J39: 266.6544
A40: SALE38 | B40: 45378 | C40: CUST1189 | D40: PROD33 | E40: STORE13 | F40: 4 | G40: 735.32 | H40: 0.06 | I40: COD | J40: 2764.8032
A41: SALE39 | B41: 45264 | C41: CUST1431 | D41: PROD94 | E41: STORE3 | F41: 2 | G41: 600.73 | H41: 0.08 | I41: Credit Card | J41: 1105.3432
A42: SALE40 | B42: 45486 | C42: CUST1072 | D42: PROD26 | E42: STORE19 | F42: 2 | G42: 873.86 | H42: 0.07 | I42: COD | J42: 1625.3796
A43: SALE41 | B43: 45241 | C43: CUST1302 | D43: PROD23 | E43: STORE8 | F43: 3 | G43: 342.47 | H43: 0.08 | I43: PayPal | J43: 945.2172
A44: SALE42 | B44: 45649 | C44: CUST1335 | D44: PROD29 | E44: STORE9 | F44: 2 | G44: 915.15 | H44: 0.16 | I44: PayPal | J44: 1537.452
A45: SALE43 | B45: 45677 | C45: CUST1084 | D45: PROD33 | E45: STORE17 | G45: 863.11 | H45: 0.28 | I45: PayPal | J45: 1864.3176
A46: SALE44 | B46: 45538 | C46: CUST1203 | D46: PROD43 | E46: STORE12 | F46: 2 | G46: 209.32 | H46: 0.23 | I46: COD | J46: 322.3528
A47: SALE45 | B47: 45606 | C47: CUST1470 | D47: PROD59 | E47: STORE8 | F47: 4 | G47: 288.6 | H47: 0.09 | I47: PayPal | J47: 1050.504
A48: SALE46 | B48: 45570 | C48: CUST1070 | D48: PROD78 | E48: STORE16 | F48: 1 | G48: 418.69 | H48: 0.06 | I48: PayPal | J48: 393.5686
A49: SALE47 | B49: 45466 | C49: CUST1008 | D49: PROD30 | E49: STORE11 | F49: 1 | G49: 135.78 | H49: 0.14 | I49: PayPal | J49: 116.7708
A50: SALE48 | B50: 45218 | C50: CUST1203 | D50: PROD44 | E50: STORE17 | F50: 1 | G50: 517.13 | H50: 0.28 | I50: Credit Card | J50: 372.3336
A51: SALE49 | B51: 45607 | C51: CUST1420 | D51: PROD21 | E51: STORE16 | F51: 2 | G51: 384.66 | H51: 0.08 | I51: COD | J51: 707.7744
A52: SALE50 | B52: 45291 | C52: CUST1070 | D52: PROD52 | E52: STORE9 | F52: 3 | G52: 83.7 | H52: 0.24 | I52: PayPal | J52: 190.836
A53: SALE51 | B53: 45689 | C53: CUST1142 | D53: PROD69 | E53: STORE7 | F53: 3 | G53: 76.57 | H53: 0.26 | I53: Credit Card | J53: 169.9854
A54: SALE52 | B54: 45894 | C54: CUST1148 | D54: PROD89 | E54: STORE6 | F54: 3 | I54: Credit Card | J54: 486.0633
A55: SALE53 | B55: 45677 | C55: CUST1324 | D55: PROD20 | E55: STORE8 | F55: 1 | G55: 900.35 | H55: 0.13 | I55: COD | J55: 783.3045
A56: SALE54 | B56: 45706 | C56: CUST1095 | D56: PROD40 | E56: STORE10 | F56: 4 | G56: 428.09 | H56: 0.07 | I56: Credit Card | J56: 1592.4948
A57: SALE55 | B57: 45589 | C57: CUST1416 | D57: PROD49 | E57: STORE11 | F57: 2 | G57: 559.71 | H57: 0.3 | I57: COD | J57: 783.594
A58: SALE56 | B58: 45282 | C58: CUST1080 | D58: PROD34 | E58: STORE6 | F58: 2 | G58: 833.7 | H58: 0.06 | I58: PayPal | J58: 1567.356
A59: SALE57 | B59: 45462 | C59: CUST1467 | D59: PROD47 | E59: STORE14 | F59: 2 | G59: 680.16 | H59: 0.28 | I59: Credit Card | J59: 979.4304
A60: SALE58 | B60: 45633 | C60: CUST1404 | D60: PROD15 | E60: STORE7 | F60: 4 | G60: 733.42 | I60: PayPal | J60: 2552.3016
A61: SALE59 | B61: 45257 | C61: CUST1367 | D61: PROD89 | E61: STORE11 | F61: 1 | G61: 996.33 | H61: 0.23 | I61: PayPal | J61: 767.1741
A62: SALE60 | B62: 45854 | C62: CUST1408 | D62: PROD31 | E62: STORE10 | F62: 1 | G62: 198.83 | H62: 0.09 | I62: COD | J62: 180.9353
A63: SALE61 | B63: 45716 | C63: CUST1239 | D63: PROD19 | E63: STORE7 | F63: 1 | G63: 374.92 | H63: 0.18 | I63: PayPal | J63: 307.4344
A64: SALE62 | B64: 45515 | C64: CUST1464 | D64: PROD93 | E64: STORE16 | F64: 1 | G64: 468.94 | H64: 0.12 | I64: Credit Card | J64: 412.6672
A65: SALE63 | B65: 45927 | C65: CUST1126 | D65: PROD89 | E65: STORE12 | F65: 2 | G65: 121.37 | H65: 0.05 | I65: Credit Card | J65: 230.603
A66: SALE64 | B66: 45914 | C66: CUST1255 | D66: PROD53 | E66: STORE10 | F66: 3 | G66: 480.06 | H66: 0.01 | I66: Credit Card
A67: SALE65 | B67: 45290 | C67: CUST1162 | D67: PROD99 | E67: STORE17 | F67: 2 | G67: 856.57 | H67: 0.24 | I67: Credit Card | J67: 1301.9864
A68: SALE66 | B68: 45213 | C68: CUST1269 | D68: PROD77 | E68: STORE2 | F68: 4 | G68: 814.25 | H68: 0.18 | I68: Credit Card | J68: 2670.74
A69: SALE67 | B69: 45255 | C69: CUST1483 | D69: PROD12 | E69: STORE2 | F69: 1 | G69: 989.17 | H69: 0.2 | I69: PayPal | J69: 791.336
A70: SALE68 | B70: 45270 | C70: CUST1372 | D70: PROD72 | E70: STORE10 | F70: 4 | G70: 62.48 | H70: 0.18 | I70: Credit Card | J70: 204.9344
A71: SALE69 | B71: 45897 | C71: CUST1423 | D71: PROD13 | E71: STORE16 | F71: 4 | G71: 561.24 | H71: 0.24 | I71: Credit Card | J71: 1706.1696
A72: SALE70 | B72: 45849 | C72: CUST1058 | D72: PROD60 | E72: STORE5 | F72: 3 | G72: 92.24 | H72: 0.28 | I72: COD
A73: SALE71 | B73: 45889 | C73: CUST1168 | D73: PROD72 | E73: STORE1 | F73: 2 | G73: 668.3 | H73: 0.07 | I73: Credit Card | J73: 1243.038
A74: SALE72 | B74: 45533 | C74: CUST1409 | D74: PROD38 | E74: STORE5 | F74: 1 | G74: 553.82 | H74: 0.09 | I74: Credit Card | J74: 503.9762
A75: SALE73 | B75: 45626 | C75: CUST1037 | D75: PROD45 | E75: STORE11 | F75: 2 | G75: 556.43 | H75: 0.13 | I75: Credit Card | J75: 968.1882
A76: SALE74 | B76: 45942 | C76: CUST1273 | D76: PROD20 | E76: STORE8 | F76: 1 | G76: 184.98 | H76: 0.1 | I76: COD | J76: 166.482
A77: SALE75 | B77: 45500 | C77: CUST1035 | D77: PROD97 | E77: STORE12 | F77: 4 | G77: 700.18 | H77: 0.23 | I77: Credit Card | J77: 2156.5544
A78: SALE76 | B78: 45285 | C78: CUST1019 | D78: PROD76 | E78: STORE10 | F78: 2 | G78: 686.31 | H78: 0.25 | I78: Credit Card | J78: 1029.465
A79: SALE77 | B79: 45800 | C79: CUST1007 | D79: PROD67 | E79: STORE15 | F79: 1 | G79: 687.82 | H79: 0.27 | I79: COD | J79: 502.1086
A80: SALE78 | B80: 45609 | C80: CUST1221 | D80: PROD83 | E80: STORE8 | F80: 2 | G80: 900.55 | H80: 0.16 | I80: Credit Card | J80: 1512.924
A81: SALE79 | B81: 45268 | C81: CUST1115 | D81: PROD21 | E81: STORE2 | F81: 1 | G81: 341.17 | H81: 0.15 | I81: Credit Card | J81: 289.9945
A82: SALE80 | B82: 45885 | C82: CUST1176 | D82: PROD52 | E82: STORE8 | F82: 1 | G82: 442.27 | H82: 0.06 | I82: COD | J82: 415.7338
A83: SALE81 | B83: 45616 | C83: CUST1253 | D83: PROD71 | E83: STORE9 | F83: 1 | G83: 363.73 | H83: 0.25 | I83: PayPal | J83: 272.7975
A84: SALE82 | B84: 45518 | C84: CUST1378 | D84: PROD91 | E84: STORE17 | F84: 2 | G84: 601.33 | H84: 0.16 | I84: PayPal | J84: 1010.2344
A85: SALE83 | B85: 45427 | C85: CUST1403 | D85: PROD17 | E85: STORE18 | F85: 4 | G85: 34.39 | H85: 0.03 | I85: PayPal | J85: 133.4332
A86: SALE84 | B86: 45268 | C86: CUST1423 | D86: PROD46 | E86: STORE17 | F86: 1 | G86: 773.57 | H86: 0.05 | I86: COD
A87: SALE85 | B87: 45282 | C87: CUST1054 | D87: PROD88 | E87: STORE7 | F87: 4 | G87: 127.1 | H87: 0.24 | I87: COD | J87: 386.384
A88: SALE86 | B88: 45545 | C88: CUST1303 | D88: PROD20 | E88: STORE3 | F88: 3 | G88: 899.58 | H88: 0.28 | I88: PayPal | J88: 1943.0928
A89: SALE87 | B89: 45755 | C89: CUST1327 | D89: PROD1 | E89: STORE10 | F89: 3 | G89: 964.39 | H89: 0.04 | I89: Credit Card | J89: 2777.4432
A90: SALE88 | B90: 45588 | C90: CUST1183 | D90: PROD38 | E90: STORE0 | F90: 2 | G90: 217.83 | H90: 0.14 | I90: PayPal | J90: 374.6676
A91: SALE89 | B91: 45848 | C91: CUST1143 | D91: PROD17 | E91: STORE1 | F91: 4 | G91: 187.71 | H91: 0.06 | I91: COD | J91: 705.7896
A92: SALE90 | B92: 45577 | C92: CUST1010 | D92: PROD33 | E92: STORE18 | F92: 2 | G92: 350.12 | H92: 0.12 | I92: COD | J92: 616.2112
A93: SALE91 | B93: 45312 | C93: CUST1406 | D93: PROD16 | E93: STORE1 | F93: 4 | G93: 102.19 | H93: 0.17 | I93: PayPal | J93: 339.2708
A94: SALE92 | B94: 45350 | C94: CUST1007 | D94: PROD86 | E94: STORE4 | F94: 1 | G94: 696.53 | H94: 0.17 | I94: Credit Card | J94: 578.1199
A95: SALE93 | B95: 45657 | C95: CUST1065 | D95: PROD19 | E95: STORE4 | F95: 2 | G95: 327.52 | H95: 0.15 | I95: PayPal | J95: 556.784
A96: SALE94 | B96: 45530 | C96: CUST1298 | D96: PROD97 | E96: STORE19 | F96: 2 | G96: 569.36 | H96: 0.01 | I96: PayPal
A97: SALE95 | B97: 45556 | C97: CUST1321 | D97: PROD99 | E97: STORE6 | F97: 2 | G97: 68.29 | H97: 0.14 | I97: COD | J97: 117.4588
A98: SALE96 | B98: 45523 | C98: CUST1244 | D98: PROD50 | E98: STORE10 | F98: 1 | G98: 842.9 | H98: 0.06 | I98: COD | J98: 792.326
A99: SALE97 | B99: 45587 | C99: CUST1287 | D99: PROD3 | E99: STORE3 | F99: 3 | G99: 751.94 | H99: 0.26 | I99: PayPal | J99: 1669.3068
A100: SALE98 | B100: 45580 | C100: CUST1131 | D100: PROD56 | E100: STORE7 | F100: 4 | G100: 476.28 | H100: 0.17 | I100: Credit Card | J100: 1581.2496
...

Sheet Sales Analysis Table 1
A1: Sales_ID | B1: Order_Date | C1: Month | D1: Year | E1: Customer_ID | F1: Customer_Age | G1: Age Range | H1: Gender | I1: Loyalty_Level | J1: City | K1: State | L1: Region | M1: Product_ID | N1: Product_Category | O1: Product_SubCategory | P1: Brand | Q1: Store_ID | R1: Store_Name | S1: Store_Type | T1: Quantity | U1: Unit_Price | V1: Discount | W1: Stock | X1: Payment_Type | Y1: Total_Amount | Z1: Product
A2: SALE0 | B2: 45480 | C2: July | D2: =YEAR(B2) -> 2024 | E2: CUST1409 | F2: 55 | G2: =IF(F2<18,"Under 18", IF(F2<=25,"18-25", IF(F2<=35,"26-35", IF(F2<=45,"36-45", IF(F2<=55,"46-55", IF(F2<=65,"56-65","65+")))))) -> 46-55 | H2: {=XLOOKUP(E2,Customer_Dim!A:A,Customer_Dim!D:D)} -> Male | I2: {=XLOOKUP(E2,Customer_Dim!A:A,Customer_Dim!H:H)} -> Gold | J2: {=XLOOKUP(E2,Customer_Dim!A:A,Customer_Dim!E:E)} -> Kathleenport | K2: {=XLOOKUP(E2,Customer_Dim!A:A,Customer_Dim!F:F)} -> Wyoming | L2: {=XLOOKUP(Q2,Store_Dim!A:A,Store_Dim!C:C)} -> North | M2: PROD97 | N2: {=XLOOKUP(M2,Product_Dim!A:A,Product_Dim!C:C)} -> Sports | O2: {=XLOOKUP(M2,Product_Dim!A:A,Product_Dim!D:D)} -> Team Sports | P2: Khan LLC | Q2: STORE3 | R2: {=XLOOKUP(Q2,Store_Dim!A:A,Store_Dim!B:B)} -> Johnson-Wright | S2: {=XLOOKUP(Q2,Store_Dim!A:A,Store_Dim!E:E)} -> Outlet | T2: 1 | U2: 218.04 | V2: 0.09 | W2: 471 | X2: Credit Card | Y2: 198.4164 | Z2: {=XLOOKUP(M2,Product_Dim!A:A,Product_Dim!B:B)} -> Cricket Bat
A3: SALE1 | B3: 45285 | C3: December | D3: =YEAR(B3) -> 2023 | E3: CUST1467 | F3: 63 | G3: =IF(F3<18,"Under 18", IF(F3<=25,"18-25", IF(F3<=35,"26-35", IF(F3<=45,"36-45", IF(F3<=55,"46-55", IF(F3<=65,"56-65","65+")))))) -> 56-65 | H3: {=XLOOKUP(E3,Customer_Dim!A:A,Customer_Dim!D:D)} -> Female | I3: {=XLOOKUP(E3,Customer_Dim!A:A,Customer_Dim!H:H)} -> Gold | J3: {=XLOOKUP(E3,Customer_Dim!A:A,Customer_Dim!E:E)} -> Oneillfurt | K3: {=XLOOKUP(E3,Customer_Dim!A:A,Customer_Dim!F:F)} -> Vermont | L3: {=XLOOKUP(Q3,Store_Dim!A:A,Store_Dim!C:C)} -> North | M3: PROD74 | N3: {=XLOOKUP(M3,Product_Dim!A:A,Product_Dim!C:C)} -> Electronics | O3: {=XLOOKUP(M3,Product_Dim!A:A,Product_Dim!D:D)} -> Audio | P3: Bruce-Bowen | Q3: STORE17 | R3: {=XLOOKUP(Q3,Store_Dim!A:A,Store_Dim!B:B)} -> Holloway Ltd | S3: {=XLOOKUP(Q3,Store_Dim!A:A,Store_Dim!E:E)} -> Flagship | T3: 3 | U3: 104.47 | V3: 0.27 | W3: 159 | X3: PayPal | Y3: 228.7893 | Z3: {=XLOOKUP(M3,Product_Dim!A:A,Product_Dim!B:B)} -> Bluetooth Car Audio System
A4: SALE2 | B4: 45446 | C4: June | D4: =YEAR(B4) -> 2024 | E4: CUST1056 | F4: 49 | G4: =IF(F4<18,"Under 18", IF(F4<=25,"18-25", IF(F4<=35,"26-35", IF(F4<=45,"36-45", IF(F4<=55,"46-55", IF(F4<=65,"56-65","65+")))))) -> 46-55 | H4: {=XLOOKUP(E4,Customer_Dim!A:A,Customer_Dim!D:D)} -> Female | I4: {=XLOOKUP(E4,Customer_Dim!A:A,Customer_Dim!H:H)} -> Gold | J4: {=XLOOKUP(E4,Customer_Dim!A:A,Customer_Dim!E:E)} -> Deborahberg | K4: {=XLOOKUP(E4,Customer_Dim!A:A,Customer_Dim!F:F)} -> Pennsylvania | L4: {=XLOOKUP(Q4,Store_Dim!A:A,Store_Dim!C:C)} -> West | M4: PROD49 | N4: {=XLOOKUP(M4,Product_Dim!A:A,Product_Dim!C:C)} -> Beauty | O4: {=XLOOKUP(M4,Product_Dim!A:A,Product_Dim!D:D)} -> Fragrance | P4: Sullivan and Sons | Q4: STORE8 | R4: {=XLOOKUP(Q4,Store_Dim!A:A,Store_Dim!B:B)} -> Bean, Jones and Park | S4: {=XLOOKUP(Q4,Store_Dim!A:A,Store_Dim!E:E)} -> Online | T4: 4 | U4: 914.05 | V4: 0.25 | W4: 267 | X4: Credit Card | Y4: 2742.15 | Z4: {=XLOOKUP(M4,Product_Dim!A:A,Product_Dim!B:B)} -> Men's Roll-On Perfume
A5: SALE3 | B5: 45259 | C5: November | D5: =YEAR(B5) -> 2023 | E5: CUST1346 | F5: 58 | G5: =IF(F5<18,"Under 18", IF(F5<=25,"18-25", IF(F5<=35,"26-35", IF(F5<=45,"36-45", IF(F5<=55,"46-55", IF(F5<=65,"56-65","65+")))))) -> 56-65 | H5: {=XLOOKUP(E5,Customer_Dim!A:A,Customer_Dim!D:D)} -> Female | I5: {=XLOOKUP(E5,Customer_Dim!A:A,Customer_Dim!H:H)} -> Platinum | J5: {=XLOOKUP(E5,Customer_Dim!A:A,Customer_Dim!E:E)} -> Port Crystalberg | K5: {=XLOOKUP(E5,Customer_Dim!A:A,Customer_Dim!F:F)} -> Tennessee | L5: {=XLOOKUP(Q5,Store_Dim!A:A,Store_Dim!C:C)} -> West | M5: PROD76 | N5: {=XLOOKUP(M5,Product_Dim!A:A,Product_Dim!C:C)} -> Electronics | O5: {=XLOOKUP(M5,Product_Dim!A:A,Product_Dim!D:D)} -> Computer | P5: Larson Ltd | Q5: STORE8 | R5: {=XLOOKUP(Q5,Store_Dim!A:A,Store_Dim!B:B)} -> Bean, Jones and Park | S5: {=XLOOKUP(Q5,Store_Dim!A:A,Store_Dim!E:E)} -> Online | T5: 1 | U5: 921.51 | V5: 0.16 | W5: 320 | X5: COD | Y5: 774.0684 | Z5: {=XLOOKUP(M5,Product_Dim!A:A,Product_Dim!B:B)} -> Wireless Mouse
A6: SALE4 | B6: 45297 | C6: January | D6: =YEAR(B6) -> 2024 | E6: CUST1493 | F6: 28 | G6: =IF(F6<18,"Under 18", IF(F6<=25,"18-25", IF(F6<=35,"26-35", IF(F6<=45,"36-45", IF(F6<=55,"46-55", IF(F6<=65,"56-65","65+")))))) -> 26-35 | H6: {=XLOOKUP(E6,Customer_Dim!A:A,Customer_Dim!D:D)} -> Male | I6: {=XLOOKUP(E6,Customer_Dim!A:A,Customer_Dim!H:H)} -> Silver | J6: {=XLOOKUP(E6,Customer_Dim!A:A,Customer_Dim!E:E)} -> South William | K6: {=XLOOKUP(E6,Customer_Dim!A:A,Customer_Dim!F:F)} -> Alabama | L6: {=XLOOKUP(Q6,Store_Dim!A:A,Store_Dim!C:C)} -> North | M6: PROD59 | N6: {=XLOOKUP(M6,Product_Dim!A:A,Product_Dim!C:C)} -> Beauty | O6: {=XLOOKUP(M6,Product_Dim!A:A,Product_Dim!D:D)} -> Haircare | P6: Cline-Mccarthy | Q6: STORE5 | R6: {=XLOOKUP(Q6,Store_Dim!A:A,Store_Dim!B:B)} -> Gray Ltd | S6: {=XLOOKUP(Q6,Store_Dim!A:A,Store_Dim!E:E)} -> Outlet | T6: 3 | U6: 745.3 | V6: 0.18 | W6: 399 | X6: Credit Card | Y6: 1833.438 | Z6: {=XLOOKUP(M6,Product_Dim!A:A,Product_Dim!B:B)} -> Men's Hair Styling Gel
A7: SALE5 | B7: 45499 | C7: July | D7: =YEAR(B7) -> 2024 | E7: CUST1116 | F7: 18 | G7: =IF(F7<18,"Under 18", IF(F7<=25,"18-25", IF(F7<=35,"26-35", IF(F7<=45,"36-45", IF(F7<=55,"46-55", IF(F7<=65,"56-65","65+")))))) -> 18-25 | H7: {=XLOOKUP(E7,Customer_Dim!A:A,Customer_Dim!D:D)} -> Female | I7: {=XLOOKUP(E7,Customer_Dim!A:A,Customer_Dim!H:H)} -> Platinum | J7: {=XLOOKUP(E7,Customer_Dim!A:A,Customer_Dim!E:E)} -> North Davidport | K7: {=XLOOKUP(E7,Customer_Dim!A:A,Customer_Dim!F:F)} -> Rhode Island | L7: {=XLOOKUP(Q7,Store_Dim!A:A,Store_Dim!C:C)} -> South | M7: PROD15 | N7: {=XLOOKUP(M7,Product_Dim!A:A,Product_Dim!C:C)} -> Electronics | O7: {=XLOOKUP(M7,Product_Dim!A:A,Product_Dim!D:D)} -> Appliances | P7: Thomas LLC | Q7: STORE7 | R7: {=XLOOKUP(Q7,Store_Dim!A:A,Store_Dim!B:B)} -> Martinez-Mullins | S7: {=XLOOKUP(Q7,Store_Dim!A:A,Store_Dim!E:E)} -> Online | T7: 3 | U7: 147.01 | V7: 0.19 | W7: 301 | X7: COD | Y7: 357.2343 | Z7: {=XLOOKUP(M7,Product_Dim!A:A,Product_Dim!B:B)} -> 4K Home Projector
A8: SALE6 | B8: 45850 | C8: July | D8: =YEAR(B8) -> 2025 | E8: CUST1016 | F8: 24 | G8: =IF(F8<18,"Under 18", IF(F8<=25,"18-25", IF(F8<=35,"26-35", IF(F8<=45,"36-45", IF(F8<=55,"46-55", IF(F8<=65,"56-65","65+")))))) -> 18-25 | H8: {=XLOOKUP(E8,Customer_Dim!A:A,Customer_Dim!D:D)} -> Female | I8: {=XLOOKUP(E8,Customer_Dim!A:A,Customer_Dim!H:H)} -> Bronze | J8: {=XLOOKUP(E8,Customer_Dim!A:A,Customer_Dim!E:E)} -> South Christopher | K8: {=XLOOKUP(E8,Customer_Dim!A:A,Customer_Dim!F:F)} -> Pennsylvania | L8: {=XLOOKUP(Q8,Store_Dim!A:A,Store_Dim!C:C)} -> South | M8: PROD56 | N8: {=XLOOKUP(M8,Product_Dim!A:A,Product_Dim!C:C)} -> Home | O8: {=XLOOKUP(M8,Product_Dim!A:A,Product_Dim!D:D)} -> Decor | P8: Hernandez, Kennedy and Porter | Q8: STORE4 | R8: {=XLOOKUP(Q8,Store_Dim!A:A,Store_Dim!B:B)} -> Alexander Group | S8: {=XLOOKUP(Q8,Store_Dim!A:A,Store_Dim!E:E)} -> Online | T8: 2 | U8: 785.31 | V8: 0.15 | W8: 190 | X8: PayPal | Y8: 1335.027 | Z8: {=XLOOKUP(M8,Product_Dim!A:A,Product_Dim!B:B)} -> Premium Blanket Throw
A9: SALE7 | B9: 45248 | C9: November | D9: =YEAR(B9) -> 2023 | E9: CUST1152 | F9: 41 | G9: =IF(F9<18,"Under 18", IF(F9<=25,"18-25", IF(F9<=35,"26-35", IF(F9<=45,"36-45", IF(F9<=55,"46-55", IF(F9<=65,"56-65","65+")))))) -> 36-45 | H9: {=XLOOKUP(E9,Customer_Dim!A:A,Customer_Dim!D:D)} -> Female | I9: {=XLOOKUP(E9,Customer_Dim!A:A,Customer_Dim!H:H)} -> Platinum | J9: {=XLOOKUP(E9,Customer_Dim!A:A,Customer_Dim!E:E)} -> Jaredville | K9: {=XLOOKUP(E9,Customer_Dim!A:A,Customer_Dim!F:F)} -> Missouri | L9: {=XLOOKUP(Q9,Store_Dim!A:A,Store_Dim!C:C)} -> West | M9: PROD70 | N9: {=XLOOKUP(M9,Product_Dim!A:A,Product_Dim!C:C)} -> Home | O9: {=XLOOKUP(M9,Product_Dim!A:A,Product_Dim!D:D)} -> Storage | P9: Duran Group | Q9: STORE8 | R9: {=XLOOKUP(Q9,Store_Dim!A:A,Store_Dim!B:B)} -> Bean, Jones and Park | S9: {=XLOOKUP(Q9,Store_Dim!A:A,Store_Dim!E:E)} -> Online | T9: 4 | U9: 342.39 | V9: 0.23 | W9: 89 | X9: PayPal | Y9: 1054.5612 | Z9: {=XLOOKUP(M9,Product_Dim!A:A,Product_Dim!B:B)} -> Kitchen Storage Rack
A10: SALE8 | B10: 45781 | C10: May | D10: =YEAR(B10) -> 2025 | E10: CUST1187 | F10: 60 | G10: =IF(F10<18,"Under 18", IF(F10<=25,"18-25", IF(F10<=35,"26-35", IF(F10<=45,"36-45", IF(F10<=55,"46-55", IF(F10<=65,"56-65","65+")))))) -> 56-65 | H10: {=XLOOKUP(E10,Customer_Dim!A:A,Customer_Dim!D:D)} -> Female | I10: {=XLOOKUP(E10,Customer_Dim!A:A,Customer_Dim!H:H)} -> Platinum | J10: {=XLOOKUP(E10,Customer_Dim!A:A,Customer_Dim!E:E)} -> Lake Blaketon | K10: {=XLOOKUP(E10,Customer_Dim!A:A,Customer_Dim!F:F)} -> Alabama | L10: {=XLOOKUP(Q10,Store_Dim!A:A,Store_Dim!C:C)} -> North | M10: PROD99 | N10: {=XLOOKUP(M10,Product_Dim!A:A,Product_Dim!C:C)} -> Home | O10: {=XLOOKUP(M10,Product_Dim!A:A,Product_Dim!D:D)} -> Kitchen | P10: Campbell Ltd | Q10: STORE5 | R10: {=XLOOKUP(Q10,Store_Dim!A:A,Store_Dim!B:B)} -> Gray Ltd | S10: {=XLOOKUP(Q10,Store_Dim!A:A,Store_Dim!E:E)} -> Outlet | T10: =Y10/(U10*(1-V10)) -> 3 | U10: 448.25 | V10: 0.07 | W10: 146 | X10: PayPal | Y10: 1250.6175 | Z10: {=XLOOKUP(M10,Product_Dim!A:A,Product_Dim!B:B)} -> Stainless Steel Cookware Set
A11: SALE9 | B11: 45869 | C11: July | D11: =YEAR(B11) -> 2025 | E11: CUST1464 | F11: 41.576845 | G11: =IF(F11<18,"Under 18", IF(F11<=25,"18-25", IF(F11<=35,"26-35", IF(F11<=45,"36-45", IF(F11<=55,"46-55", IF(F11<=65,"56-65","65+")))))) -> 36-45 | H11: {=XLOOKUP(E11,Customer_Dim!A:A,Customer_Dim!D:D)} -> Female | I11: {=XLOOKUP(E11,Customer_Dim!A:A,Customer_Dim!H:H)} -> Platinum | J11: {=XLOOKUP(E11,Customer_Dim!A:A,Customer_Dim!E:E)} -> Grayland | K11: {=XLOOKUP(E11,Customer_Dim!A:A,Customer_Dim!F:F)} -> Washington | L11: {=XLOOKUP(Q11,Store_Dim!A:A,Store_Dim!C:C)} -> East | M11: PROD33 | N11: {=XLOOKUP(M11,Product_Dim!A:A,Product_Dim!C:C)} -> Home | O11: {=XLOOKUP(M11,Product_Dim!A:A,Product_Dim!D:D)} -> Decor | P11: Weiss-Watson | Q11: STORE0 | R11: {=XLOOKUP(Q11,Store_Dim!A:A,Store_Dim!B:B)} -> Rivera-Warner | S11: {=XLOOKUP(Q11,Store_Dim!A:A,Store_Dim!E:E)} -> Flagship | T11: 2 | U11: 873.17 | V11: 0.23 | W11: 305 | X11: PayPal | Y11: 1344.6818 | Z11: {=XLOOKUP(M11,Product_Dim!A:A,Product_Dim!B:B)} -> Modern Wall Clock
A12: SALE10 | B12: 45335 | C12: February | D12: =YEAR(B12) -> 2024 | E12: CUST1065 | F12: 21 | G12: =IF(F12<18,"Under 18", IF(F12<=25,"18-25", IF(F12<=35,"26-35", IF(F12<=45,"36-45", IF(F12<=55,"46-55", IF(F12<=65,"56-65","65+")))))) -> 18-25 | H12: {=XLOOKUP(E12,Customer_Dim!A:A,Customer_Dim!D:D)} -> Female | I12: {=XLOOKUP(E12,Customer_Dim!A:A,Customer_Dim!H:H)} -> Silver | J12: {=XLOOKUP(E12,Customer_Dim!A:A,Customer_Dim!E:E)} -> Woodmouth | K12: {=XLOOKUP(E12,Customer_Dim!A:A,Customer_Dim!F:F)} -> Nevada | L12: {=XLOOKUP(Q12,Store_Dim!A:A,Store_Dim!C:C)} -> South | M12: PROD24 | N12: {=XLOOKUP(M12,Product_Dim!A:A,Product_Dim!C:C)} -> Sports | O12: {=XLOOKUP(M12,Product_Dim!A:A,Product_Dim!D:D)} -> Outdoor | P12: Cook Ltd | Q12: STORE14 | R12: {=XLOOKUP(Q12,Store_Dim!A:A,Store_Dim!B:B)} -> Mcdonald Inc | S12: {=XLOOKUP(Q12,Store_Dim!A:A,Store_Dim!E:E)} -> Outlet | T12: 1 | U12: 278.63 | V12: 0.07 | W12: 340 | X12: Credit Card | Y12: 259.1259 | Z12: {=XLOOKUP(M12,Product_Dim!A:A,Product_Dim!B:B)} -> Foldable Camping Chair
A13: SALE11 | B13: 45801 | C13: May | D13: =YEAR(B13) -> 2025 | E13: CUST1320 | F13: 34 | G13: =IF(F13<18,"Under 18", IF(F13<=25,"18-25", IF(F13<=35,"26-35", IF(F13<=45,"36-45", IF(F13<=55,"46-55", IF(F13<=65,"56-65","65+")))))) -> 26-35 | H13: {=XLOOKUP(E13,Customer_Dim!A:A,Customer_Dim!D:D)} -> Female | I13: {=XLOOKUP(E13,Customer_Dim!A:A,Customer_Dim!H:H)} -> Bronze | J13: {=XLOOKUP(E13,Customer_Dim!A:A,Customer_Dim!E:E)} -> South Darrenland | K13: {=XLOOKUP(E13,Customer_Dim!A:A,Customer_Dim!F:F)} -> Iowa | L13: {=XLOOKUP(Q13,Store_Dim!A:A,Store_Dim!C:C)} -> North | M13: PROD39 | N13: {=XLOOKUP(M13,Product_Dim!A:A,Product_Dim!C:C)} -> Electronics | O13: {=XLOOKUP(M13,Product_Dim!A:A,Product_Dim!D:D)} -> Mobile | P13: Cummings and Sons | Q13: STORE1 | R13: {=XLOOKUP(Q13,Store_Dim!A:A,Store_Dim!B:B)} -> Martinez, Adkins and Johnson | S13: {=XLOOKUP(Q13,Store_Dim!A:A,Store_Dim!E:E)} -> Flagship | T13: 4 | U13: 286.92 | V13: 0.17 | W13: 301 | X13: Credit Card | Y13: 952.5744 | Z13: {=XLOOKUP(M13,Product_Dim!A:A,Product_Dim!B:B)} -> Portable Power Bank
A14: SALE12 | B14: 45528 | C14: August | D14: =YEAR(B14) -> 2024 | E14: CUST1237 | F14: 41 | G14: =IF(F14<18,"Under 18", IF(F14<=25,"18-25", IF(F14<=35,"26-35", IF(F14<=45,"36-45", IF(F14<=55,"46-55", IF(F14<=65,"56-65","65+")))))) -> 36-45 | H14: {=XLOOKUP(E14,Customer_Dim!A:A,Customer_Dim!D:D)} -> Female | I14: {=XLOOKUP(E14,Customer_Dim!A:A,Customer_Dim!H:H)} -> Gold | J14: {=XLOOKUP(E14,Customer_Dim!A:A,Customer_Dim!E:E)} -> Susanstad | K14: {=XLOOKUP(E14,Customer_Dim!A:A,Customer_Dim!F:F)} -> Montana | L14: {=XLOOKUP(Q14,Store_Dim!A:A,Store_Dim!C:C)} -> South | M14: PROD88 | N14: {=XLOOKUP(M14,Product_Dim!A:A,Product_Dim!C:C)} -> Sports | O14: {=XLOOKUP(M14,Product_Dim!A:A,Product_Dim!D:D)} -> Accessories | P14: Olsen-Daniels | Q14: STORE4 | R14: {=XLOOKUP(Q14,Store_Dim!A:A,Store_Dim!B:B)} -> Alexander Group | S14: {=XLOOKUP(Q14,Store_Dim!A:A,Store_Dim!E:E)} -> Online | T14: 4 | U14: 644.58 | V14: 0.01 | W14: 232 | X14: Credit Card | Y14: 2552.5368 | Z14: {=XLOOKUP(M14,Product_Dim!A:A,Product_Dim!B:B)} -> Sports Wrist Sweatbands
A15: SALE13 | B15: 45875 | C15: August | D15: =YEAR(B15) -> 2025 | E15: CUST1443 | F15: 51 | G15: =IF(F15<18,"Under 18", IF(F15<=25,"18-25", IF(F15<=35,"26-35", IF(F15<=45,"36-45", IF(F15<=55,"46-55", IF(F15<=65,"56-65","65+")))))) -> 46-55 | H15: {=XLOOKUP(E15,Customer_Dim!A:A,Customer_Dim!D:D)} -> Male | I15: {=XLOOKUP(E15,Customer_Dim!A:A,Customer_Dim!H:H)} -> Silver | J15: {=XLOOKUP(E15,Customer_Dim!A:A,Customer_Dim!E:E)} -> New Donnabury | K15: {=XLOOKUP(E15,Customer_Dim!A:A,Customer_Dim!F:F)} -> Texas | L15: {=XLOOKUP(Q15,Store_Dim!A:A,Store_Dim!C:C)} -> West | M15: PROD34 | N15: {=XLOOKUP(M15,Product_Dim!A:A,Product_Dim!C:C)} -> Electronics | O15: {=XLOOKUP(M15,Product_Dim!A:A,Product_Dim!D:D)} -> Computer | P15: Lucero LLC | Q15: STORE16 | R15: {=XLOOKUP(Q15,Store_Dim!A:A,Store_Dim!B:B)} -> Frederick-Wright | S15: {=XLOOKUP(Q15,Store_Dim!A:A,Store_Dim!E:E)} -> Flagship | T15: 2 | U15: 316.9 | V15: 0.3 | W15: 86 | X15: PayPal | Y15: 443.66 | Z15: {=XLOOKUP(M15,Product_Dim!A:A,Product_Dim!B:B)} -> Gaming Mechanical Keyboard
A16: SALE14 | B16: 45829 | C16: June | D16: =YEAR(B16) -> 2025 | E16: CUST1348 | F16: 55 | G16: =IF(F16<18,"Under 18", IF(F16<=25,"18-25", IF(F16<=35,"26-35", IF(F16<=45,"36-45", IF(F16<=55,"46-55", IF(F16<=65,"56-65","65+")))))) -> 46-55 | H16: {=XLOOKUP(E16,Customer_Dim!A:A,Customer_Dim!D:D)} -> Male | I16: {=XLOOKUP(E16,Customer_Dim!A:A,Customer_Dim!H:H)} -> Silver | J16: {=XLOOKUP(E16,Customer_Dim!A:A,Customer_Dim!E:E)} -> Shannonview | K16: {=XLOOKUP(E16,Customer_Dim!A:A,Customer_Dim!F:F)} -> Pennsylvania | L16: {=XLOOKUP(Q16,Store_Dim!A:A,Store_Dim!C:C)} -> North | M16: PROD24 | N16: {=XLOOKUP(M16,Product_Dim!A:A,Product_Dim!C:C)} -> Sports | O16: {=XLOOKUP(M16,Product_Dim!A:A,Product_Dim!D:D)} -> Outdoor | P16: Cook Ltd | Q16: STORE15 | R16: {=XLOOKUP(Q16,Store_Dim!A:A,Store_Dim!B:B)} -> Shelton PLC | S16: {=XLOOKUP(Q16,Store_Dim!A:A,Store_Dim!E:E)} -> Flagship | T16: 4 | U16: 403.47 | V16: 0.29 | W16: 340 | X16: PayPal | Y16: 1145.8548 | Z16: {=XLOOKUP(M16,Product_Dim!A:A,Product_Dim!B:B)} -> Foldable Camping Chair
A17: SALE15 | B17: 45636 | C17: December | D17: =YEAR(B17) -> 2024 | E17: CUST1435 | F17: 37 | G17: =IF(F17<18,"Under 18", IF(F17<=25,"18-25", IF(F17<=35,"26-35", IF(F17<=45,"36-45", IF(F17<=55,"46-55", IF(F17<=65,"56-65","65+")))))) -> 36-45 | H17: {=XLOOKUP(E17,Customer_Dim!A:A,Customer_Dim!D:D)} -> Female | I17: {=XLOOKUP(E17,Customer_Dim!A:A,Customer_Dim!H:H)} -> Silver | J17: {=XLOOKUP(E17,Customer_Dim!A:A,Customer_Dim!E:E)} -> Wesleyhaven | K17: {=XLOOKUP(E17,Customer_Dim!A:A,Customer_Dim!F:F)} -> Idaho | L17: {=XLOOKUP(Q17,Store_Dim!A:A,Store_Dim!C:C)} -> South | M17: PROD36 | N17: {=XLOOKUP(M17,Product_Dim!A:A,Product_Dim!C:C)} -> Clothing | O17: {=XLOOKUP(M17,Product_Dim!A:A,Product_Dim!D:D)} -> Tops | P17: Smith-Mills | Q17: STORE9 | R17: {=XLOOKUP(Q17,Store_Dim!A:A,Store_Dim!B:B)} -> Moore, Padilla and Butler | S17: {=XLOOKUP(Q17,Store_Dim!A:A,Store_Dim!E:E)} -> Flagship | T17: =Y17/(U17*(1-V17)) -> 3 | U17: 871.34 | V17: 0.04 | W17: 154 | X17: COD | Y17: 2509.4592 | Z17: {=XLOOKUP(M17,Product_Dim!A:A,Product_Dim!B:B)} -> Women's Summer Dress
A18: SALE16 | B18: 45913 | C18: September | D18: =YEAR(B18) -> 2025 | E18: CUST1276 | F18: 38 | G18: =IF(F18<18,"Under 18", IF(F18<=25,"18-25", IF(F18<=35,"26-35", IF(F18<=45,"36-45", IF(F18<=55,"46-55", IF(F18<=65,"56-65","65+")))))) -> 36-45 | H18: {=XLOOKUP(E18,Customer_Dim!A:A,Customer_Dim!D:D)} -> Male | I18: {=XLOOKUP(E18,Customer_Dim!A:A,Customer_Dim!H:H)} -> Gold | J18: {=XLOOKUP(E18,Customer_Dim!A:A,Customer_Dim!E:E)} -> Ericshire | K18: {=XLOOKUP(E18,Customer_Dim!A:A,Customer_Dim!F:F)} -> Nevada | L18: {=XLOOKUP(Q18,Store_Dim!A:A,Store_Dim!C:C)} -> East | M18: PROD65 | N18: {=XLOOKUP(M18,Product_Dim!A:A,Product_Dim!C:C)} -> Sports | O18: {=XLOOKUP(M18,Product_Dim!A:A,Product_Dim!D:D)} -> Fitness | P18: Montgomery, Benton and Miller | Q18: STORE19 | R18: {=XLOOKUP(Q18,Store_Dim!A:A,Store_Dim!B:B)} -> Mann-Austin | S18: {=XLOOKUP(Q18,Store_Dim!A:A,Store_Dim!E:E)} -> Online | T18: 2 | U18: 451.98 | V18: 0.25 | W18: 423 | X18: Credit Card | Y18: 677.97 | Z18: {=XLOOKUP(M18,Product_Dim!A:A,Product_Dim!B:B)} -> Adjustable Dumbbells 20kg
A19: SALE17 | B19: 45637 | C19: December | D19: =YEAR(B19) -> 2024 | E19: CUST1079 | F19: 22 | G19: =IF(F19<18,"Under 18", IF(F19<=25,"18-25", IF(F19<=35,"26-35", IF(F19<=45,"36-45", IF(F19<=55,"46-55", IF(F19<=65,"56-65","65+")))))) -> 18-25 | H19: {=XLOOKUP(E19,Customer_Dim!A:A,Customer_Dim!D:D)} -> Female | I19: {=XLOOKUP(E19,Customer_Dim!A:A,Customer_Dim!H:H)} -> Platinum | J19: {=XLOOKUP(E19,Customer_Dim!A:A,Customer_Dim!E:E)} -> Nicoleborough | K19: {=XLOOKUP(E19,Customer_Dim!A:A,Customer_Dim!F:F)} -> Arkansas | L19: {=XLOOKUP(Q19,Store_Dim!A:A,Store_Dim!C:C)} -> South | M19: PROD27 | N19: {=XLOOKUP(M19,Product_Dim!A:A,Product_Dim!C:C)} -> Home | O19: {=XLOOKUP(M19,Product_Dim!A:A,Product_Dim!D:D)} -> Decor | P19: Khan, Jones and Paul | Q19: STORE4 | R19: {=XLOOKUP(Q19,Store_Dim!A:A,Store_Dim!B:B)} -> Alexander Group | S19: {=XLOOKUP(Q19,Store_Dim!A:A,Store_Dim!E:E)} -> Online | T19: 2 | U19: 502.69 | V19: 0.23 | W19: 378 | X19: Credit Card | Y19: 774.1426 | Z19: {=XLOOKUP(M19,Product_Dim!A:A,Product_Dim!B:B)} -> Decorative Floor Vase
A20: SALE18 | B20: 45517 | C20: August | D20: =YEAR(B20) -> 2024 | E20: CUST1094 | F20: 43 | G20: =IF(F20<18,"Under 18", IF(F20<=25,"18-25", IF(F20<=35,"26-35", IF(F20<=45,"36-45", IF(F20<=55,"46-55", IF(F20<=65,"56-65","65+")))))) -> 36-45 | H20: {=XLOOKUP(E20,Customer_Dim!A:A,Customer_Dim!D:D)} -> Female | I20: {=XLOOKUP(E20,Customer_Dim!A:A,Customer_Dim!H:H)} -> Gold | J20: {=XLOOKUP(E20,Customer_Dim!A:A,Customer_Dim!E:E)} -> New Amyport | K20: {=XLOOKUP(E20,Customer_Dim!A:A,Customer_Dim!F:F)} -> Nevada | L20: {=XLOOKUP(Q20,Store_Dim!A:A,Store_Dim!C:C)} -> South | M20: PROD39 | N20: {=XLOOKUP(M20,Product_Dim!A:A,Product_Dim!C:C)} -> Electronics | O20: {=XLOOKUP(M20,Product_Dim!A:A,Product_Dim!D:D)} -> Mobile | P20: Cummings and Sons | Q20: STORE4 | R20: {=XLOOKUP(Q20,Store_Dim!A:A,Store_Dim!B:B)} -> Alexander Group | S20: {=XLOOKUP(Q20,Store_Dim!A:A,Store_Dim!E:E)} -> Online | T20: 2 | U20: 559.23 | V20: 0.25 | W20: 301 | X20: COD | Y20: 838.845 | Z20: {=XLOOKUP(M20,Product_Dim!A:A,Product_Dim!B:B)} -> Portable Power Bank
A21: SALE19 | B21: 45369 | C21: March | D21: =YEAR(B21) -> 2024 | E21: CUST1239 | F21: 58 | G21: =IF(F21<18,"Under 18", IF(F21<=25,"18-25", IF(F21<=35,"26-35", IF(F21<=45,"36-45", IF(F21<=55,"46-55", IF(F21<=65,"56-65","65+")))))) -> 56-65 | H21: {=XLOOKUP(E21,Customer_Dim!A:A,Customer_Dim!D:D)} -> Female | I21: {=XLOOKUP(E21,Customer_Dim!A:A,Customer_Dim!H:H)} -> Platinum | J21: {=XLOOKUP(E21,Customer_Dim!A:A,Customer_Dim!E:E)} -> Zamoraborough | K21: {=XLOOKUP(E21,Customer_Dim!A:A,Customer_Dim!F:F)} -> Nevada | L21: {=XLOOKUP(Q21,Store_Dim!A:A,Store_Dim!C:C)} -> East | M21: PROD60 | N21: {=XLOOKUP(M21,Product_Dim!A:A,Product_Dim!C:C)} -> Beauty | O21: {=XLOOKUP(M21,Product_Dim!A:A,Product_Dim!D:D)} -> Fragrance | P21: Gibson, Green and Lopez | Q21: STORE13 | R21: {=XLOOKUP(Q21,Store_Dim!A:A,Store_Dim!B:B)} -> Gardner, Humphrey and Contreras | S21: {=XLOOKUP(Q21,Store_Dim!A:A,Store_Dim!E:E)} -> Flagship | T21: 4 | U21: =Y21/(1-V21)/T21 -> 464.18 | V21: 0.04 | W21: 444 | X21: COD | Y21: 1782.4512 | Z21: {=XLOOKUP(M21,Product_Dim!A:A,Product_Dim!B:B)} -> Luxury Perfume Spray
A22: SALE20 | B22: 45843 | C22: July | D22: =YEAR(B22) -> 2025 | E22: CUST1144 | F22: 62 | G22: =IF(F22<18,"Under 18", IF(F22<=25,"18-25", IF(F22<=35,"26-35", IF(F22<=45,"36-45", IF(F22<=55,"46-55", IF(F22<=65,"56-65","65+")))))) -> 56-65 | H22: {=XLOOKUP(E22,Customer_Dim!A:A,Customer_Dim!D:D)} -> Female | I22: {=XLOOKUP(E22,Customer_Dim!A:A,Customer_Dim!H:H)} -> Bronze | J22: {=XLOOKUP(E22,Customer_Dim!A:A,Customer_Dim!E:E)} -> North Anthonychester | K22: {=XLOOKUP(E22,Customer_Dim!A:A,Customer_Dim!F:F)} -> Nevada | L22: {=XLOOKUP(Q22,Store_Dim!A:A,Store_Dim!C:C)} -> North | M22: PROD72 | N22: {=XLOOKUP(M22,Product_Dim!A:A,Product_Dim!C:C)} -> Sports | O22: {=XLOOKUP(M22,Product_Dim!A:A,Product_Dim!D:D)} -> Fitness | P22: Davis PLC | Q22: STORE17 | R22: {=XLOOKUP(Q22,Store_Dim!A:A,Store_Dim!B:B)} -> Holloway Ltd | S22: {=XLOOKUP(Q22,Store_Dim!A:A,Store_Dim!E:E)} -> Flagship | T22: 3 | U22: 986.04 | V22: 0.27 | W22: 300 | X22: COD | Y22: 2159.4276 | Z22: {=XLOOKUP(M22,Product_Dim!A:A,Product_Dim!B:B)} -> Professional Jump Rope
A23: SALE21 | B23: 45447 | C23: June | D23: =YEAR(B23) -> 2024 | E23: CUST1396 | F23: 25 | G23: =IF(F23<18,"Under 18", IF(F23<=25,"18-25", IF(F23<=35,"26-35", IF(F23<=45,"36-45", IF(F23<=55,"46-55", IF(F23<=65,"56-65","65+")))))) -> 18-25 | H23: {=XLOOKUP(E23,Customer_Dim!A:A,Customer_Dim!D:D)} -> Female | I23: {=XLOOKUP(E23,Customer_Dim!A:A,Customer_Dim!H:H)} -> Silver | J23: {=XLOOKUP(E23,Customer_Dim!A:A,Customer_Dim!E:E)} -> Parkerview | K23: {=XLOOKUP(E23,Customer_Dim!A:A,Customer_Dim!F:F)} -> New York | L23: {=XLOOKUP(Q23,Store_Dim!A:A,Store_Dim!C:C)} -> East | M23: PROD43 | N23: {=XLOOKUP(M23,Product_Dim!A:A,Product_Dim!C:C)} -> Electronics | O23: {=XLOOKUP(M23,Product_Dim!A:A,Product_Dim!D:D)} -> Computer | P23: Robinson Inc | Q23: STORE18 | R23: {=XLOOKUP(Q23,Store_Dim!A:A,Store_Dim!B:B)} -> Guerrero-Schmitt | S23: {=XLOOKUP(Q23,Store_Dim!A:A,Store_Dim!E:E)} -> Flagship | T23: 1 | U23: 589.56 | V23: 0.22 | W23: 266 | X23: Credit Card | Y23: 459.8568 | Z23: {=XLOOKUP(M23,Product_Dim!A:A,Product_Dim!B:B)} -> USB External Hard Drive
A24: SALE22 | B24: 45394 | C24: April | D24: =YEAR(B24) -> 2024 | E24: CUST1476 | F24: 33 | G24: =IF(F24<18,"Under 18", IF(F24<=25,"18-25", IF(F24<=35,"26-35", IF(F24<=45,"36-45", IF(F24<=55,"46-55", IF(F24<=65,"56-65","65+")))))) -> 26-35 | H24: {=XLOOKUP(E24,Customer_Dim!A:A,Customer_Dim!D:D)} -> Female | I24: {=XLOOKUP(E24,Customer_Dim!A:A,Customer_Dim!H:H)} -> Gold | J24: {=XLOOKUP(E24,Customer_Dim!A:A,Customer_Dim!E:E)} -> Anthonymouth | K24: {=XLOOKUP(E24,Customer_Dim!A:A,Customer_Dim!F:F)} -> Oklahoma | L24: {=XLOOKUP(Q24,Store_Dim!A:A,Store_Dim!C:C)} -> East | M24: PROD69 | N24: {=XLOOKUP(M24,Product_Dim!A:A,Product_Dim!C:C)} -> Clothing | O24: {=XLOOKUP(M24,Product_Dim!A:A,Product_Dim!D:D)} -> Bottoms | P24: Fitzpatrick Ltd | Q24: STORE10 | R24: {=XLOOKUP(Q24,Store_Dim!A:A,Store_Dim!B:B)} -> Hill, Wagner and Ballard | S24: {=XLOOKUP(Q24,Store_Dim!A:A,Store_Dim!E:E)} -> Online | T24: 3 | U24: 979.42 | V24: 0.03 | W24: 224 | X24: PayPal | Y24: 2850.1122 | Z24: {=XLOOKUP(M24,Product_Dim!A:A,Product_Dim!B:B)} -> Men's Sports Shorts
A25: SALE23 | B25: 45466 | C25: June | D25: =YEAR(B25) -> 2024 | E25: CUST1368 | F25: 34 | G25: =IF(F25<18,"Under 18", IF(F25<=25,"18-25", IF(F25<=35,"26-35", IF(F25<=45,"36-45", IF(F25<=55,"46-55", IF(F25<=65,"56-65","65+")))))) -> 26-35 | H25: {=XLOOKUP(E25,Customer_Dim!A:A,Customer_Dim!D:D)} -> Female | I25: {=XLOOKUP(E25,Customer_Dim!A:A,Customer_Dim!H:H)} -> Platinum | J25: {=XLOOKUP(E25,Customer_Dim!A:A,Customer_Dim!E:E)} -> West Mathew | K25: {=XLOOKUP(E25,Customer_Dim!A:A,Customer_Dim!F:F)} -> New York | L25: {=XLOOKUP(Q25,Store_Dim!A:A,Store_Dim!C:C)} -> West | M25: PROD12 | N25: {=XLOOKUP(M25,Product_Dim!A:A,Product_Dim!C:C)} -> Beauty | O25: {=XLOOKUP(M25,Product_Dim!A:A,Product_Dim!D:D)} -> Haircare | P25: Rice LLC | Q25: STORE8 | R25: {=XLOOKUP(Q25,Store_Dim!A:A,Store_Dim!B:B)} -> Bean, Jones and Park | S25: {=XLOOKUP(Q25,Store_Dim!A:A,Store_Dim!E:E)} -> Online | T25: 1 | U25: 719.28 | V25: 0.08 | W25: 460 | X25: Credit Card | Y25: 661.7376 | Z25: {=XLOOKUP(M25,Product_Dim!A:A,Product_Dim!B:B)} -> Hair Strengthening Shampoo
A26: SALE24 | B26: 45908 | C26: September | D26: =YEAR(B26) -> 2025 | E26: CUST1186 | F26: 53 | G26: =IF(F26<18,"Under 18", IF(F26<=25,"18-25", IF(F26<=35,"26-35", IF(F26<=45,"36-45", IF(F26<=55,"46-55", IF(F26<=65,"56-65","65+")))))) -> 46-55 | H26: {=XLOOKUP(E26,Customer_Dim!A:A,Customer_Dim!D:D)} -> Male | I26: {=XLOOKUP(E26,Customer_Dim!A:A,Customer_Dim!H:H)} -> Silver | J26: {=XLOOKUP(E26,Customer_Dim!A:A,Customer_Dim!E:E)} -> East Justin | K26: {=XLOOKUP(E26,Customer_Dim!A:A,Customer_Dim!F:F)} -> Missouri | L26: {=XLOOKUP(Q26,Store_Dim!A:A,Store_Dim!C:C)} -> East | M26: PROD67 | N26: {=XLOOKUP(M26,Product_Dim!A:A,Product_Dim!C:C)} -> Electronics | O26: {=XLOOKUP(M26,Product_Dim!A:A,Product_Dim!D:D)} -> Accessories | P26: Flores-Davis | Q26: STORE6 | R26: {=XLOOKUP(Q26,Store_Dim!A:A,Store_Dim!B:B)} -> Benson-Elliott | S26: {=XLOOKUP(Q26,Store_Dim!A:A,Store_Dim!E:E)} -> Online | T26: 3 | U26: 77.6 | V26: 0.07 | W26: 476 | X26: Credit Card | Y26: 216.504 | Z26: {=XLOOKUP(M26,Product_Dim!A:A,Product_Dim!B:B)} -> Smart LED Light Strip
A27: SALE25 | B27: 45552 | C27: September | D27: =YEAR(B27) -> 2024 | E27: CUST1381 | F27: 50 | G27: =IF(F27<18,"Under 18", IF(F27<=25,"18-25", IF(F27<=35,"26-35", IF(F27<=45,"36-45", IF(F27<=55,"46-55", IF(F27<=65,"56-65","65+")))))) -> 46-55 | H27: {=XLOOKUP(E27,Customer_Dim!A:A,Customer_Dim!D:D)} -> Male | I27: {=XLOOKUP(E27,Customer_Dim!A:A,Customer_Dim!H:H)} -> Silver | J27: {=XLOOKUP(E27,Customer_Dim!A:A,Customer_Dim!E:E)} -> Andrewsland | K27: {=XLOOKUP(E27,Customer_Dim!A:A,Customer_Dim!F:F)} -> Alabama | L27: {=XLOOKUP(Q27,Store_Dim!A:A,Store_Dim!C:C)} -> North | M27: PROD5 | N27: {=XLOOKUP(M27,Product_Dim!A:A,Product_Dim!C:C)} -> Clothing | O27: {=XLOOKUP(M27,Product_Dim!A:A,Product_Dim!D:D)} -> Accessories | P27: Baldwin, Garza and Gonzalez | Q27: STORE3 | R27: {=XLOOKUP(Q27,Store_Dim!A:A,Store_Dim!B:B)} -> Johnson-Wright | S27: {=XLOOKUP(Q27,Store_Dim!A:A,Store_Dim!E:E)} -> Outlet | T27: 4 | U27: 852.71 | V27: 0.14 | W27: 59 | X27: PayPal | Y27: 2933.3224 | Z27: {=XLOOKUP(M27,Product_Dim!A:A,Product_Dim!B:B)} -> Men's Leather Belt
A28: SALE26 | B28: 45294 | C28: January | D28: =YEAR(B28) -> 2024 | E28: CUST1213 | F28: 42 | G28: =IF(F28<18,"Under 18", IF(F28<=25,"18-25", IF(F28<=35,"26-35", IF(F28<=45,"36-45", IF(F28<=55,"46-55", IF(F28<=65,"56-65","65+")))))) -> 36-45 | H28: {=XLOOKUP(E28,Customer_Dim!A:A,Customer_Dim!D:D)} -> Female | I28: {=XLOOKUP(E28,Customer_Dim!A:A,Customer_Dim!H:H)} -> Platinum | J28: {=XLOOKUP(E28,Customer_Dim!A:A,Customer_Dim!E:E)} -> West Markport | K28: {=XLOOKUP(E28,Customer_Dim!A:A,Customer_Dim!F:F)} -> North Dakota | L28: {=XLOOKUP(Q28,Store_Dim!A:A,Store_Dim!C:C)} -> West | M28: PROD98 | N28: {=XLOOKUP(M28,Product_Dim!A:A,Product_Dim!C:C)} -> Electronics | O28: {=XLOOKUP(M28,Product_Dim!A:A,Product_Dim!D:D)} -> Audio | P28: Flores-King | Q28: STORE8 | R28: {=XLOOKUP(Q28,Store_Dim!A:A,Store_Dim!B:B)} -> Bean, Jones and Park | S28: {=XLOOKUP(Q28,Store_Dim!A:A,Store_Dim!E:E)} -> Online | T28: 4 | U28: 156.16 | V28: =1-Y28/(U28*T28) -> 0.04 | W28: 73 | X28: Credit Card | Y28: 599.6544 | Z28: {=XLOOKUP(M28,Product_Dim!A:A,Product_Dim!B:B)} -> Portable Bluetooth Speaker
A29: SALE27 | B29: 45710 | C29: February | D29: =YEAR(B29) -> 2025 | E29: CUST1200 | F29: 30 | G29: =IF(F29<18,"Under 18", IF(F29<=25,"18-25", IF(F29<=35,"26-35", IF(F29<=45,"36-45", IF(F29<=55,"46-55", IF(F29<=65,"56-65","65+")))))) -> 26-35 | H29: {=XLOOKUP(E29,Customer_Dim!A:A,Customer_Dim!D:D)} -> Male | I29: {=XLOOKUP(E29,Customer_Dim!A:A,Customer_Dim!H:H)} -> Platinum | J29: {=XLOOKUP(E29,Customer_Dim!A:A,Customer_Dim!E:E)} -> South Jerry | K29: {=XLOOKUP(E29,Customer_Dim!A:A,Customer_Dim!F:F)} -> Maine | L29: {=XLOOKUP(Q29,Store_Dim!A:A,Store_Dim!C:C)} -> West | M29: PROD77 | N29: {=XLOOKUP(M29,Product_Dim!A:A,Product_Dim!C:C)} -> Electronics | O29: {=XLOOKUP(M29,Product_Dim!A:A,Product_Dim!D:D)} -> Appliances | P29: White, Reeves and Woods | Q29: STORE8 | R29: {=XLOOKUP(Q29,Store_Dim!A:A,Store_Dim!B:B)} -> Bean, Jones and Park | S29: {=XLOOKUP(Q29,Store_Dim!A:A,Store_Dim!E:E)} -> Online | T29: 3 | U29: 815.49 | V29: 0.17 | W29: 104 | X29: Credit Card | Y29: 2030.5701 | Z29: {=XLOOKUP(M29,Product_Dim!A:A,Product_Dim!B:B)} -> WiFi Mesh Router
A30: SALE28 | B30: 45923 | C30: September | D30: =YEAR(B30) -> 2025 | E30: CUST1148 | F30: 42 | G30: =IF(F30<18,"Under 18", IF(F30<=25,"18-25", IF(F30<=35,"26-35", IF(F30<=45,"36-45", IF(F30<=55,"46-55", IF(F30<=65,"56-65","65+")))))) -> 36-45 | H30: {=XLOOKUP(E30,Customer_Dim!A:A,Customer_Dim!D:D)} -> Female | I30: {=XLOOKUP(E30,Customer_Dim!A:A,Customer_Dim!H:H)} -> Bronze | J30: {=XLOOKUP(E30,Customer_Dim!A:A,Customer_Dim!E:E)} -> New Brian | K30: {=XLOOKUP(E30,Customer_Dim!A:A,Customer_Dim!F:F)} -> Wisconsin | L30: {=XLOOKUP(Q30,Store_Dim!A:A,Store_Dim!C:C)} -> South | M30: PROD13 | N30: {=XLOOKUP(M30,Product_Dim!A:A,Product_Dim!C:C)} -> Electronics | O30: {=XLOOKUP(M30,Product_Dim!A:A,Product_Dim!D:D)} -> Accessories | P30: Dawson-Perkins | Q30: STORE2 | R30: {=XLOOKUP(Q30,Store_Dim!A:A,Store_Dim!B:B)} -> Black-Horn | S30: {=XLOOKUP(Q30,Store_Dim!A:A,Store_Dim!E:E)} -> Outlet | T30: 2 | U30: 74.21 | V30: 0.11 | W30: 453 | X30: PayPal | Y30: 132.0938 | Z30: {=XLOOKUP(M30,Product_Dim!A:A,Product_Dim!B:B)} -> USB-C Fast Charger
A31: SALE29 | B31: 45302 | C31: January | D31: =YEAR(B31) -> 2024 | E31: CUST1348 | F31: 55 | G31: =IF(F31<18,"Under 18", IF(F31<=25,"18-25", IF(F31<=35,"26-35", IF(F31<=45,"36-45", IF(F31<=55,"46-55", IF(F31<=65,"56-65","65+")))))) -> 46-55 | H31: {=XLOOKUP(E31,Customer_Dim!A:A,Customer_Dim!D:D)} -> Male | I31: {=XLOOKUP(E31,Customer_Dim!A:A,Customer_Dim!H:H)} -> Silver | J31: {=XLOOKUP(E31,Customer_Dim!A:A,Customer_Dim!E:E)} -> Shannonview | K31: {=XLOOKUP(E31,Customer_Dim!A:A,Customer_Dim!F:F)} -> Pennsylvania | L31: {=XLOOKUP(Q31,Store_Dim!A:A,Store_Dim!C:C)} -> North | M31: PROD99 | N31: {=XLOOKUP(M31,Product_Dim!A:A,Product_Dim!C:C)} -> Home | O31: {=XLOOKUP(M31,Product_Dim!A:A,Product_Dim!D:D)} -> Kitchen | P31: Campbell Ltd | Q31: STORE3 | R31: {=XLOOKUP(Q31,Store_Dim!A:A,Store_Dim!B:B)} -> Johnson-Wright | S31: {=XLOOKUP(Q31,Store_Dim!A:A,Store_Dim!E:E)} -> Outlet | T31: =Y31/(U31*(1-V31)) -> 4 | U31: 451.67 | V31: 0.15 | W31: 146 | X31: Credit Card | Y31: 1535.678 | Z31: {=XLOOKUP(M31,Product_Dim!A:A,Product_Dim!B:B)} -> Stainless Steel Cookware Set
A32: SALE30 | B32: 45217 | C32: October | D32: =YEAR(B32) -> 2023 | E32: CUST1028 | F32: 27 | G32: =IF(F32<18,"Under 18", IF(F32<=25,"18-25", IF(F32<=35,"26-35", IF(F32<=45,"36-45", IF(F32<=55,"46-55", IF(F32<=65,"56-65","65+")))))) -> 26-35 | H32: {=XLOOKUP(E32,Customer_Dim!A:A,Customer_Dim!D:D)} -> Female | I32: {=XLOOKUP(E32,Customer_Dim!A:A,Customer_Dim!H:H)} -> Platinum | J32: {=XLOOKUP(E32,Customer_Dim!A:A,Customer_Dim!E:E)} -> New David | K32: {=XLOOKUP(E32,Customer_Dim!A:A,Customer_Dim!F:F)} -> New Jersey | L32: {=XLOOKUP(Q32,Store_Dim!A:A,Store_Dim!C:C)} -> East | M32: PROD5 | N32: {=XLOOKUP(M32,Product_Dim!A:A,Product_Dim!C:C)} -> Clothing | O32: {=XLOOKUP(M32,Product_Dim!A:A,Product_Dim!D:D)} -> Accessories | P32: Baldwin, Garza and Gonzalez | Q32: STORE19 | R32: {=XLOOKUP(Q32,Store_Dim!A:A,Store_Dim!B:B)} -> Mann-Austin | S32: {=XLOOKUP(Q32,Store_Dim!A:A,Store_Dim!E:E)} -> Online | T32: 1 | U32: 429.38 | V32: 0.13 | W32: 59 | X32: PayPal | Y32: 373.5606 | Z32: {=XLOOKUP(M32,Product_Dim!A:A,Product_Dim!B:B)} -> Men's Leather Belt
A33: SALE31 | B33: 45593 | C33: October | D33: =YEAR(B33) -> 2024 | E33: CUST1412 | F33: 23 | G33: =IF(F33<18,"Under 18", IF(F33<=25,"18-25", IF(F33<=35,"26-35", IF(F33<=45,"36-45", IF(F33<=55,"46-55", IF(F33<=65,"56-65","65+")))))) -> 18-25 | H33: {=XLOOKUP(E33,Customer_Dim!A:A,Customer_Dim!D:D)} -> Female | I33: {=XLOOKUP(E33,Customer_Dim!A:A,Customer_Dim!H:H)} -> Gold | J33: {=XLOOKUP(E33,Customer_Dim!A:A,Customer_Dim!E:E)} -> East Andrea | K33: {=XLOOKUP(E33,Customer_Dim!A:A,Customer_Dim!F:F)} -> Michigan | L33: {=XLOOKUP(Q33,Store_Dim!A:A,Store_Dim!C:C)} -> North | M33: PROD53 | N33: {=XLOOKUP(M33,Product_Dim!A:A,Product_Dim!C:C)} -> Clothing | O33: {=XLOOKUP(M33,Product_Dim!A:A,Product_Dim!D:D)} -> Bottoms | P33: Hamilton, Woods and Walker | Q33: STORE12 | R33: {=XLOOKUP(Q33,Store_Dim!A:A,Store_Dim!B:B)} -> Thomas, Bridges and Harris | S33: {=XLOOKUP(Q33,Store_Dim!A:A,Store_Dim!E:E)} -> Online | T33: 2 | U33: 148.96 | V33: 0.03 | W33: 125 | X33: COD | Y33: 288.9824 | Z33: {=XLOOKUP(M33,Product_Dim!A:A,Product_Dim!B:B)} -> Men's Track Pants
A34: SALE32 | B34: 45597 | C34: November | D34: =YEAR(B34) -> 2024 | E34: CUST1398 | F34: 54 | G34: =IF(F34<18,"Under 18", IF(F34<=25,"18-25", IF(F34<=35,"26-35", IF(F34<=45,"36-45", IF(F34<=55,"46-55", IF(F34<=65,"56-65","65+")))))) -> 46-55 | H34: {=XLOOKUP(E34,Customer_Dim!A:A,Customer_Dim!D:D)} -> Male | I34: {=XLOOKUP(E34,Customer_Dim!A:A,Customer_Dim!H:H)} -> Bronze | J34: {=XLOOKUP(E34,Customer_Dim!A:A,Customer_Dim!E:E)} -> Cheyenneborough | K34: {=XLOOKUP(E34,Customer_Dim!A:A,Customer_Dim!F:F)} -> New Hampshire | L34: {=XLOOKUP(Q34,Store_Dim!A:A,Store_Dim!C:C)} -> West | M34: PROD75 | N34: {=XLOOKUP(M34,Product_Dim!A:A,Product_Dim!C:C)} -> Clothing | O34: {=XLOOKUP(M34,Product_Dim!A:A,Product_Dim!D:D)} -> Footwear | P34: Poole PLC | Q34: STORE8 | R34: {=XLOOKUP(Q34,Store_Dim!A:A,Store_Dim!B:B)} -> Bean, Jones and Park | S34: {=XLOOKUP(Q34,Store_Dim!A:A,Store_Dim!E:E)} -> Online | T34: 4 | U34: 313.83 | V34: 0.08 | W34: 82 | X34: Credit Card | Y34: 1154.8944 | Z34: {=XLOOKUP(M34,Product_Dim!A:A,Product_Dim!B:B)} -> Women's Ankle Boots
A35: SALE33 | B35: 45620 | C35: November | D35: =YEAR(B35) -> 2024 | E35: CUST1453 | F35: 62 | G35: =IF(F35<18,"Under 18", IF(F35<=25,"18-25", IF(F35<=35,"26-35", IF(F35<=45,"36-45", IF(F35<=55,"46-55", IF(F35<=65,"56-65","65+")))))) -> 56-65 | H35: {=XLOOKUP(E35,Customer_Dim!A:A,Customer_Dim!D:D)} -> Female | I35: {=XLOOKUP(E35,Customer_Dim!A:A,Customer_Dim!H:H)} -> Platinum | J35: {=XLOOKUP(E35,Customer_Dim!A:A,Customer_Dim!E:E)} -> Lake Carolyn | K35: {=XLOOKUP(E35,Customer_Dim!A:A,Customer_Dim!F:F)} -> Hawaii | L35: {=XLOOKUP(Q35,Store_Dim!A:A,Store_Dim!C:C)} -> East | M35: PROD12 | N35: {=XLOOKUP(M35,Product_Dim!A:A,Product_Dim!C:C)} -> Beauty | O35: {=XLOOKUP(M35,Product_Dim!A:A,Product_Dim!D:D)} -> Haircare | P35: Rice LLC | Q35: STORE6 | R35: {=XLOOKUP(Q35,Store_Dim!A:A,Store_Dim!B:B)} -> Benson-Elliott | S35: {=XLOOKUP(Q35,Store_Dim!A:A,Store_Dim!E:E)} -> Online | T35: 2 | U35: 717.31 | V35: 0.15 | W35: 460 | X35: Credit Card | Y35: 1219.427 | Z35: {=XLOOKUP(M35,Product_Dim!A:A,Product_Dim!B:B)} -> Hair Strengthening Shampoo
A36: SALE34 | B36: 45215 | C36: October | D36: =YEAR(B36) -> 2023 | E36: CUST1344 | F36: 39 | G36: =IF(F36<18,"Under 18", IF(F36<=25,"18-25", IF(F36<=35,"26-35", IF(F36<=45,"36-45", IF(F36<=55,"46-55", IF(F36<=65,"56-65","65+")))))) -> 36-45 | H36: {=XLOOKUP(E36,Customer_Dim!A:A,Customer_Dim!D:D)} -> Male | I36: {=XLOOKUP(E36,Customer_Dim!A:A,Customer_Dim!H:H)} -> Gold | J36: {=XLOOKUP(E36,Customer_Dim!A:A,Customer_Dim!E:E)} -> West Victoriaborough | K36: {=XLOOKUP(E36,Customer_Dim!A:A,Customer_Dim!F:F)} -> New Mexico | L36: {=XLOOKUP(Q36,Store_Dim!A:A,Store_Dim!C:C)} -> North | M36: PROD79 | N36: {=XLOOKUP(M36,Product_Dim!A:A,Product_Dim!C:C)} -> Home | O36: {=XLOOKUP(M36,Product_Dim!A:A,Product_Dim!D:D)} -> Lighting | P36: Ramirez-Hanson | Q36: STORE1 | R36: {=XLOOKUP(Q36,Store_Dim!A:A,Store_Dim!B:B)} -> Martinez, Adkins and Johnson | S36: {=XLOOKUP(Q36,Store_Dim!A:A,Store_Dim!E:E)} -> Flagship | T36: =Y36/(U36*(1-V36)) -> 3 | U36: 873.22 | V36: 0.18 | W36: 469 | X36: Credit Card | Y36: 2148.1212 | Z36: {=XLOOKUP(M36,Product_Dim!A:A,Product_Dim!B:B)} -> Decorative Lamp Shade
A37: SALE35 | B37: 45878 | C37: August | D37: =YEAR(B37) -> 2025 | E37: CUST1218 | F37: 46 | G37: =IF(F37<18,"Under 18", IF(F37<=25,"18-25", IF(F37<=35,"26-35", IF(F37<=45,"36-45", IF(F37<=55,"46-55", IF(F37<=65,"56-65","65+")))))) -> 46-55 | H37: {=XLOOKUP(E37,Customer_Dim!A:A,Customer_Dim!D:D)} -> Male | I37: {=XLOOKUP(E37,Customer_Dim!A:A,Customer_Dim!H:H)} -> Platinum | J37: {=XLOOKUP(E37,Customer_Dim!A:A,Customer_Dim!E:E)} -> Edwardland | K37: {=XLOOKUP(E37,Customer_Dim!A:A,Customer_Dim!F:F)} -> California | L37: {=XLOOKUP(Q37,Store_Dim!A:A,Store_Dim!C:C)} -> North | M37: PROD16 | N37: {=XLOOKUP(M37,Product_Dim!A:A,Product_Dim!C:C)} -> Beauty | O37: {=XLOOKUP(M37,Product_Dim!A:A,Product_Dim!D:D)} -> Grooming | P37: Erickson-Green | Q37: STORE3 | R37: {=XLOOKUP(Q37,Store_Dim!A:A,Store_Dim!B:B)} -> Johnson-Wright | S37: {=XLOOKUP(Q37,Store_Dim!A:A,Store_Dim!E:E)} -> Outlet | T37: 4 | U37: 109.36 | V37: 0.19 | W37: 256 | X37: COD | Y37: 354.3264 | Z37: {=XLOOKUP(M37,Product_Dim!A:A,Product_Dim!B:B)} -> Beard Grooming Kit
A38: SALE36 | B38: 45635 | C38: December | D38: =YEAR(B38) -> 2024 | E38: CUST1086 | F38: 19 | G38: =IF(F38<18,"Under 18", IF(F38<=25,"18-25", IF(F38<=35,"26-35", IF(F38<=45,"36-45", IF(F38<=55,"46-55", IF(F38<=65,"56-65","65+")))))) -> 18-25 | H38: {=XLOOKUP(E38,Customer_Dim!A:A,Customer_Dim!D:D)} -> Female | I38: {=XLOOKUP(E38,Customer_Dim!A:A,Customer_Dim!H:H)} -> Gold | J38: {=XLOOKUP(E38,Customer_Dim!A:A,Customer_Dim!E:E)} -> Austinfurt | K38: {=XLOOKUP(E38,Customer_Dim!A:A,Customer_Dim!F:F)} -> Mississippi | L38: {=XLOOKUP(Q38,Store_Dim!A:A,Store_Dim!C:C)} -> South | M38: PROD5 | N38: {=XLOOKUP(M38,Product_Dim!A:A,Product_Dim!C:C)} -> Clothing | O38: {=XLOOKUP(M38,Product_Dim!A:A,Product_Dim!D:D)} -> Accessories | P38: Baldwin, Garza and Gonzalez | Q38: STORE7 | R38: {=XLOOKUP(Q38,Store_Dim!A:A,Store_Dim!B:B)} -> Martinez-Mullins | S38: {=XLOOKUP(Q38,Store_Dim!A:A,Store_Dim!E:E)} -> Online | T38: 3 | U38: 559.52 | V38: 0.16 | W38: 59 | X38: PayPal | Y38: 1409.9904 | Z38: {=XLOOKUP(M38,Product_Dim!A:A,Product_Dim!B:B)} -> Men's Leather Belt
A39: SALE37 | B39: 45329 | C39: February | D39: =YEAR(B39) -> 2024 | E39: CUST1492 | F39: 59 | G39: =IF(F39<18,"Under 18", IF(F39<=25,"18-25", IF(F39<=35,"26-35", IF(F39<=45,"36-45", IF(F39<=55,"46-55", IF(F39<=65,"56-65","65+")))))) -> 56-65 | H39: {=XLOOKUP(E39,Customer_Dim!A:A,Customer_Dim!D:D)} -> Female | I39: {=XLOOKUP(E39,Customer_Dim!A:A,Customer_Dim!H:H)} -> Platinum | J39: {=XLOOKUP(E39,Customer_Dim!A:A,Customer_Dim!E:E)} -> Port Carol | K39: {=XLOOKUP(E39,Customer_Dim!A:A,Customer_Dim!F:F)} -> Florida | L39: {=XLOOKUP(Q39,Store_Dim!A:A,Store_Dim!C:C)} -> North | M39: PROD10 | N39: {=XLOOKUP(M39,Product_Dim!A:A,Product_Dim!C:C)} -> Home | O39: {=XLOOKUP(M39,Product_Dim!A:A,Product_Dim!D:D)} -> Kitchen | P39: Hamilton Group | Q39: STORE17 | R39: {=XLOOKUP(Q39,Store_Dim!A:A,Store_Dim!B:B)} -> Holloway Ltd | S39: {=XLOOKUP(Q39,Store_Dim!A:A,Store_Dim!E:E)} -> Flagship | T39: 3 | U39: 121.76 | V39: 0.27 | W39: 308 | X39: PayPal | Y39: 266.6544 | Z39: {=XLOOKUP(M39,Product_Dim!A:A,Product_Dim!B:B)} -> Ceramic Kitchen Bowl Set
A40: SALE38 | B40: 45378 | C40: March | D40: =YEAR(B40) -> 2024 | E40: CUST1189 | F40: 29 | G40: =IF(F40<18,"Under 18", IF(F40<=25,"18-25", IF(F40<=35,"26-35", IF(F40<=45,"36-45", IF(F40<=55,"46-55", IF(F40<=65,"56-65","65+")))))) -> 26-35 | H40: {=XLOOKUP(E40,Customer_Dim!A:A,Customer_Dim!D:D)} -> Male | I40: {=XLOOKUP(E40,Customer_Dim!A:A,Customer_Dim!H:H)} -> Gold | J40: {=XLOOKUP(E40,Customer_Dim!A:A,Customer_Dim!E:E)} -> Lake Howardberg | K40: {=XLOOKUP(E40,Customer_Dim!A:A,Customer_Dim!F:F)} -> Kentucky | L40: {=XLOOKUP(Q40,Store_Dim!A:A,Store_Dim!C:C)} -> East | M40: PROD33 | N40: {=XLOOKUP(M40,Product_Dim!A:A,Product_Dim!C:C)} -> Home | O40: {=XLOOKUP(M40,Product_Dim!A:A,Product_Dim!D:D)} -> Decor | P40: Weiss-Watson | Q40: STORE13 | R40: {=XLOOKUP(Q40,Store_Dim!A:A,Store_Dim!B:B)} -> Gardner, Humphrey and Contreras | S40: {=XLOOKUP(Q40,Store_Dim!A:A,Store_Dim!E:E)} -> Flagship | T40: 4 | U40: 735.32 | V40: 0.06 | W40: 305 | X40: COD | Y40: 2764.8032 | Z40: {=XLOOKUP(M40,Product_Dim!A:A,Product_Dim!B:B)} -> Modern Wall Clock
A41: SALE39 | B41: 45264 | C41: December | D41: =YEAR(B41) -> 2023 | E41: CUST1431 | F41: 27 | G41: =IF(F41<18,"Under 18", IF(F41<=25,"18-25", IF(F41<=35,"26-35", IF(F41<=45,"36-45", IF(F41<=55,"46-55", IF(F41<=65,"56-65","65+")))))) -> 26-35 | H41: {=XLOOKUP(E41,Customer_Dim!A:A,Customer_Dim!D:D)} -> Male | I41: {=XLOOKUP(E41,Customer_Dim!A:A,Customer_Dim!H:H)} -> Platinum | J41: {=XLOOKUP(E41,Customer_Dim!A:A,Customer_Dim!E:E)} -> South Andrewport | K41: {=XLOOKUP(E41,Customer_Dim!A:A,Customer_Dim!F:F)} -> California | L41: {=XLOOKUP(Q41,Store_Dim!A:A,Store_Dim!C:C)} -> North | M41: PROD94 | N41: {=XLOOKUP(M41,Product_Dim!A:A,Product_Dim!C:C)} -> Beauty | O41: {=XLOOKUP(M41,Product_Dim!A:A,Product_Dim!D:D)} -> Skincare | P41: Hoffman-Williams | Q41: STORE3 | R41: {=XLOOKUP(Q41,Store_Dim!A:A,Store_Dim!B:B)} -> Johnson-Wright | S41: {=XLOOKUP(Q41,Store_Dim!A:A,Store_Dim!E:E)} -> Outlet | T41: 2 | U41: 600.73 | V41: 0.08 | W41: 213 | X41: Credit Card | Y41: 1105.3432 | Z41: {=XLOOKUP(M41,Product_Dim!A:A,Product_Dim!B:B)} -> Vitamin E Body Lotion
A42: SALE40 | B42: 45486 | C42: July | D42: =YEAR(B42) -> 2024 | E42: CUST1072 | F42: 39 | G42: =IF(F42<18,"Under 18", IF(F42<=25,"18-25", IF(F42<=35,"26-35", IF(F42<=45,"36-45", IF(F42<=55,"46-55", IF(F42<=65,"56-65","65+")))))) -> 36-45 | H42: {=XLOOKUP(E42,Customer_Dim!A:A,Customer_Dim!D:D)} -> Female | I42: {=XLOOKUP(E42,Customer_Dim!A:A,Customer_Dim!H:H)} -> Gold | J42: {=XLOOKUP(E42,Customer_Dim!A:A,Customer_Dim!E:E)} -> Olsonhaven | K42: {=XLOOKUP(E42,Customer_Dim!A:A,Customer_Dim!F:F)} -> Iowa | L42: {=XLOOKUP(Q42,Store_Dim!A:A,Store_Dim!C:C)} -> East | M42: PROD26 | N42: {=XLOOKUP(M42,Product_Dim!A:A,Product_Dim!C:C)} -> Electronics | O42: {=XLOOKUP(M42,Product_Dim!A:A,Product_Dim!D:D)} -> Audio | P42: Reed-Schmidt | Q42: STORE19 | R42: {=XLOOKUP(Q42,Store_Dim!A:A,Store_Dim!B:B)} -> Mann-Austin | S42: {=XLOOKUP(Q42,Store_Dim!A:A,Store_Dim!E:E)} -> Online | T42: 2 | U42: 873.86 | V42: 0.07 | W42: 213 | X42: COD | Y42: 1625.3796 | Z42: {=XLOOKUP(M42,Product_Dim!A:A,Product_Dim!B:B)} -> Wireless Bluetooth Speaker
A43: SALE41 | B43: 45241 | C43: November | D43: =YEAR(B43) -> 2023 | E43: CUST1302 | F43: 36 | G43: =IF(F43<18,"Under 18", IF(F43<=25,"18-25", IF(F43<=35,"26-35", IF(F43<=45,"36-45", IF(F43<=55,"46-55", IF(F43<=65,"56-65","65+")))))) -> 36-45 | H43: {=XLOOKUP(E43,Customer_Dim!A:A,Customer_Dim!D:D)} -> Male | I43: {=XLOOKUP(E43,Customer_Dim!A:A,Customer_Dim!H:H)} -> Gold | J43: {=XLOOKUP(E43,Customer_Dim!A:A,Customer_Dim!E:E)} -> Lake Charlotte | K43: {=XLOOKUP(E43,Customer_Dim!A:A,Customer_Dim!F:F)} -> Arizona | L43: {=XLOOKUP(Q43,Store_Dim!A:A,Store_Dim!C:C)} -> West | M43: PROD23 | N43: {=XLOOKUP(M43,Product_Dim!A:A,Product_Dim!C:C)} -> Clothing | O43: {=XLOOKUP(M43,Product_Dim!A:A,Product_Dim!D:D)} -> Tops | P43: Moon, Mora and Santos | Q43: STORE8 | R43: {=XLOOKUP(Q43,Store_Dim!A:A,Store_Dim!B:B)} -> Bean, Jones and Park | S43: {=XLOOKUP(Q43,Store_Dim!A:A,Store_Dim!E:E)} -> Online | T43: 3 | U43: 342.47 | V43: 0.08 | W43: 360 | X43: PayPal | Y43: 945.2172 | Z43: {=XLOOKUP(M43,Product_Dim!A:A,Product_Dim!B:B)} -> Men's Formal Shirt
A44: SALE42 | B44: 45649 | C44: December | D44: =YEAR(B44) -> 2024 | E44: CUST1335 | F44: 37 | G44: =IF(F44<18,"Under 18", IF(F44<=25,"18-25", IF(F44<=35,"26-35", IF(F44<=45,"36-45", IF(F44<=55,"46-55", IF(F44<=65,"56-65","65+")))))) -> 36-45 | H44: {=XLOOKUP(E44,Customer_Dim!A:A,Customer_Dim!D:D)} -> Male | I44: {=XLOOKUP(E44,Customer_Dim!A:A,Customer_Dim!H:H)} -> Platinum | J44: {=XLOOKUP(E44,Customer_Dim!A:A,Customer_Dim!E:E)} -> West Brendamouth | K44: {=XLOOKUP(E44,Customer_Dim!A:A,Customer_Dim!F:F)} -> North Carolina | L44: {=XLOOKUP(Q44,Store_Dim!A:A,Store_Dim!C:C)} -> South | M44: PROD29 | N44: {=XLOOKUP(M44,Product_Dim!A:A,Product_Dim!C:C)} -> Home | O44: {=XLOOKUP(M44,Product_Dim!A:A,Product_Dim!D:D)} -> Decor | P44: Hoffman Group | Q44: STORE9 | R44: {=XLOOKUP(Q44,Store_Dim!A:A,Store_Dim!B:B)} -> Moore, Padilla and Butler | S44: {=XLOOKUP(Q44,Store_Dim!A:A,Store_Dim!E:E)} -> Flagship | T44: 2 | U44: 915.15 | V44: 0.16 | W44: 276 | X44: PayPal | Y44: 1537.452 | Z44: {=XLOOKUP(M44,Product_Dim!A:A,Product_Dim!B:B)} -> Fabric Sofa Throw Blanket
A45: SALE43 | B45: 45677 | C45: January | D45: =YEAR(B45) -> 2025 | E45: CUST1084 | F45: 26 | G45: =IF(F45<18,"Under 18", IF(F45<=25,"18-25", IF(F45<=35,"26-35", IF(F45<=45,"36-45", IF(F45<=55,"46-55", IF(F45<=65,"56-65","65+")))))) -> 26-35 | H45: {=XLOOKUP(E45,Customer_Dim!A:A,Customer_Dim!D:D)} -> Female | I45: {=XLOOKUP(E45,Customer_Dim!A:A,Customer_Dim!H:H)} -> Platinum | J45: {=XLOOKUP(E45,Customer_Dim!A:A,Customer_Dim!E:E)} -> Garyberg | K45: {=XLOOKUP(E45,Customer_Dim!A:A,Customer_Dim!F:F)} -> Indiana | L45: {=XLOOKUP(Q45,Store_Dim!A:A,Store_Dim!C:C)} -> North | M45: PROD33 | N45: {=XLOOKUP(M45,Product_Dim!A:A,Product_Dim!C:C)} -> Home | O45: {=XLOOKUP(M45,Product_Dim!A:A,Product_Dim!D:D)} -> Decor | P45: Weiss-Watson | Q45: STORE17 | R45: {=XLOOKUP(Q45,Store_Dim!A:A,Store_Dim!B:B)} -> Holloway Ltd | S45: {=XLOOKUP(Q45,Store_Dim!A:A,Store_Dim!E:E)} -> Flagship | T45: =Y45/(U45*(1-V45)) -> 3 | U45: 863.11 | V45: 0.28 | W45: 305 | X45: PayPal | Y45: 1864.3176 | Z45: {=XLOOKUP(M45,Product_Dim!A:A,Product_Dim!B:B)} -> Modern Wall Clock
A46: SALE44 | B46: 45538 | C46: September | D46: =YEAR(B46) -> 2024 | E46: CUST1203 | F46: 47 | G46: =IF(F46<18,"Under 18", IF(F46<=25,"18-25", IF(F46<=35,"26-35", IF(F46<=45,"36-45", IF(F46<=55,"46-55", IF(F46<=65,"56-65","65+")))))) -> 46-55 | H46: {=XLOOKUP(E46,Customer_Dim!A:A,Customer_Dim!D:D)} -> Male | I46: {=XLOOKUP(E46,Customer_Dim!A:A,Customer_Dim!H:H)} -> Platinum | J46: {=XLOOKUP(E46,Customer_Dim!A:A,Customer_Dim!E:E)} -> Johnsonland | K46: {=XLOOKUP(E46,Customer_Dim!A:A,Customer_Dim!F:F)} -> Iowa | L46: {=XLOOKUP(Q46,Store_Dim!A:A,Store_Dim!C:C)} -> North | M46: PROD43 | N46: {=XLOOKUP(M46,Product_Dim!A:A,Product_Dim!C:C)} -> Electronics | O46: {=XLOOKUP(M46,Product_Dim!A:A,Product_Dim!D:D)} -> Computer | P46: Robinson Inc | Q46: STORE12 | R46: {=XLOOKUP(Q46,Store_Dim!A:A,Store_Dim!B:B)} -> Thomas, Bridges and Harris | S46: {=XLOOKUP(Q46,Store_Dim!A:A,Store_Dim!E:E)} -> Online | T46: 2 | U46: 209.32 | V46: 0.23 | W46: 266 | X46: COD | Y46: 322.3528 | Z46: {=XLOOKUP(M46,Product_Dim!A:A,Product_Dim!B:B)} -> USB External Hard Drive
A47: SALE45 | B47: 45606 | C47: November | D47: =YEAR(B47) -> 2024 | E47: CUST1470 | F47: 21 | G47: =IF(F47<18,"Under 18", IF(F47<=25,"18-25", IF(F47<=35,"26-35", IF(F47<=45,"36-45", IF(F47<=55,"46-55", IF(F47<=65,"56-65","65+")))))) -> 18-25 | H47: {=XLOOKUP(E47,Customer_Dim!A:A,Customer_Dim!D:D)} -> Female | I47: {=XLOOKUP(E47,Customer_Dim!A:A,Customer_Dim!H:H)} -> Gold | J47: {=XLOOKUP(E47,Customer_Dim!A:A,Customer_Dim!E:E)} -> Kanebury | K47: {=XLOOKUP(E47,Customer_Dim!A:A,Customer_Dim!F:F)} -> New Hampshire | L47: {=XLOOKUP(Q47,Store_Dim!A:A,Store_Dim!C:C)} -> West | M47: PROD59 | N47: {=XLOOKUP(M47,Product_Dim!A:A,Product_Dim!C:C)} -> Beauty | O47: {=XLOOKUP(M47,Product_Dim!A:A,Product_Dim!D:D)} -> Haircare | P47: Cline-Mccarthy | Q47: STORE8 | R47: {=XLOOKUP(Q47,Store_Dim!A:A,Store_Dim!B:B)} -> Bean, Jones and Park | S47: {=XLOOKUP(Q47,Store_Dim!A:A,Store_Dim!E:E)} -> Online | T47: 4 | U47: 288.6 | V47: 0.09 | W47: 399 | X47: PayPal | Y47: 1050.504 | Z47: {=XLOOKUP(M47,Product_Dim!A:A,Product_Dim!B:B)} -> Men's Hair Styling Gel
A48: SALE46 | B48: 45570 | C48: October | D48: =YEAR(B48) -> 2024 | E48: CUST1070 | F48: 29 | G48: =IF(F48<18,"Under 18", IF(F48<=25,"18-25", IF(F48<=35,"26-35", IF(F48<=45,"36-45", IF(F48<=55,"46-55", IF(F48<=65,"56-65","65+")))))) -> 26-35 | H48: {=XLOOKUP(E48,Customer_Dim!A:A,Customer_Dim!D:D)} -> Female | I48: {=XLOOKUP(E48,Customer_Dim!A:A,Customer_Dim!H:H)} -> Gold | J48: {=XLOOKUP(E48,Customer_Dim!A:A,Customer_Dim!E:E)} -> Port Lisa | K48: {=XLOOKUP(E48,Customer_Dim!A:A,Customer_Dim!F:F)} -> New Mexico | L48: {=XLOOKUP(Q48,Store_Dim!A:A,Store_Dim!C:C)} -> West | M48: PROD78 | N48: {=XLOOKUP(M48,Product_Dim!A:A,Product_Dim!C:C)} -> Home | O48: {=XLOOKUP(M48,Product_Dim!A:A,Product_Dim!D:D)} -> Decor | P48: Hernandez Inc | Q48: STORE16 | R48: {=XLOOKUP(Q48,Store_Dim!A:A,Store_Dim!B:B)} -> Frederick-Wright | S48: {=XLOOKUP(Q48,Store_Dim!A:A,Store_Dim!E:E)} -> Flagship | T48: 1 | U48: 418.69 | V48: 0.06 | W48: 400 | X48: PayPal | Y48: 393.5686 | Z48: {=XLOOKUP(M48,Product_Dim!A:A,Product_Dim!B:B)} -> Essential Oil Diffuser
A49: SALE47 | B49: 45466 | C49: June | D49: =YEAR(B49) -> 2024 | E49: CUST1008 | F49: 53 | G49: =IF(F49<18,"Under 18", IF(F49<=25,"18-25", IF(F49<=35,"26-35", IF(F49<=45,"36-45", IF(F49<=55,"46-55", IF(F49<=65,"56-65","65+")))))) -> 46-55 | H49: {=XLOOKUP(E49,Customer_Dim!A:A,Customer_Dim!D:D)} -> Female | I49: {=XLOOKUP(E49,Customer_Dim!A:A,Customer_Dim!H:H)} -> Gold | J49: {=XLOOKUP(E49,Customer_Dim!A:A,Customer_Dim!E:E)} -> Maynardton | K49: {=XLOOKUP(E49,Customer_Dim!A:A,Customer_Dim!F:F)} -> New Hampshire | L49: {=XLOOKUP(Q49,Store_Dim!A:A,Store_Dim!C:C)} -> South | M49: PROD30 | N49: {=XLOOKUP(M49,Product_Dim!A:A,Product_Dim!C:C)} -> Home | O49: {=XLOOKUP(M49,Product_Dim!A:A,Product_Dim!D:D)} -> Kitchen | P49: Stevens, Fernandez and Martin | Q49: STORE11 | R49: {=XLOOKUP(Q49,Store_Dim!A:A,Store_Dim!B:B)} -> Aguirre-Keller | S49: {=XLOOKUP(Q49,Store_Dim!A:A,Store_Dim!E:E)} -> Online | T49: 1 | U49: 135.78 | V49: 0.14 | W49: 57 | X49: PayPal | Y49: 116.7708 | Z49: {=XLOOKUP(M49,Product_Dim!A:A,Product_Dim!B:B)} -> Stainless Steel Cutlery Set
A50: SALE48 | B50: 45218 | C50: October | D50: =YEAR(B50) -> 2023 | E50: CUST1203 | F50: 47 | G50: =IF(F50<18,"Under 18", IF(F50<=25,"18-25", IF(F50<=35,"26-35", IF(F50<=45,"36-45", IF(F50<=55,"46-55", IF(F50<=65,"56-65","65+")))))) -> 46-55 | H50: {=XLOOKUP(E50,Customer_Dim!A:A,Customer_Dim!D:D)} -> Male | I50: {=XLOOKUP(E50,Customer_Dim!A:A,Customer_Dim!H:H)} -> Platinum | J50: {=XLOOKUP(E50,Customer_Dim!A:A,Customer_Dim!E:E)} -> Johnsonland | K50: {=XLOOKUP(E50,Customer_Dim!A:A,Customer_Dim!F:F)} -> Iowa | L50: {=XLOOKUP(Q50,Store_Dim!A:A,Store_Dim!C:C)} -> North | M50: PROD44 | N50: {=XLOOKUP(M50,Product_Dim!A:A,Product_Dim!C:C)} -> Sports | O50: {=XLOOKUP(M50,Product_Dim!A:A,Product_Dim!D:D)} -> Fitness | P50: Cox Inc | Q50: STORE17 | R50: {=XLOOKUP(Q50,Store_Dim!A:A,Store_Dim!B:B)} -> Holloway Ltd | S50: {=XLOOKUP(Q50,Store_Dim!A:A,Store_Dim!E:E)} -> Flagship | T50: 1 | U50: 517.13 | V50: 0.28 | W50: 316 | X50: Credit Card | Y50: 372.3336 | Z50: {=XLOOKUP(M50,Product_Dim!A:A,Product_Dim!B:B)} -> Adjustable Jump Rope
A51: SALE49 | B51: 45607 | C51: November | D51: =YEAR(B51) -> 2024 | E51: CUST1420 | F51: 60 | G51: =IF(F51<18,"Under 18", IF(F51<=25,"18-25", IF(F51<=35,"26-35", IF(F51<=45,"36-45", IF(F51<=55,"46-55", IF(F51<=65,"56-65","65+")))))) -> 56-65 | H51: {=XLOOKUP(E51,Customer_Dim!A:A,Customer_Dim!D:D)} -> Male | I51: {=XLOOKUP(E51,Customer_Dim!A:A,Customer_Dim!H:H)} -> Bronze | J51: {=XLOOKUP(E51,Customer_Dim!A:A,Customer_Dim!E:E)} -> New Benjamin | K51: {=XLOOKUP(E51,Customer_Dim!A:A,Customer_Dim!F:F)} -> North Carolina | L51: {=XLOOKUP(Q51,Store_Dim!A:A,Store_Dim!C:C)} -> West | M51: PROD21 | N51: {=XLOOKUP(M51,Product_Dim!A:A,Product_Dim!C:C)} -> Home | O51: {=XLOOKUP(M51,Product_Dim!A:A,Product_Dim!D:D)} -> Storage | P51: Gardner-Montes | Q51: STORE16 | R51: {=XLOOKUP(Q51,Store_Dim!A:A,Store_Dim!B:B)} -> Frederick-Wright | S51: {=XLOOKUP(Q51,Store_Dim!A:A,Store_Dim!E:E)} -> Flagship | T51: 2 | U51: 384.66 | V51: 0.08 | W51: 76 | X51: COD | Y51: 707.7744 | Z51: {=XLOOKUP(M51,Product_Dim!A:A,Product_Dim!B:B)} -> Multi-Purpose Storage Box
A52: SALE50 | B52: 45291 | C52: December | D52: =YEAR(B52) -> 2023 | E52: CUST1070 | F52: 29 | G52: =IF(F52<18,"Under 18", IF(F52<=25,"18-25", IF(F52<=35,"26-35", IF(F52<=45,"36-45", IF(F52<=55,"46-55", IF(F52<=65,"56-65","65+")))))) -> 26-35 | H52: {=XLOOKUP(E52,Customer_Dim!A:A,Customer_Dim!D:D)} -> Female | I52: {=XLOOKUP(E52,Customer_Dim!A:A,Customer_Dim!H:H)} -> Gold | J52: {=XLOOKUP(E52,Customer_Dim!A:A,Customer_Dim!E:E)} -> Port Lisa | K52: {=XLOOKUP(E52,Customer_Dim!A:A,Customer_Dim!F:F)} -> New Mexico | L52: {=XLOOKUP(Q52,Store_Dim!A:A,Store_Dim!C:C)} -> South | M52: PROD52 | N52: {=XLOOKUP(M52,Product_Dim!A:A,Product_Dim!C:C)} -> Sports | O52: {=XLOOKUP(M52,Product_Dim!A:A,Product_Dim!D:D)} -> Team Sports | P52: Harris Inc | Q52: STORE9 | R52: {=XLOOKUP(Q52,Store_Dim!A:A,Store_Dim!B:B)} -> Moore, Padilla and Butler | S52: {=XLOOKUP(Q52,Store_Dim!A:A,Store_Dim!E:E)} -> Flagship | T52: 3 | U52: 83.7 | V52: 0.24 | W52: 82 | X52: PayPal | Y52: 190.836 | Z52: {=XLOOKUP(M52,Product_Dim!A:A,Product_Dim!B:B)} -> Rugby Ball
A53: SALE51 | B53: 45689 | C53: February | D53: =YEAR(B53) -> 2025 | E53: CUST1142 | F53: 37 | G53: =IF(F53<18,"Under 18", IF(F53<=25,"18-25", IF(F53<=35,"26-35", IF(F53<=45,"36-45", IF(F53<=55,"46-55", IF(F53<=65,"56-65","65+")))))) -> 36-45 | H53: {=XLOOKUP(E53,Customer_Dim!A:A,Customer_Dim!D:D)} -> Male | I53: {=XLOOKUP(E53,Customer_Dim!A:A,Customer_Dim!H:H)} -> Bronze | J53: {=XLOOKUP(E53,Customer_Dim!A:A,Customer_Dim!E:E)} -> West Brandon | K53: {=XLOOKUP(E53,Customer_Dim!A:A,Customer_Dim!F:F)} -> Montana | L53: {=XLOOKUP(Q53,Store_Dim!A:A,Store_Dim!C:C)} -> South | M53: PROD69 | N53: {=XLOOKUP(M53,Product_Dim!A:A,Product_Dim!C:C)} -> Clothing | O53: {=XLOOKUP(M53,Product_Dim!A:A,Product_Dim!D:D)} -> Bottoms | P53: Fitzpatrick Ltd | Q53: STORE7 | R53: {=XLOOKUP(Q53,Store_Dim!A:A,Store_Dim!B:B)} -> Martinez-Mullins | S53: {=XLOOKUP(Q53,Store_Dim!A:A,Store_Dim!E:E)} -> Online | T53: 3 | U53: 76.57 | V53: 0.26 | W53: 224 | X53: Credit Card | Y53: 169.9854 | Z53: {=XLOOKUP(M53,Product_Dim!A:A,Product_Dim!B:B)} -> Men's Sports Shorts
A54: SALE52 | B54: 45894 | C54: August | D54: =YEAR(B54) -> 2025 | E54: CUST1148 | F54: 42 | G54: =IF(F54<18,"Under 18", IF(F54<=25,"18-25", IF(F54<=35,"26-35", IF(F54<=45,"36-45", IF(F54<=55,"46-55", IF(F54<=65,"56-65","65+")))))) -> 36-45 | H54: {=XLOOKUP(E54,Customer_Dim!A:A,Customer_Dim!D:D)} -> Female | I54: {=XLOOKUP(E54,Customer_Dim!A:A,Customer_Dim!H:H)} -> Bronze | J54: {=XLOOKUP(E54,Customer_Dim!A:A,Customer_Dim!E:E)} -> New Brian | K54: {=XLOOKUP(E54,Customer_Dim!A:A,Customer_Dim!F:F)} -> Wisconsin | L54: {=XLOOKUP(Q54,Store_Dim!A:A,Store_Dim!C:C)} -> East | M54: PROD89 | N54: {=XLOOKUP(M54,Product_Dim!A:A,Product_Dim!C:C)} -> Beauty | O54: {=XLOOKUP(M54,Product_Dim!A:A,Product_Dim!D:D)} -> Makeup | P54: Taylor-Elliott | Q54: STORE6 | R54: {=XLOOKUP(Q54,Store_Dim!A:A,Store_Dim!B:B)} -> Benson-Elliott | S54: {=XLOOKUP(Q54,Store_Dim!A:A,Store_Dim!E:E)} -> Online | T54: 3 | U54: =Y54/(1-V54)/T54 -> 162.0211 | V54: 0 | W54: 457 | X54: Credit Card | Y54: 486.0633 | Z54: {=XLOOKUP(M54,Product_Dim!A:A,Product_Dim!B:B)} -> Face Foundation Kit
A55: SALE53 | B55: 45677 | C55: January | D55: =YEAR(B55) -> 2025 | E55: CUST1324 | F55: 58 | G55: =IF(F55<18,"Under 18", IF(F55<=25,"18-25", IF(F55<=35,"26-35", IF(F55<=45,"36-45", IF(F55<=55,"46-55", IF(F55<=65,"56-65","65+")))))) -> 56-65 | H55: {=XLOOKUP(E55,Customer_Dim!A:A,Customer_Dim!D:D)} -> Male | I55: {=XLOOKUP(E55,Customer_Dim!A:A,Customer_Dim!H:H)} -> Bronze | J55: {=XLOOKUP(E55,Customer_Dim!A:A,Customer_Dim!E:E)} -> South Zacharychester | K55: {=XLOOKUP(E55,Customer_Dim!A:A,Customer_Dim!F:F)} -> Oklahoma | L55: {=XLOOKUP(Q55,Store_Dim!A:A,Store_Dim!C:C)} -> West | M55: PROD20 | N55: {=XLOOKUP(M55,Product_Dim!A:A,Product_Dim!C:C)} -> Sports | O55: {=XLOOKUP(M55,Product_Dim!A:A,Product_Dim!D:D)} -> Accessories | P55: Soto-Ellis | Q55: STORE8 | R55: {=XLOOKUP(Q55,Store_Dim!A:A,Store_Dim!B:B)} -> Bean, Jones and Park | S55: {=XLOOKUP(Q55,Store_Dim!A:A,Store_Dim!E:E)} -> Online | T55: 1 | U55: 900.35 | V55: 0.13 | W55: 273.86258 | X55: COD | Y55: 783.3045 | Z55: {=XLOOKUP(M55,Product_Dim!A:A,Product_Dim!B:B)} -> Outdoor Sports Water Bottle
A56: SALE54 | B56: 45706 | C56: February | D56: =YEAR(B56) -> 2025 | E56: CUST1095 | F56: 62 | G56: =IF(F56<18,"Under 18", IF(F56<=25,"18-25", IF(F56<=35,"26-35", IF(F56<=45,"36-45", IF(F56<=55,"46-55", IF(F56<=65,"56-65","65+")))))) -> 56-65 | H56: {=XLOOKUP(E56,Customer_Dim!A:A,Customer_Dim!D:D)} -> Female | I56: {=XLOOKUP(E56,Customer_Dim!A:A,Customer_Dim!H:H)} -> Platinum | J56: {=XLOOKUP(E56,Customer_Dim!A:A,Customer_Dim!E:E)} -> West Bobbyshire | K56: {=XLOOKUP(E56,Customer_Dim!A:A,Customer_Dim!F:F)} -> New York | L56: {=XLOOKUP(Q56,Store_Dim!A:A,Store_Dim!C:C)} -> East | M56: PROD40 | N56: {=XLOOKUP(M56,Product_Dim!A:A,Product_Dim!C:C)} -> Electronics | O56: {=XLOOKUP(M56,Product_Dim!A:A,Product_Dim!D:D)} -> Audio | P56: Taylor-Hart | Q56: STORE10 | R56: {=XLOOKUP(Q56,Store_Dim!A:A,Store_Dim!B:B)} -> Hill, Wagner and Ballard | S56: {=XLOOKUP(Q56,Store_Dim!A:A,Store_Dim!E:E)} -> Online | T56: 4 | U56: 428.09 | V56: 0.07 | W56: 378 | X56: Credit Card | Y56: 1592.4948 | Z56: {=XLOOKUP(M56,Product_Dim!A:A,Product_Dim!B:B)} -> Noise-Canceling Headphones
A57: SALE55 | B57: 45589 | C57: October | D57: =YEAR(B57) -> 2024 | E57: CUST1416 | F57: 46 | G57: =IF(F57<18,"Under 18", IF(F57<=25,"18-25", IF(F57<=35,"26-35", IF(F57<=45,"36-45", IF(F57<=55,"46-55", IF(F57<=65,"56-65","65+")))))) -> 46-55 | H57: {=XLOOKUP(E57,Customer_Dim!A:A,Customer_Dim!D:D)} -> Male | I57: {=XLOOKUP(E57,Customer_Dim!A:A,Customer_Dim!H:H)} -> Platinum | J57: {=XLOOKUP(E57,Customer_Dim!A:A,Customer_Dim!E:E)} -> Marthaborough | K57: {=XLOOKUP(E57,Customer_Dim!A:A,Customer_Dim!F:F)} -> Wisconsin | L57: {=XLOOKUP(Q57,Store_Dim!A:A,Store_Dim!C:C)} -> South | M57: PROD49 | N57: {=XLOOKUP(M57,Product_Dim!A:A,Product_Dim!C:C)} -> Beauty | O57: {=XLOOKUP(M57,Product_Dim!A:A,Product_Dim!D:D)} -> Fragrance | P57: Sullivan and Sons | Q57: STORE11 | R57: {=XLOOKUP(Q57,Store_Dim!A:A,Store_Dim!B:B)} -> Aguirre-Keller | S57: {=XLOOKUP(Q57,Store_Dim!A:A,Store_Dim!E:E)} -> Online | T57: 2 | U57: 559.71 | V57: 0.3 | W57: 267 | X57: COD | Y57: 783.594 | Z57: {=XLOOKUP(M57,Product_Dim!A:A,Product_Dim!B:B)} -> Men's Roll-On Perfume
A58: SALE56 | B58: 45282 | C58: December | D58: =YEAR(B58) -> 2023 | E58: CUST1080 | F58: 61 | G58: =IF(F58<18,"Under 18", IF(F58<=25,"18-25", IF(F58<=35,"26-35", IF(F58<=45,"36-45", IF(F58<=55,"46-55", IF(F58<=65,"56-65","65+")))))) -> 56-65 | H58: {=XLOOKUP(E58,Customer_Dim!A:A,Customer_Dim!D:D)} -> Female | I58: {=XLOOKUP(E58,Customer_Dim!A:A,Customer_Dim!H:H)} -> Bronze | J58: {=XLOOKUP(E58,Customer_Dim!A:A,Customer_Dim!E:E)} -> New Sean | K58: {=XLOOKUP(E58,Customer_Dim!A:A,Customer_Dim!F:F)} -> New Mexico | L58: {=XLOOKUP(Q58,Store_Dim!A:A,Store_Dim!C:C)} -> East | M58: PROD34 | N58: {=XLOOKUP(M58,Product_Dim!A:A,Product_Dim!C:C)} -> Electronics | O58: {=XLOOKUP(M58,Product_Dim!A:A,Product_Dim!D:D)} -> Computer | P58: Lucero LLC | Q58: STORE6 | R58: {=XLOOKUP(Q58,Store_Dim!A:A,Store_Dim!B:B)} -> Benson-Elliott | S58: {=XLOOKUP(Q58,Store_Dim!A:A,Store_Dim!E:E)} -> Online | T58: 2 | U58: 833.7 | V58: 0.06 | W58: 86 | X58: PayPal | Y58: 1567.356 | Z58: {=XLOOKUP(M58,Product_Dim!A:A,Product_Dim!B:B)} -> Gaming Mechanical Keyboard
A59: SALE57 | B59: 45462 | C59: June | D59: =YEAR(B59) -> 2024 | E59: CUST1467 | F59: 63 | G59: =IF(F59<18,"Under 18", IF(F59<=25,"18-25", IF(F59<=35,"26-35", IF(F59<=45,"36-45", IF(F59<=55,"46-55", IF(F59<=65,"56-65","65+")))))) -> 56-65 | H59: {=XLOOKUP(E59,Customer_Dim!A:A,Customer_Dim!D:D)} -> Female | I59: {=XLOOKUP(E59,Customer_Dim!A:A,Customer_Dim!H:H)} -> Gold | J59: {=XLOOKUP(E59,Customer_Dim!A:A,Customer_Dim!E:E)} -> Oneillfurt | K59: {=XLOOKUP(E59,Customer_Dim!A:A,Customer_Dim!F:F)} -> Vermont | L59: {=XLOOKUP(Q59,Store_Dim!A:A,Store_Dim!C:C)} -> South | M59: PROD47 | N59: {=XLOOKUP(M59,Product_Dim!A:A,Product_Dim!C:C)} -> Beauty | O59: {=XLOOKUP(M59,Product_Dim!A:A,Product_Dim!D:D)} -> Makeup | P59: Cook Inc | Q59: STORE14 | R59: {=XLOOKUP(Q59,Store_Dim!A:A,Store_Dim!B:B)} -> Mcdonald Inc | S59: {=XLOOKUP(Q59,Store_Dim!A:A,Store_Dim!E:E)} -> Outlet | T59: 2 | U59: 680.16 | V59: 0.28 | W59: 431 | X59: Credit Card | Y59: 979.4304 | Z59: {=XLOOKUP(M59,Product_Dim!A:A,Product_Dim!B:B)} -> Makeup Brush Set
A60: SALE58 | B60: 45633 | C60: December | D60: =YEAR(B60) -> 2024 | E60: CUST1404 | F60: 22 | G60: =IF(F60<18,"Under 18", IF(F60<=25,"18-25", IF(F60<=35,"26-35", IF(F60<=45,"36-45", IF(F60<=55,"46-55", IF(F60<=65,"56-65","65+")))))) -> 18-25 | H60: {=XLOOKUP(E60,Customer_Dim!A:A,Customer_Dim!D:D)} -> Female | I60: {=XLOOKUP(E60,Customer_Dim!A:A,Customer_Dim!H:H)} -> Silver | J60: {=XLOOKUP(E60,Customer_Dim!A:A,Customer_Dim!E:E)} -> South Angela | K60: {=XLOOKUP(E60,Customer_Dim!A:A,Customer_Dim!F:F)} -> Arkansas | L60: {=XLOOKUP(Q60,Store_Dim!A:A,Store_Dim!C:C)} -> South | M60: PROD15 | N60: {=XLOOKUP(M60,Product_Dim!A:A,Product_Dim!C:C)} -> Electronics | O60: {=XLOOKUP(M60,Product_Dim!A:A,Product_Dim!D:D)} -> Appliances | P60: Thomas LLC | Q60: STORE7 | R60: {=XLOOKUP(Q60,Store_Dim!A:A,Store_Dim!B:B)} -> Martinez-Mullins | S60: {=XLOOKUP(Q60,Store_Dim!A:A,Store_Dim!E:E)} -> Online | T60: 4 | U60: 733.42 | V60: =1-Y60/(U60*T60) -> 0.13 | W60: 301 | X60: PayPal | Y60: 2552.3016 | Z60: {=XLOOKUP(M60,Product_Dim!A:A,Product_Dim!B:B)} -> 4K Home Projector
A61: SALE59 | B61: 45257 | C61: November | D61: =YEAR(B61) -> 2023 | E61: CUST1367 | F61: 51 | G61: =IF(F61<18,"Under 18", IF(F61<=25,"18-25", IF(F61<=35,"26-35", IF(F61<=45,"36-45", IF(F61<=55,"46-55", IF(F61<=65,"56-65","65+")))))) -> 46-55 | H61: {=XLOOKUP(E61,Customer_Dim!A:A,Customer_Dim!D:D)} -> Male | I61: {=XLOOKUP(E61,Customer_Dim!A:A,Customer_Dim!H:H)} -> Bronze | J61: {=XLOOKUP(E61,Customer_Dim!A:A,Customer_Dim!E:E)} -> Kaufmanfurt | K61: {=XLOOKUP(E61,Customer_Dim!A:A,Customer_Dim!F:F)} -> Ohio | L61: {=XLOOKUP(Q61,Store_Dim!A:A,Store_Dim!C:C)} -> South | M61: PROD89 | N61: {=XLOOKUP(M61,Product_Dim!A:A,Product_Dim!C:C)} -> Beauty | O61: {=XLOOKUP(M61,Product_Dim!A:A,Product_Dim!D:D)} -> Makeup | P61: Taylor-Elliott | Q61: STORE11 | R61: {=XLOOKUP(Q61,Store_Dim!A:A,Store_Dim!B:B)} -> Aguirre-Keller | S61: {=XLOOKUP(Q61,Store_Dim!A:A,Store_Dim!E:E)} -> Online | T61: 1 | U61: 996.33 | V61: 0.23 | W61: 457 | X61: PayPal | Y61: 767.1741 | Z61: {=XLOOKUP(M61,Product_Dim!A:A,Product_Dim!B:B)} -> Face Foundation Kit
A62: SALE60 | B62: 45854 | C62: July | D62: =YEAR(B62) -> 2025 | E62: CUST1408 | F62: 36 | G62: =IF(F62<18,"Under 18", IF(F62<=25,"18-25", IF(F62<=35,"26-35", IF(F62<=45,"36-45", IF(F62<=55,"46-55", IF(F62<=65,"56-65","65+")))))) -> 36-45 | H62: {=XLOOKUP(E62,Customer_Dim!A:A,Customer_Dim!D:D)} -> Male | I62: {=XLOOKUP(E62,Customer_Dim!A:A,Customer_Dim!H:H)} -> Gold | J62: {=XLOOKUP(E62,Customer_Dim!A:A,Customer_Dim!E:E)} -> Port Joshuaville | K62: {=XLOOKUP(E62,Customer_Dim!A:A,Customer_Dim!F:F)} -> New Jersey | L62: {=XLOOKUP(Q62,Store_Dim!A:A,Store_Dim!C:C)} -> East | M62: PROD31 | N62: {=XLOOKUP(M62,Product_Dim!A:A,Product_Dim!C:C)} -> Sports | O62: {=XLOOKUP(M62,Product_Dim!A:A,Product_Dim!D:D)} -> Team Sports | P62: Nolan-Snow | Q62: STORE10 | R62: {=XLOOKUP(Q62,Store_Dim!A:A,Store_Dim!B:B)} -> Hill, Wagner and Ballard | S62: {=XLOOKUP(Q62,Store_Dim!A:A,Store_Dim!E:E)} -> Online | T62: 1 | U62: 198.83 | V62: 0.09 | W62: 281 | X62: COD | Y62: 180.9353 | Z62: {=XLOOKUP(M62,Product_Dim!A:A,Product_Dim!B:B)} -> Basketball
A63: SALE61 | B63: 45716 | C63: February | D63: =YEAR(B63) -> 2025 | E63: CUST1239 | F63: 58 | G63: =IF(F63<18,"Under 18", IF(F63<=25,"18-25", IF(F63<=35,"26-35", IF(F63<=45,"36-45", IF(F63<=55,"46-55", IF(F63<=65,"56-65","65+")))))) -> 56-65 | H63: {=XLOOKUP(E63,Customer_Dim!A:A,Customer_Dim!D:D)} -> Female | I63: {=XLOOKUP(E63,Customer_Dim!A:A,Customer_Dim!H:H)} -> Platinum | J63: {=XLOOKUP(E63,Customer_Dim!A:A,Customer_Dim!E:E)} -> Zamoraborough | K63: {=XLOOKUP(E63,Customer_Dim!A:A,Customer_Dim!F:F)} -> Nevada | L63: {=XLOOKUP(Q63,Store_Dim!A:A,Store_Dim!C:C)} -> South | M63: PROD19 | N63: {=XLOOKUP(M63,Product_Dim!A:A,Product_Dim!C:C)} -> Sports | O63: {=XLOOKUP(M63,Product_Dim!A:A,Product_Dim!D:D)} -> Equipment | P63: May-Reese | Q63: STORE7 | R63: {=XLOOKUP(Q63,Store_Dim!A:A,Store_Dim!B:B)} -> Martinez-Mullins | S63: {=XLOOKUP(Q63,Store_Dim!A:A,Store_Dim!E:E)} -> Online | T63: 1 | U63: 374.92 | V63: 0.18 | W63: 65 | X63: PayPal | Y63: 307.4344 | Z63: {=XLOOKUP(M63,Product_Dim!A:A,Product_Dim!B:B)} -> Knee Support Brace
A64: SALE62 | B64: 45515 | C64: August | D64: =YEAR(B64) -> 2024 | E64: CUST1464 | F64: 41.576845 | G64: =IF(F64<18,"Under 18", IF(F64<=25,"18-25", IF(F64<=35,"26-35", IF(F64<=45,"36-45", IF(F64<=55,"46-55", IF(F64<=65,"56-65","65+")))))) -> 36-45 | H64: {=XLOOKUP(E64,Customer_Dim!A:A,Customer_Dim!D:D)} -> Female | I64: {=XLOOKUP(E64,Customer_Dim!A:A,Customer_Dim!H:H)} -> Platinum | J64: {=XLOOKUP(E64,Customer_Dim!A:A,Customer_Dim!E:E)} -> Grayland | K64: {=XLOOKUP(E64,Customer_Dim!A:A,Customer_Dim!F:F)} -> Washington | L64: {=XLOOKUP(Q64,Store_Dim!A:A,Store_Dim!C:C)} -> West | M64: PROD93 | N64: {=XLOOKUP(M64,Product_Dim!A:A,Product_Dim!C:C)} -> Electronics | O64: {=XLOOKUP(M64,Product_Dim!A:A,Product_Dim!D:D)} -> Computer | P64: Martin LLC | Q64: STORE16 | R64: {=XLOOKUP(Q64,Store_Dim!A:A,Store_Dim!B:B)} -> Frederick-Wright | S64: {=XLOOKUP(Q64,Store_Dim!A:A,Store_Dim!E:E)} -> Flagship | T64: 1 | U64: 468.94 | V64: 0.12 | W64: 485 | X64: Credit Card | Y64: 412.6672 | Z64: {=XLOOKUP(M64,Product_Dim!A:A,Product_Dim!B:B)} -> USB-C Laptop Charger
A65: SALE63 | B65: 45927 | C65: September | D65: =YEAR(B65) -> 2025 | E65: CUST1126 | F65: 62 | G65: =IF(F65<18,"Under 18", IF(F65<=25,"18-25", IF(F65<=35,"26-35", IF(F65<=45,"36-45", IF(F65<=55,"46-55", IF(F65<=65,"56-65","65+")))))) -> 56-65 | H65: {=XLOOKUP(E65,Customer_Dim!A:A,Customer_Dim!D:D)} -> Female | I65: {=XLOOKUP(E65,Customer_Dim!A:A,Customer_Dim!H:H)} -> Gold | J65: {=XLOOKUP(E65,Customer_Dim!A:A,Customer_Dim!E:E)} -> Benjaminton | K65: {=XLOOKUP(E65,Customer_Dim!A:A,Customer_Dim!F:F)} -> Arizona | L65: {=XLOOKUP(Q65,Store_Dim!A:A,Store_Dim!C:C)} -> North | M65: PROD89 | N65: {=XLOOKUP(M65,Product_Dim!A:A,Product_Dim!C:C)} -> Beauty | O65: {=XLOOKUP(M65,Product_Dim!A:A,Product_Dim!D:D)} -> Makeup | P65: Taylor-Elliott | Q65: STORE12 | R65: {=XLOOKUP(Q65,Store_Dim!A:A,Store_Dim!B:B)} -> Thomas, Bridges and Harris | S65: {=XLOOKUP(Q65,Store_Dim!A:A,Store_Dim!E:E)} -> Online | T65: 2 | U65: 121.37 | V65: 0.05 | W65: 457 | X65: Credit Card | Y65: 230.603 | Z65: {=XLOOKUP(M65,Product_Dim!A:A,Product_Dim!B:B)} -> Face Foundation Kit
A66: SALE64 | B66: 45914 | C66: September | D66: =YEAR(B66) -> 2025 | E66: CUST1255 | F66: 21 | G66: =IF(F66<18,"Under 18", IF(F66<=25,"18-25", IF(F66<=35,"26-35", IF(F66<=45,"36-45", IF(F66<=55,"46-55", IF(F66<=65,"56-65","65+")))))) -> 18-25 | H66: {=XLOOKUP(E66,Customer_Dim!A:A,Customer_Dim!D:D)} -> Male | I66: {=XLOOKUP(E66,Customer_Dim!A:A,Customer_Dim!H:H)} -> Gold | J66: {=XLOOKUP(E66,Customer_Dim!A:A,Customer_Dim!E:E)} -> Jasonton | K66: {=XLOOKUP(E66,Customer_Dim!A:A,Customer_Dim!F:F)} -> Ohio | L66: {=XLOOKUP(Q66,Store_Dim!A:A,Store_Dim!C:C)} -> East | M66: PROD53 | N66: {=XLOOKUP(M66,Product_Dim!A:A,Product_Dim!C:C)} -> Clothing | O66: {=XLOOKUP(M66,Product_Dim!A:A,Product_Dim!D:D)} -> Bottoms | P66: Hamilton, Woods and Walker | Q66: STORE10 | R66: {=XLOOKUP(Q66,Store_Dim!A:A,Store_Dim!B:B)} -> Hill, Wagner and Ballard | S66: {=XLOOKUP(Q66,Store_Dim!A:A,Store_Dim!E:E)} -> Online | T66: 3 | U66: 480.06 | V66: 0.01 | W66: 125 | X66: Credit Card | Y66: =(U66*T66)-((U66*T66)*V66) -> 1425.7782 | Z66: {=XLOOKUP(M66,Product_Dim!A:A,Product_Dim!B:B)} -> Men's Track Pants
A67: SALE65 | B67: 45290 | C67: December | D67: =YEAR(B67) -> 2023 | E67: CUST1162 | F67: 37 | G67: =IF(F67<18,"Under 18", IF(F67<=25,"18-25", IF(F67<=35,"26-35", IF(F67<=45,"36-45", IF(F67<=55,"46-55", IF(F67<=65,"56-65","65+")))))) -> 36-45 | H67: {=XLOOKUP(E67,Customer_Dim!A:A,Customer_Dim!D:D)} -> Male | I67: {=XLOOKUP(E67,Customer_Dim!A:A,Customer_Dim!H:H)} -> Silver | J67: {=XLOOKUP(E67,Customer_Dim!A:A,Customer_Dim!E:E)} -> Palmerbury | K67: {=XLOOKUP(E67,Customer_Dim!A:A,Customer_Dim!F:F)} -> Tennessee | L67: {=XLOOKUP(Q67,Store_Dim!A:A,Store_Dim!C:C)} -> North | M67: PROD99 | N67: {=XLOOKUP(M67,Product_Dim!A:A,Product_Dim!C:C)} -> Home | O67: {=XLOOKUP(M67,Product_Dim!A:A,Product_Dim!D:D)} -> Kitchen | P67: Campbell Ltd | Q67: STORE17 | R67: {=XLOOKUP(Q67,Store_Dim!A:A,Store_Dim!B:B)} -> Holloway Ltd | S67: {=XLOOKUP(Q67,Store_Dim!A:A,Store_Dim!E:E)} -> Flagship | T67: 2 | U67: 856.57 | V67: 0.24 | W67: 146 | X67: Credit Card | Y67: 1301.9864 | Z67: {=XLOOKUP(M67,Product_Dim!A:A,Product_Dim!B:B)} -> Stainless Steel Cookware Set
A68: SALE66 | B68: 45213 | C68: October | D68: =YEAR(B68) -> 2023 | E68: CUST1269 | F68: 45 | G68: =IF(F68<18,"Under 18", IF(F68<=25,"18-25", IF(F68<=35,"26-35", IF(F68<=45,"36-45", IF(F68<=55,"46-55", IF(F68<=65,"56-65","65+")))))) -> 36-45 | H68: {=XLOOKUP(E68,Customer_Dim!A:A,Customer_Dim!D:D)} -> Female | I68: {=XLOOKUP(E68,Customer_Dim!A:A,Customer_Dim!H:H)} -> Silver | J68: {=XLOOKUP(E68,Customer_Dim!A:A,Customer_Dim!E:E)} -> Emilytown | K68: {=XLOOKUP(E68,Customer_Dim!A:A,Customer_Dim!F:F)} -> California | L68: {=XLOOKUP(Q68,Store_Dim!A:A,Store_Dim!C:C)} -> South | M68: PROD77 | N68: {=XLOOKUP(M68,Product_Dim!A:A,Product_Dim!C:C)} -> Electronics | O68: {=XLOOKUP(M68,Product_Dim!A:A,Product_Dim!D:D)} -> Appliances | P68: White, Reeves and Woods | Q68: STORE2 | R68: {=XLOOKUP(Q68,Store_Dim!A:A,Store_Dim!B:B)} -> Black-Horn | S68: {=XLOOKUP(Q68,Store_Dim!A:A,Store_Dim!E:E)} -> Outlet | T68: 4 | U68: 814.25 | V68: 0.18 | W68: 104 | X68: Credit Card | Y68: 2670.74 | Z68: {=XLOOKUP(M68,Product_Dim!A:A,Product_Dim!B:B)} -> WiFi Mesh Router
A69: SALE67 | B69: 45255 | C69: November | D69: =YEAR(B69) -> 2023 | E69: CUST1483 | F69: 48 | G69: =IF(F69<18,"Under 18", IF(F69<=25,"18-25", IF(F69<=35,"26-35", IF(F69<=45,"36-45", IF(F69<=55,"46-55", IF(F69<=65,"56-65","65+")))))) -> 46-55 | H69: {=XLOOKUP(E69,Customer_Dim!A:A,Customer_Dim!D:D)} -> Male | I69: {=XLOOKUP(E69,Customer_Dim!A:A,Customer_Dim!H:H)} -> Gold | J69: {=XLOOKUP(E69,Customer_Dim!A:A,Customer_Dim!E:E)} -> East Rodney | K69: {=XLOOKUP(E69,Customer_Dim!A:A,Customer_Dim!F:F)} -> Nevada | L69: {=XLOOKUP(Q69,Store_Dim!A:A,Store_Dim!C:C)} -> South | M69: PROD12 | N69: {=XLOOKUP(M69,Product_Dim!A:A,Product_Dim!C:C)} -> Beauty | O69: {=XLOOKUP(M69,Product_Dim!A:A,Product_Dim!D:D)} -> Haircare | P69: Rice LLC | Q69: STORE2 | R69: {=XLOOKUP(Q69,Store_Dim!A:A,Store_Dim!B:B)} -> Black-Horn | S69: {=XLOOKUP(Q69,Store_Dim!A:A,Store_Dim!E:E)} -> Outlet | T69: 1 | U69: 989.17 | V69: 0.2 | W69: 460 | X69: PayPal | Y69: 791.336 | Z69: {=XLOOKUP(M69,Product_Dim!A:A,Product_Dim!B:B)} -> Hair Strengthening Shampoo
A70: SALE68 | B70: 45270 | C70: December | D70: =YEAR(B70) -> 2023 | E70: CUST1372 | F70: 28 | G70: =IF(F70<18,"Under 18", IF(F70<=25,"18-25", IF(F70<=35,"26-35", IF(F70<=45,"36-45", IF(F70<=55,"46-55", IF(F70<=65,"56-65","65+")))))) -> 26-35 | H70: {=XLOOKUP(E70,Customer_Dim!A:A,Customer_Dim!D:D)} -> Male | I70: {=XLOOKUP(E70,Customer_Dim!A:A,Customer_Dim!H:H)} -> Bronze | J70: {=XLOOKUP(E70,Customer_Dim!A:A,Customer_Dim!E:E)} -> Vincentside | K70: {=XLOOKUP(E70,Customer_Dim!A:A,Customer_Dim!F:F)} -> Ohio | L70: {=XLOOKUP(Q70,Store_Dim!A:A,Store_Dim!C:C)} -> East | M70: PROD72 | N70: {=XLOOKUP(M70,Product_Dim!A:A,Product_Dim!C:C)} -> Sports | O70: {=XLOOKUP(M70,Product_Dim!A:A,Product_Dim!D:D)} -> Fitness | P70: Davis PLC | Q70: STORE10 | R70: {=XLOOKUP(Q70,Store_Dim!A:A,Store_Dim!B:B)} -> Hill, Wagner and Ballard | S70: {=XLOOKUP(Q70,Store_Dim!A:A,Store_Dim!E:E)} -> Online | T70: 4 | U70: 62.48 | V70: 0.18 | W70: 300 | X70: Credit Card | Y70: 204.9344 | Z70: {=XLOOKUP(M70,Product_Dim!A:A,Product_Dim!B:B)} -> Professional Jump Rope
A71: SALE69 | B71: 45897 | C71: August | D71: =YEAR(B71) -> 2025 | E71: CUST1423 | F71: 35 | G71: =IF(F71<18,"Under 18", IF(F71<=25,"18-25", IF(F71<=35,"26-35", IF(F71<=45,"36-45", IF(F71<=55,"46-55", IF(F71<=65,"56-65","65+")))))) -> 26-35 | H71: {=XLOOKUP(E71,Customer_Dim!A:A,Customer_Dim!D:D)} -> Male | I71: {=XLOOKUP(E71,Customer_Dim!A:A,Customer_Dim!H:H)} -> Silver | J71: {=XLOOKUP(E71,Customer_Dim!A:A,Customer_Dim!E:E)} -> New Katherine | K71: {=XLOOKUP(E71,Customer_Dim!A:A,Customer_Dim!F:F)} -> Kansas | L71: {=XLOOKUP(Q71,Store_Dim!A:A,Store_Dim!C:C)} -> West | M71: PROD13 | N71: {=XLOOKUP(M71,Product_Dim!A:A,Product_Dim!C:C)} -> Electronics | O71: {=XLOOKUP(M71,Product_Dim!A:A,Product_Dim!D:D)} -> Accessories | P71: Dawson-Perkins | Q71: STORE16 | R71: {=XLOOKUP(Q71,Store_Dim!A:A,Store_Dim!B:B)} -> Frederick-Wright | S71: {=XLOOKUP(Q71,Store_Dim!A:A,Store_Dim!E:E)} -> Flagship | T71: 4 | U71: 561.24 | V71: 0.24 | W71: 453 | X71: Credit Card | Y71: 1706.1696 | Z71: {=XLOOKUP(M71,Product_Dim!A:A,Product_Dim!B:B)} -> USB-C Fast Charger
A72: SALE70 | B72: 45849 | C72: July | D72: =YEAR(B72) -> 2025 | E72: CUST1058 | F72: 51 | G72: =IF(F72<18,"Under 18", IF(F72<=25,"18-25", IF(F72<=35,"26-35", IF(F72<=45,"36-45", IF(F72<=55,"46-55", IF(F72<=65,"56-65","65+")))))) -> 46-55 | H72: {=XLOOKUP(E72,Customer_Dim!A:A,Customer_Dim!D:D)} -> Male | I72: {=XLOOKUP(E72,Customer_Dim!A:A,Customer_Dim!H:H)} -> Platinum | J72: {=XLOOKUP(E72,Customer_Dim!A:A,Customer_Dim!E:E)} -> Snowmouth | K72: {=XLOOKUP(E72,Customer_Dim!A:A,Customer_Dim!F:F)} -> Maryland | L72: {=XLOOKUP(Q72,Store_Dim!A:A,Store_Dim!C:C)} -> North | M72: PROD60 | N72: {=XLOOKUP(M72,Product_Dim!A:A,Product_Dim!C:C)} -> Beauty | O72: {=XLOOKUP(M72,Product_Dim!A:A,Product_Dim!D:D)} -> Fragrance | P72: Gibson, Green and Lopez | Q72: STORE5 | R72: {=XLOOKUP(Q72,Store_Dim!A:A,Store_Dim!B:B)} -> Gray Ltd | S72: {=XLOOKUP(Q72,Store_Dim!A:A,Store_Dim!E:E)} -> Outlet | T72: 3 | U72: 92.24 | V72: 0.28 | W72: 444 | X72: COD | Y72: =(U72*T72)-((U72*T72)*V72) -> 199.2384 | Z72: {=XLOOKUP(M72,Product_Dim!A:A,Product_Dim!B:B)} -> Luxury Perfume Spray
A73: SALE71 | B73: 45889 | C73: August | D73: =YEAR(B73) -> 2025 | E73: CUST1168 | F73: 36 | G73: =IF(F73<18,"Under 18", IF(F73<=25,"18-25", IF(F73<=35,"26-35", IF(F73<=45,"36-45", IF(F73<=55,"46-55", IF(F73<=65,"56-65","65+")))))) -> 36-45 | H73: {=XLOOKUP(E73,Customer_Dim!A:A,Customer_Dim!D:D)} -> Female | I73: {=XLOOKUP(E73,Customer_Dim!A:A,Customer_Dim!H:H)} -> Platinum | J73: {=XLOOKUP(E73,Customer_Dim!A:A,Customer_Dim!E:E)} -> Robertview | K73: {=XLOOKUP(E73,Customer_Dim!A:A,Customer_Dim!F:F)} -> Florida | L73: {=XLOOKUP(Q73,Store_Dim!A:A,Store_Dim!C:C)} -> North | M73: PROD72 | N73: {=XLOOKUP(M73,Product_Dim!A:A,Product_Dim!C:C)} -> Sports | O73: {=XLOOKUP(M73,Product_Dim!A:A,Product_Dim!D:D)} -> Fitness | P73: Davis PLC | Q73: STORE1 | R73: {=XLOOKUP(Q73,Store_Dim!A:A,Store_Dim!B:B)} -> Martinez, Adkins and Johnson | S73: {=XLOOKUP(Q73,Store_Dim!A:A,Store_Dim!E:E)} -> Flagship | T73: 2 | U73: 668.3 | V73: 0.07 | W73: 300 | X73: Credit Card | Y73: 1243.038 | Z73: {=XLOOKUP(M73,Product_Dim!A:A,Product_Dim!B:B)} -> Professional Jump Rope
A74: SALE72 | B74: 45533 | C74: August | D74: =YEAR(B74) -> 2024 | E74: CUST1409 | F74: 55 | G74: =IF(F74<18,"Under 18", IF(F74<=25,"18-25", IF(F74<=35,"26-35", IF(F74<=45,"36-45", IF(F74<=55,"46-55", IF(F74<=65,"56-65","65+")))))) -> 46-55 | H74: {=XLOOKUP(E74,Customer_Dim!A:A,Customer_Dim!D:D)} -> Male | I74: {=XLOOKUP(E74,Customer_Dim!A:A,Customer_Dim!H:H)} -> Gold | J74: {=XLOOKUP(E74,Customer_Dim!A:A,Customer_Dim!E:E)} -> Kathleenport | K74: {=XLOOKUP(E74,Customer_Dim!A:A,Customer_Dim!F:F)} -> Wyoming | L74: {=XLOOKUP(Q74,Store_Dim!A:A,Store_Dim!C:C)} -> North | M74: PROD38 | N74: {=XLOOKUP(M74,Product_Dim!A:A,Product_Dim!C:C)} -> Sports | O74: {=XLOOKUP(M74,Product_Dim!A:A,Product_Dim!D:D)} -> Outdoor | P74: Sims-Smith | Q74: STORE5 | R74: {=XLOOKUP(Q74,Store_Dim!A:A,Store_Dim!B:B)} -> Gray Ltd | S74: {=XLOOKUP(Q74,Store_Dim!A:A,Store_Dim!E:E)} -> Outlet | T74: 1 | U74: 553.82 | V74: 0.09 | W74: 394 | X74: Credit Card | Y74: 503.9762 | Z74: {=XLOOKUP(M74,Product_Dim!A:A,Product_Dim!B:B)} -> Sports Water Hydration Pack
A75: SALE73 | B75: 45626 | C75: November | D75: =YEAR(B75) -> 2024 | E75: CUST1037 | F75: 27 | G75: =IF(F75<18,"Under 18", IF(F75<=25,"18-25", IF(F75<=35,"26-35", IF(F75<=45,"36-45", IF(F75<=55,"46-55", IF(F75<=65,"56-65","65+")))))) -> 26-35 | H75: {=XLOOKUP(E75,Customer_Dim!A:A,Customer_Dim!D:D)} -> Female | I75: Platinum | J75: {=XLOOKUP(E75,Customer_Dim!A:A,Customer_Dim!E:E)} -> Brendastad | K75: {=XLOOKUP(E75,Customer_Dim!A:A,Customer_Dim!F:F)} -> South Dakota | L75: {=XLOOKUP(Q75,Store_Dim!A:A,Store_Dim!C:C)} -> South | M75: PROD45 | N75: {=XLOOKUP(M75,Product_Dim!A:A,Product_Dim!C:C)} -> Sports | O75: {=XLOOKUP(M75,Product_Dim!A:A,Product_Dim!D:D)} -> Team Sports | P75: Bridges, Banks and Cummings | Q75: STORE11 | R75: {=XLOOKUP(Q75,Store_Dim!A:A,Store_Dim!B:B)} -> Aguirre-Keller | S75: {=XLOOKUP(Q75,Store_Dim!A:A,Store_Dim!E:E)} -> Online | T75: 2 | U75: 556.43 | V75: 0.13 | W75: 114 | X75: Credit Card | Y75: 968.1882 | Z75: {=XLOOKUP(M75,Product_Dim!A:A,Product_Dim!B:B)} -> High-Grip Football
A76: SALE74 | B76: 45942 | C76: October | D76: =YEAR(B76) -> 2025 | E76: CUST1273 | F76: 23 | G76: =IF(F76<18,"Under 18", IF(F76<=25,"18-25", IF(F76<=35,"26-35", IF(F76<=45,"36-45", IF(F76<=55,"46-55", IF(F76<=65,"56-65","65+")))))) -> 18-25 | H76: {=XLOOKUP(E76,Customer_Dim!A:A,Customer_Dim!D:D)} -> Male | I76: {=XLOOKUP(E76,Customer_Dim!A:A,Customer_Dim!H:H)} -> Bronze | J76: {=XLOOKUP(E76,Customer_Dim!A:A,Customer_Dim!E:E)} -> North Roy | K76: {=XLOOKUP(E76,Customer_Dim!A:A,Customer_Dim!F:F)} -> Mississippi | L76: {=XLOOKUP(Q76,Store_Dim!A:A,Store_Dim!C:C)} -> West | M76: PROD20 | N76: {=XLOOKUP(M76,Product_Dim!A:A,Product_Dim!C:C)} -> Sports | O76: {=XLOOKUP(M76,Product_Dim!A:A,Product_Dim!D:D)} -> Accessories | P76: Soto-Ellis | Q76: STORE8 | R76: {=XLOOKUP(Q76,Store_Dim!A:A,Store_Dim!B:B)} -> Bean, Jones and Park | S76: {=XLOOKUP(Q76,Store_Dim!A:A,Store_Dim!E:E)} -> Online | T76: 1 | U76: 184.98 | V76: 0.1 | W76: 273.86258 | X76: COD | Y76: 166.482 | Z76: {=XLOOKUP(M76,Product_Dim!A:A,Product_Dim!B:B)} -> Outdoor Sports Water Bottle
A77: SALE75 | B77: 45500 | C77: July | D77: =YEAR(B77) -> 2024 | E77: CUST1035 | F77: 52 | G77: =IF(F77<18,"Under 18", IF(F77<=25,"18-25", IF(F77<=35,"26-35", IF(F77<=45,"36-45", IF(F77<=55,"46-55", IF(F77<=65,"56-65","65+")))))) -> 46-55 | H77: {=XLOOKUP(E77,Customer_Dim!A:A,Customer_Dim!D:D)} -> Male | I77: {=XLOOKUP(E77,Customer_Dim!A:A,Customer_Dim!H:H)} -> Silver | J77: {=XLOOKUP(E77,Customer_Dim!A:A,Customer_Dim!E:E)} -> Robertberg | K77: {=XLOOKUP(E77,Customer_Dim!A:A,Customer_Dim!F:F)} -> North Dakota | L77: {=XLOOKUP(Q77,Store_Dim!A:A,Store_Dim!C:C)} -> North | M77: PROD97 | N77: {=XLOOKUP(M77,Product_Dim!A:A,Product_Dim!C:C)} -> Sports | O77: {=XLOOKUP(M77,Product_Dim!A:A,Product_Dim!D:D)} -> Team Sports | P77: Khan LLC | Q77: STORE12 | R77: {=XLOOKUP(Q77,Store_Dim!A:A,Store_Dim!B:B)} -> Thomas, Bridges and Harris | S77: {=XLOOKUP(Q77,Store_Dim!A:A,Store_Dim!E:E)} -> Online | T77: 4 | U77: 700.18 | V77: 0.23 | W77: 471 | X77: Credit Card | Y77: 2156.5544 | Z77: {=XLOOKUP(M77,Product_Dim!A:A,Product_Dim!B:B)} -> Cricket Bat
A78: SALE76 | B78: 45285 | C78: December | D78: =YEAR(B78) -> 2023 | E78: CUST1019 | F78: 46 | G78: =IF(F78<18,"Under 18", IF(F78<=25,"18-25", IF(F78<=35,"26-35", IF(F78<=45,"36-45", IF(F78<=55,"46-55", IF(F78<=65,"56-65","65+")))))) -> 46-55 | H78: {=XLOOKUP(E78,Customer_Dim!A:A,Customer_Dim!D:D)} -> Female | I78: {=XLOOKUP(E78,Customer_Dim!A:A,Customer_Dim!H:H)} -> Platinum | J78: {=XLOOKUP(E78,Customer_Dim!A:A,Customer_Dim!E:E)} -> Gonzalezfort | K78: {=XLOOKUP(E78,Customer_Dim!A:A,Customer_Dim!F:F)} -> New Jersey | L78: {=XLOOKUP(Q78,Store_Dim!A:A,Store_Dim!C:C)} -> East | M78: PROD76 | N78: {=XLOOKUP(M78,Product_Dim!A:A,Product_Dim!C:C)} -> Electronics | O78: {=XLOOKUP(M78,Product_Dim!A:A,Product_Dim!D:D)} -> Computer | P78: Larson Ltd | Q78: STORE10 | R78: {=XLOOKUP(Q78,Store_Dim!A:A,Store_Dim!B:B)} -> Hill, Wagner and Ballard | S78: {=XLOOKUP(Q78,Store_Dim!A:A,Store_Dim!E:E)} -> Online | T78: 2 | U78: 686.31 | V78: 0.25 | W78: 320 | X78: Credit Card | Y78: 1029.465 | Z78: {=XLOOKUP(M78,Product_Dim!A:A,Product_Dim!B:B)} -> Wireless Mouse
A79: SALE77 | B79: 45800 | C79: May | D79: =YEAR(B79) -> 2025 | E79: CUST1007 | F79: 29 | G79: =IF(F79<18,"Under 18", IF(F79<=25,"18-25", IF(F79<=35,"26-35", IF(F79<=45,"36-45", IF(F79<=55,"46-55", IF(F79<=65,"56-65","65+")))))) -> 26-35 | H79: {=XLOOKUP(E79,Customer_Dim!A:A,Customer_Dim!D:D)} -> Female | I79: {=XLOOKUP(E79,Customer_Dim!A:A,Customer_Dim!H:H)} -> Bronze | J79: {=XLOOKUP(E79,Customer_Dim!A:A,Customer_Dim!E:E)} -> West Pamelafurt | K79: {=XLOOKUP(E79,Customer_Dim!A:A,Customer_Dim!F:F)} -> West Virginia | L79: {=XLOOKUP(Q79,Store_Dim!A:A,Store_Dim!C:C)} -> North | M79: PROD67 | N79: {=XLOOKUP(M79,Product_Dim!A:A,Product_Dim!C:C)} -> Electronics | O79: {=XLOOKUP(M79,Product_Dim!A:A,Product_Dim!D:D)} -> Accessories | P79: Flores-Davis | Q79: STORE15 | R79: {=XLOOKUP(Q79,Store_Dim!A:A,Store_Dim!B:B)} -> Shelton PLC | S79: {=XLOOKUP(Q79,Store_Dim!A:A,Store_Dim!E:E)} -> Flagship | T79: 1 | U79: 687.82 | V79: 0.27 | W79: 476 | X79: COD | Y79: 502.1086 | Z79: {=XLOOKUP(M79,Product_Dim!A:A,Product_Dim!B:B)} -> Smart LED Light Strip
A80: SALE78 | B80: 45609 | C80: November | D80: =YEAR(B80) -> 2024 | E80: CUST1221 | F80: 38 | G80: =IF(F80<18,"Under 18", IF(F80<=25,"18-25", IF(F80<=35,"26-35", IF(F80<=45,"36-45", IF(F80<=55,"46-55", IF(F80<=65,"56-65","65+")))))) -> 36-45 | H80: {=XLOOKUP(E80,Customer_Dim!A:A,Customer_Dim!D:D)} -> Male | I80: {=XLOOKUP(E80,Customer_Dim!A:A,Customer_Dim!H:H)} -> Platinum | J80: {=XLOOKUP(E80,Customer_Dim!A:A,Customer_Dim!E:E)} -> Maybury | K80: {=XLOOKUP(E80,Customer_Dim!A:A,Customer_Dim!F:F)} -> Georgia | L80: {=XLOOKUP(Q80,Store_Dim!A:A,Store_Dim!C:C)} -> West | M80: PROD83 | N80: {=XLOOKUP(M80,Product_Dim!A:A,Product_Dim!C:C)} -> Beauty | O80: {=XLOOKUP(M80,Product_Dim!A:A,Product_Dim!D:D)} -> Skincare | P80: Butler Group | Q80: STORE8 | R80: {=XLOOKUP(Q80,Store_Dim!A:A,Store_Dim!B:B)} -> Bean, Jones and Park | S80: {=XLOOKUP(Q80,Store_Dim!A:A,Store_Dim!E:E)} -> Online | T80: 2 | U80: 900.55 | V80: 0.16 | W80: 159 | X80: Credit Card | Y80: 1512.924 | Z80: {=XLOOKUP(M80,Product_Dim!A:A,Product_Dim!B:B)} -> Hydrating Face Cleanser
A81: SALE79 | B81: 45268 | C81: December | D81: =YEAR(B81) -> 2023 | E81: CUST1115 | F81: 53 | G81: =IF(F81<18,"Under 18", IF(F81<=25,"18-25", IF(F81<=35,"26-35", IF(F81<=45,"36-45", IF(F81<=55,"46-55", IF(F81<=65,"56-65","65+")))))) -> 46-55 | H81: {=XLOOKUP(E81,Customer_Dim!A:A,Customer_Dim!D:D)} -> Female | I81: {=XLOOKUP(E81,Customer_Dim!A:A,Customer_Dim!H:H)} -> Platinum | J81: {=XLOOKUP(E81,Customer_Dim!A:A,Customer_Dim!E:E)} -> North Curtischester | K81: {=XLOOKUP(E81,Customer_Dim!A:A,Customer_Dim!F:F)} -> North Dakota | L81: {=XLOOKUP(Q81,Store_Dim!A:A,Store_Dim!C:C)} -> South | M81: PROD21 | N81: {=XLOOKUP(M81,Product_Dim!A:A,Product_Dim!C:C)} -> Home | O81: {=XLOOKUP(M81,Product_Dim!A:A,Product_Dim!D:D)} -> Storage | P81: Gardner-Montes | Q81: STORE2 | R81: {=XLOOKUP(Q81,Store_Dim!A:A,Store_Dim!B:B)} -> Black-Horn | S81: {=XLOOKUP(Q81,Store_Dim!A:A,Store_Dim!E:E)} -> Outlet | T81: 1 | U81: 341.17 | V81: 0.15 | W81: 76 | X81: Credit Card | Y81: 289.9945 | Z81: {=XLOOKUP(M81,Product_Dim!A:A,Product_Dim!B:B)} -> Multi-Purpose Storage Box
A82: SALE80 | B82: 45885 | C82: August | D82: =YEAR(B82) -> 2025 | E82: CUST1176 | F82: 48 | G82: =IF(F82<18,"Under 18", IF(F82<=25,"18-25", IF(F82<=35,"26-35", IF(F82<=45,"36-45", IF(F82<=55,"46-55", IF(F82<=65,"56-65","65+")))))) -> 46-55 | H82: {=XLOOKUP(E82,Customer_Dim!A:A,Customer_Dim!D:D)} -> Male | I82: {=XLOOKUP(E82,Customer_Dim!A:A,Customer_Dim!H:H)} -> Silver | J82: {=XLOOKUP(E82,Customer_Dim!A:A,Customer_Dim!E:E)} -> Anabury | K82: {=XLOOKUP(E82,Customer_Dim!A:A,Customer_Dim!F:F)} -> Vermont | L82: {=XLOOKUP(Q82,Store_Dim!A:A,Store_Dim!C:C)} -> West | M82: PROD52 | N82: {=XLOOKUP(M82,Product_Dim!A:A,Product_Dim!C:C)} -> Sports | O82: {=XLOOKUP(M82,Product_Dim!A:A,Product_Dim!D:D)} -> Team Sports | P82: Harris Inc | Q82: STORE8 | R82: {=XLOOKUP(Q82,Store_Dim!A:A,Store_Dim!B:B)} -> Bean, Jones and Park | S82: {=XLOOKUP(Q82,Store_Dim!A:A,Store_Dim!E:E)} -> Online | T82: 1 | U82: 442.27 | V82: 0.06 | W82: 82 | X82: COD | Y82: 415.7338 | Z82: {=XLOOKUP(M82,Product_Dim!A:A,Product_Dim!B:B)} -> Rugby Ball
A83: SALE81 | B83: 45616 | C83: November | D83: =YEAR(B83) -> 2024 | E83: CUST1253 | F83: 32 | G83: =IF(F83<18,"Under 18", IF(F83<=25,"18-25", IF(F83<=35,"26-35", IF(F83<=45,"36-45", IF(F83<=55,"46-55", IF(F83<=65,"56-65","65+")))))) -> 26-35 | H83: {=XLOOKUP(E83,Customer_Dim!A:A,Customer_Dim!D:D)} -> Male | I83: {=XLOOKUP(E83,Customer_Dim!A:A,Customer_Dim!H:H)} -> Bronze | J83: {=XLOOKUP(E83,Customer_Dim!A:A,Customer_Dim!E:E)} -> New Maria | K83: {=XLOOKUP(E83,Customer_Dim!A:A,Customer_Dim!F:F)} -> Wisconsin | L83: {=XLOOKUP(Q83,Store_Dim!A:A,Store_Dim!C:C)} -> South | M83: PROD71 | N83: {=XLOOKUP(M83,Product_Dim!A:A,Product_Dim!C:C)} -> Beauty | O83: {=XLOOKUP(M83,Product_Dim!A:A,Product_Dim!D:D)} -> Haircare | P83: Hopkins Ltd | Q83: STORE9 | R83: {=XLOOKUP(Q83,Store_Dim!A:A,Store_Dim!B:B)} -> Moore, Padilla and Butler | S83: {=XLOOKUP(Q83,Store_Dim!A:A,Store_Dim!E:E)} -> Flagship | T83: 1 | U83: 363.73 | V83: 0.25 | W83: 383 | X83: PayPal | Y83: 272.7975 | Z83: {=XLOOKUP(M83,Product_Dim!A:A,Product_Dim!B:B)} -> Hair Repair Oil Treatment
A84: SALE82 | B84: 45518 | C84: August | D84: =YEAR(B84) -> 2024 | E84: CUST1378 | F84: 44 | G84: =IF(F84<18,"Under 18", IF(F84<=25,"18-25", IF(F84<=35,"26-35", IF(F84<=45,"36-45", IF(F84<=55,"46-55", IF(F84<=65,"56-65","65+")))))) -> 36-45 | H84: {=XLOOKUP(E84,Customer_Dim!A:A,Customer_Dim!D:D)} -> Female | I84: {=XLOOKUP(E84,Customer_Dim!A:A,Customer_Dim!H:H)} -> Bronze | J84: {=XLOOKUP(E84,Customer_Dim!A:A,Customer_Dim!E:E)} -> Fischerborough | K84: {=XLOOKUP(E84,Customer_Dim!A:A,Customer_Dim!F:F)} -> Delaware | L84: {=XLOOKUP(Q84,Store_Dim!A:A,Store_Dim!C:C)} -> North | M84: PROD91 | N84: {=XLOOKUP(M84,Product_Dim!A:A,Product_Dim!C:C)} -> Clothing | O84: {=XLOOKUP(M84,Product_Dim!A:A,Product_Dim!D:D)} -> Footwear | P84: Smith-Charles | Q84: STORE17 | R84: {=XLOOKUP(Q84,Store_Dim!A:A,Store_Dim!B:B)} -> Holloway Ltd | S84: {=XLOOKUP(Q84,Store_Dim!A:A,Store_Dim!E:E)} -> Flagship | T84: 2 | U84: 601.33 | V84: 0.16 | W84: 496 | X84: PayPal | Y84: 1010.2344 | Z84: {=XLOOKUP(M84,Product_Dim!A:A,Product_Dim!B:B)} -> Women's High Heels
A85: SALE83 | B85: 45427 | C85: May | D85: =YEAR(B85) -> 2024 | E85: CUST1403 | F85: 34 | G85: =IF(F85<18,"Under 18", IF(F85<=25,"18-25", IF(F85<=35,"26-35", IF(F85<=45,"36-45", IF(F85<=55,"46-55", IF(F85<=65,"56-65","65+")))))) -> 26-35 | H85: {=XLOOKUP(E85,Customer_Dim!A:A,Customer_Dim!D:D)} -> Male | I85: {=XLOOKUP(E85,Customer_Dim!A:A,Customer_Dim!H:H)} -> Bronze | J85: {=XLOOKUP(E85,Customer_Dim!A:A,Customer_Dim!E:E)} -> Lake Lisaland | K85: {=XLOOKUP(E85,Customer_Dim!A:A,Customer_Dim!F:F)} -> Louisiana | L85: {=XLOOKUP(Q85,Store_Dim!A:A,Store_Dim!C:C)} -> East | M85: PROD17 | N85: {=XLOOKUP(M85,Product_Dim!A:A,Product_Dim!C:C)} -> Sports | O85: {=XLOOKUP(M85,Product_Dim!A:A,Product_Dim!D:D)} -> Accessories | P85: Ford, Murphy and Wilson | Q85: STORE18 | R85: {=XLOOKUP(Q85,Store_Dim!A:A,Store_Dim!B:B)} -> Guerrero-Schmitt | S85: {=XLOOKUP(Q85,Store_Dim!A:A,Store_Dim!E:E)} -> Flagship | T85: 4 | U85: 34.39 | V85: 0.03 | W85: 367 | X85: PayPal | Y85: 133.4332 | Z85: {=XLOOKUP(M85,Product_Dim!A:A,Product_Dim!B:B)} -> Soccer Training Cone Set
A86: SALE84 | B86: 45268 | C86: December | D86: =YEAR(B86) -> 2023 | E86: CUST1423 | F86: 35 | G86: =IF(F86<18,"Under 18", IF(F86<=25,"18-25", IF(F86<=35,"26-35", IF(F86<=45,"36-45", IF(F86<=55,"46-55", IF(F86<=65,"56-65","65+")))))) -> 26-35 | H86: {=XLOOKUP(E86,Customer_Dim!A:A,Customer_Dim!D:D)} -> Male | I86: {=XLOOKUP(E86,Customer_Dim!A:A,Customer_Dim!H:H)} -> Silver | J86: {=XLOOKUP(E86,Customer_Dim!A:A,Customer_Dim!E:E)} -> New Katherine | K86: {=XLOOKUP(E86,Customer_Dim!A:A,Customer_Dim!F:F)} -> Kansas | L86: {=XLOOKUP(Q86,Store_Dim!A:A,Store_Dim!C:C)} -> North | M86: PROD46 | N86: {=XLOOKUP(M86,Product_Dim!A:A,Product_Dim!C:C)} -> Clothing | O86: {=XLOOKUP(M86,Product_Dim!A:A,Product_Dim!D:D)} -> Outerwear | P86: Kelly, Smith and Perez | Q86: STORE17 | R86: {=XLOOKUP(Q86,Store_Dim!A:A,Store_Dim!B:B)} -> Holloway Ltd | S86: {=XLOOKUP(Q86,Store_Dim!A:A,Store_Dim!E:E)} -> Flagship | T86: 1 | U86: 773.57 | V86: 0.05 | W86: 296 | X86: COD | Y86: =(U86*T86)-((U86*T86)*V86) -> 734.8915 | Z86: {=XLOOKUP(M86,Product_Dim!A:A,Product_Dim!B:B)} -> Men's Winter Jacket
A87: SALE85 | B87: 45282 | C87: December | D87: =YEAR(B87) -> 2023 | E87: CUST1054 | F87: 24 | G87: =IF(F87<18,"Under 18", IF(F87<=25,"18-25", IF(F87<=35,"26-35", IF(F87<=45,"36-45", IF(F87<=55,"46-55", IF(F87<=65,"56-65","65+")))))) -> 18-25 | H87: {=XLOOKUP(E87,Customer_Dim!A:A,Customer_Dim!D:D)} -> Male | I87: {=XLOOKUP(E87,Customer_Dim!A:A,Customer_Dim!H:H)} -> Platinum | J87: {=XLOOKUP(E87,Customer_Dim!A:A,Customer_Dim!E:E)} -> Christopherland | K87: {=XLOOKUP(E87,Customer_Dim!A:A,Customer_Dim!F:F)} -> Oklahoma | L87: {=XLOOKUP(Q87,Store_Dim!A:A,Store_Dim!C:C)} -> South | M87: PROD88 | N87: {=XLOOKUP(M87,Product_Dim!A:A,Product_Dim!C:C)} -> Sports | O87: {=XLOOKUP(M87,Product_Dim!A:A,Product_Dim!D:D)} -> Accessories | P87: Olsen-Daniels | Q87: STORE7 | R87: {=XLOOKUP(Q87,Store_Dim!A:A,Store_Dim!B:B)} -> Martinez-Mullins | S87: {=XLOOKUP(Q87,Store_Dim!A:A,Store_Dim!E:E)} -> Online | T87: 4 | U87: 127.1 | V87: 0.24 | W87: 232 | X87: COD | Y87: 386.384 | Z87: {=XLOOKUP(M87,Product_Dim!A:A,Product_Dim!B:B)} -> Sports Wrist Sweatbands
A88: SALE86 | B88: 45545 | C88: September | D88: =YEAR(B88) -> 2024 | E88: CUST1303 | F88: 23 | G88: =IF(F88<18,"Under 18", IF(F88<=25,"18-25", IF(F88<=35,"26-35", IF(F88<=45,"36-45", IF(F88<=55,"46-55", IF(F88<=65,"56-65","65+")))))) -> 18-25 | H88: {=XLOOKUP(E88,Customer_Dim!A:A,Customer_Dim!D:D)} -> Female | I88: {=XLOOKUP(E88,Customer_Dim!A:A,Customer_Dim!H:H)} -> Platinum | J88: {=XLOOKUP(E88,Customer_Dim!A:A,Customer_Dim!E:E)} -> East Johntown | K88: {=XLOOKUP(E88,Customer_Dim!A:A,Customer_Dim!F:F)} -> Delaware | L88: {=XLOOKUP(Q88,Store_Dim!A:A,Store_Dim!C:C)} -> North | M88: PROD20 | N88: {=XLOOKUP(M88,Product_Dim!A:A,Product_Dim!C:C)} -> Sports | O88: {=XLOOKUP(M88,Product_Dim!A:A,Product_Dim!D:D)} -> Accessories | P88: Soto-Ellis | Q88: STORE3 | R88: {=XLOOKUP(Q88,Store_Dim!A:A,Store_Dim!B:B)} -> Johnson-Wright | S88: {=XLOOKUP(Q88,Store_Dim!A:A,Store_Dim!E:E)} -> Outlet | T88: 3 | U88: 899.58 | V88: 0.28 | W88: 273.86258 | X88: PayPal | Y88: 1943.0928 | Z88: {=XLOOKUP(M88,Product_Dim!A:A,Product_Dim!B:B)} -> Outdoor Sports Water Bottle
A89: SALE87 | B89: 45755 | C89: April | D89: =YEAR(B89) -> 2025 | E89: CUST1327 | F89: 62 | G89: =IF(F89<18,"Under 18", IF(F89<=25,"18-25", IF(F89<=35,"26-35", IF(F89<=45,"36-45", IF(F89<=55,"46-55", IF(F89<=65,"56-65","65+")))))) -> 56-65 | H89: {=XLOOKUP(E89,Customer_Dim!A:A,Customer_Dim!D:D)} -> Female | I89: {=XLOOKUP(E89,Customer_Dim!A:A,Customer_Dim!H:H)} -> Bronze | J89: {=XLOOKUP(E89,Customer_Dim!A:A,Customer_Dim!E:E)} -> Kellybury | K89: {=XLOOKUP(E89,Customer_Dim!A:A,Customer_Dim!F:F)} -> New York | L89: {=XLOOKUP(Q89,Store_Dim!A:A,Store_Dim!C:C)} -> East | M89: PROD1 | N89: {=XLOOKUP(M89,Product_Dim!A:A,Product_Dim!C:C)} -> Clothing | O89: {=XLOOKUP(M89,Product_Dim!A:A,Product_Dim!D:D)} -> Tops | P89: Terry-Moore | Q89: STORE10 | R89: {=XLOOKUP(Q89,Store_Dim!A:A,Store_Dim!B:B)} -> Hill, Wagner and Ballard | S89: {=XLOOKUP(Q89,Store_Dim!A:A,Store_Dim!E:E)} -> Online | T89: 3 | U89: 964.39 | V89: 0.04 | W89: 181 | X89: Credit Card | Y89: 2777.4432 | Z89: {=XLOOKUP(M89,Product_Dim!A:A,Product_Dim!B:B)} -> Men's Graphic T-Shirt
A90: SALE88 | B90: 45588 | C90: October | D90: =YEAR(B90) -> 2024 | E90: CUST1183 | F90: 18 | G90: =IF(F90<18,"Under 18", IF(F90<=25,"18-25", IF(F90<=35,"26-35", IF(F90<=45,"36-45", IF(F90<=55,"46-55", IF(F90<=65,"56-65","65+")))))) -> 18-25 | H90: {=XLOOKUP(E90,Customer_Dim!A:A,Customer_Dim!D:D)} -> Male | I90: {=XLOOKUP(E90,Customer_Dim!A:A,Customer_Dim!H:H)} -> Platinum | J90: {=XLOOKUP(E90,Customer_Dim!A:A,Customer_Dim!E:E)} -> Port James | K90: {=XLOOKUP(E90,Customer_Dim!A:A,Customer_Dim!F:F)} -> New York | L90: {=XLOOKUP(Q90,Store_Dim!A:A,Store_Dim!C:C)} -> East | M90: PROD38 | N90: {=XLOOKUP(M90,Product_Dim!A:A,Product_Dim!C:C)} -> Sports | O90: {=XLOOKUP(M90,Product_Dim!A:A,Product_Dim!D:D)} -> Outdoor | P90: Sims-Smith | Q90: STORE0 | R90: {=XLOOKUP(Q90,Store_Dim!A:A,Store_Dim!B:B)} -> Rivera-Warner | S90: {=XLOOKUP(Q90,Store_Dim!A:A,Store_Dim!E:E)} -> Flagship | T90: 2 | U90: 217.83 | V90: 0.14 | W90: 394 | X90: PayPal | Y90: 374.6676 | Z90: {=XLOOKUP(M90,Product_Dim!A:A,Product_Dim!B:B)} -> Sports Water Hydration Pack
A91: SALE89 | B91: 45848 | C91: July | D91: =YEAR(B91) -> 2025 | E91: CUST1143 | F91: 46 | G91: =IF(F91<18,"Under 18", IF(F91<=25,"18-25", IF(F91<=35,"26-35", IF(F91<=45,"36-45", IF(F91<=55,"46-55", IF(F91<=65,"56-65","65+")))))) -> 46-55 | H91: {=XLOOKUP(E91,Customer_Dim!A:A,Customer_Dim!D:D)} -> Male | I91: {=XLOOKUP(E91,Customer_Dim!A:A,Customer_Dim!H:H)} -> Bronze | J91: {=XLOOKUP(E91,Customer_Dim!A:A,Customer_Dim!E:E)} -> Dwaynemouth | K91: {=XLOOKUP(E91,Customer_Dim!A:A,Customer_Dim!F:F)} -> Alabama | L91: {=XLOOKUP(Q91,Store_Dim!A:A,Store_Dim!C:C)} -> North | M91: PROD17 | N91: {=XLOOKUP(M91,Product_Dim!A:A,Product_Dim!C:C)} -> Sports | O91: {=XLOOKUP(M91,Product_Dim!A:A,Product_Dim!D:D)} -> Accessories | P91: Ford, Murphy and Wilson | Q91: STORE1 | R91: {=XLOOKUP(Q91,Store_Dim!A:A,Store_Dim!B:B)} -> Martinez, Adkins and Johnson | S91: {=XLOOKUP(Q91,Store_Dim!A:A,Store_Dim!E:E)} -> Flagship | T91: 4 | U91: 187.71 | V91: 0.06 | W91: 367 | X91: COD | Y91: 705.7896 | Z91: {=XLOOKUP(M91,Product_Dim!A:A,Product_Dim!B:B)} -> Soccer Training Cone Set
A92: SALE90 | B92: 45577 | C92: October | D92: =YEAR(B92) -> 2024 | E92: CUST1010 | F92: 53 | G92: =IF(F92<18,"Under 18", IF(F92<=25,"18-25", IF(F92<=35,"26-35", IF(F92<=45,"36-45", IF(F92<=55,"46-55", IF(F92<=65,"56-65","65+")))))) -> 46-55 | H92: {=XLOOKUP(E92,Customer_Dim!A:A,Customer_Dim!D:D)} -> Male | I92: {=XLOOKUP(E92,Customer_Dim!A:A,Customer_Dim!H:H)} -> Bronze | J92: {=XLOOKUP(E92,Customer_Dim!A:A,Customer_Dim!E:E)} -> Port Michaelburgh | K92: {=XLOOKUP(E92,Customer_Dim!A:A,Customer_Dim!F:F)} -> Pennsylvania | L92: {=XLOOKUP(Q92,Store_Dim!A:A,Store_Dim!C:C)} -> East | M92: PROD33 | N92: {=XLOOKUP(M92,Product_Dim!A:A,Product_Dim!C:C)} -> Home | O92: {=XLOOKUP(M92,Product_Dim!A:A,Product_Dim!D:D)} -> Decor | P92: Weiss-Watson | Q92: STORE18 | R92: {=XLOOKUP(Q92,Store_Dim!A:A,Store_Dim!B:B)} -> Guerrero-Schmitt | S92: {=XLOOKUP(Q92,Store_Dim!A:A,Store_Dim!E:E)} -> Flagship | T92: 2 | U92: 350.12 | V92: 0.12 | W92: 305 | X92: COD | Y92: 616.2112 | Z92: {=XLOOKUP(M92,Product_Dim!A:A,Product_Dim!B:B)} -> Modern Wall Clock
A93: SALE91 | B93: 45312 | C93: January | D93: =YEAR(B93) -> 2024 | E93: CUST1406 | F93: 23 | G93: =IF(F93<18,"Under 18", IF(F93<=25,"18-25", IF(F93<=35,"26-35", IF(F93<=45,"36-45", IF(F93<=55,"46-55", IF(F93<=65,"56-65","65+")))))) -> 18-25 | H93: {=XLOOKUP(E93,Customer_Dim!A:A,Customer_Dim!D:D)} -> Female | I93: {=XLOOKUP(E93,Customer_Dim!A:A,Customer_Dim!H:H)} -> Gold | J93: {=XLOOKUP(E93,Customer_Dim!A:A,Customer_Dim!E:E)} -> North Michaelfurt | K93: {=XLOOKUP(E93,Customer_Dim!A:A,Customer_Dim!F:F)} -> Wisconsin | L93: {=XLOOKUP(Q93,Store_Dim!A:A,Store_Dim!C:C)} -> North | M93: PROD16 | N93: {=XLOOKUP(M93,Product_Dim!A:A,Product_Dim!C:C)} -> Beauty | O93: {=XLOOKUP(M93,Product_Dim!A:A,Product_Dim!D:D)} -> Grooming | P93: Erickson-Green | Q93: STORE1 | R93: {=XLOOKUP(Q93,Store_Dim!A:A,Store_Dim!B:B)} -> Martinez, Adkins and Johnson | S93: {=XLOOKUP(Q93,Store_Dim!A:A,Store_Dim!E:E)} -> Flagship | T93: 4 | U93: 102.19 | V93: 0.17 | W93: 256 | X93: PayPal | Y93: 339.2708 | Z93: {=XLOOKUP(M93,Product_Dim!A:A,Product_Dim!B:B)} -> Beard Grooming Kit
A94: SALE92 | B94: 45350 | C94: February | D94: =YEAR(B94) -> 2024 | E94: CUST1007 | F94: 29 | G94: =IF(F94<18,"Under 18", IF(F94<=25,"18-25", IF(F94<=35,"26-35", IF(F94<=45,"36-45", IF(F94<=55,"46-55", IF(F94<=65,"56-65","65+")))))) -> 26-35 | H94: {=XLOOKUP(E94,Customer_Dim!A:A,Customer_Dim!D:D)} -> Female | I94: {=XLOOKUP(E94,Customer_Dim!A:A,Customer_Dim!H:H)} -> Bronze | J94: {=XLOOKUP(E94,Customer_Dim!A:A,Customer_Dim!E:E)} -> West Pamelafurt | K94: {=XLOOKUP(E94,Customer_Dim!A:A,Customer_Dim!F:F)} -> West Virginia | L94: {=XLOOKUP(Q94,Store_Dim!A:A,Store_Dim!C:C)} -> South | M94: PROD86 | N94: {=XLOOKUP(M94,Product_Dim!A:A,Product_Dim!C:C)} -> Home | O94: {=XLOOKUP(M94,Product_Dim!A:A,Product_Dim!D:D)} -> Kitchen | P94: Taylor, Dodson and Johnston | Q94: STORE4 | R94: {=XLOOKUP(Q94,Store_Dim!A:A,Store_Dim!B:B)} -> Alexander Group | S94: {=XLOOKUP(Q94,Store_Dim!A:A,Store_Dim!E:E)} -> Online | T94: 1 | U94: 696.53 | V94: 0.17 | W94: 82 | X94: Credit Card | Y94: 578.1199 | Z94: {=XLOOKUP(M94,Product_Dim!A:A,Product_Dim!B:B)} -> Kitchen Cutting Board
A95: SALE93 | B95: 45657 | C95: December | D95: =YEAR(B95) -> 2024 | E95: CUST1065 | F95: 21 | G95: =IF(F95<18,"Under 18", IF(F95<=25,"18-25", IF(F95<=35,"26-35", IF(F95<=45,"36-45", IF(F95<=55,"46-55", IF(F95<=65,"56-65","65+")))))) -> 18-25 | H95: {=XLOOKUP(E95,Customer_Dim!A:A,Customer_Dim!D:D)} -> Female | I95: {=XLOOKUP(E95,Customer_Dim!A:A,Customer_Dim!H:H)} -> Silver | J95: {=XLOOKUP(E95,Customer_Dim!A:A,Customer_Dim!E:E)} -> Woodmouth | K95: {=XLOOKUP(E95,Customer_Dim!A:A,Customer_Dim!F:F)} -> Nevada | L95: {=XLOOKUP(Q95,Store_Dim!A:A,Store_Dim!C:C)} -> South | M95: PROD19 | N95: {=XLOOKUP(M95,Product_Dim!A:A,Product_Dim!C:C)} -> Sports | O95: {=XLOOKUP(M95,Product_Dim!A:A,Product_Dim!D:D)} -> Equipment | P95: May-Reese | Q95: STORE4 | R95: {=XLOOKUP(Q95,Store_Dim!A:A,Store_Dim!B:B)} -> Alexander Group | S95: {=XLOOKUP(Q95,Store_Dim!A:A,Store_Dim!E:E)} -> Online | T95: 2 | U95: 327.52 | V95: 0.15 | W95: 65 | X95: PayPal | Y95: 556.784 | Z95: {=XLOOKUP(M95,Product_Dim!A:A,Product_Dim!B:B)} -> Knee Support Brace
A96: SALE94 | B96: 45530 | C96: August | D96: =YEAR(B96) -> 2024 | E96: CUST1298 | F96: 64 | G96: =IF(F96<18,"Under 18", IF(F96<=25,"18-25", IF(F96<=35,"26-35", IF(F96<=45,"36-45", IF(F96<=55,"46-55", IF(F96<=65,"56-65","65+")))))) -> 56-65 | H96: {=XLOOKUP(E96,Customer_Dim!A:A,Customer_Dim!D:D)} -> Male | I96: {=XLOOKUP(E96,Customer_Dim!A:A,Customer_Dim!H:H)} -> Platinum | J96: {=XLOOKUP(E96,Customer_Dim!A:A,Customer_Dim!E:E)} -> New Joshuatown | K96: {=XLOOKUP(E96,Customer_Dim!A:A,Customer_Dim!F:F)} -> Maine | L96: {=XLOOKUP(Q96,Store_Dim!A:A,Store_Dim!C:C)} -> East | M96: PROD97 | N96: {=XLOOKUP(M96,Product_Dim!A:A,Product_Dim!C:C)} -> Sports | O96: {=XLOOKUP(M96,Product_Dim!A:A,Product_Dim!D:D)} -> Team Sports | P96: Khan LLC | Q96: STORE19 | R96: {=XLOOKUP(Q96,Store_Dim!A:A,Store_Dim!B:B)} -> Mann-Austin | S96: {=XLOOKUP(Q96,Store_Dim!A:A,Store_Dim!E:E)} -> Online | T96: 2 | U96: 569.36 | V96: 0.01 | W96: 471 | X96: PayPal | Y96: =(U96*T96)-((U96*T96)*V96) -> 1127.3328 | Z96: {=XLOOKUP(M96,Product_Dim!A:A,Product_Dim!B:B)} -> Cricket Bat
A97: SALE95 | B97: 45556 | C97: September | D97: =YEAR(B97) -> 2024 | E97: CUST1321 | F97: 21 | G97: =IF(F97<18,"Under 18", IF(F97<=25,"18-25", IF(F97<=35,"26-35", IF(F97<=45,"36-45", IF(F97<=55,"46-55", IF(F97<=65,"56-65","65+")))))) -> 18-25 | H97: {=XLOOKUP(E97,Customer_Dim!A:A,Customer_Dim!D:D)} -> Female | I97: {=XLOOKUP(E97,Customer_Dim!A:A,Customer_Dim!H:H)} -> Bronze | J97: {=XLOOKUP(E97,Customer_Dim!A:A,Customer_Dim!E:E)} -> Lake Alice | K97: {=XLOOKUP(E97,Customer_Dim!A:A,Customer_Dim!F:F)} -> Tennessee | L97: {=XLOOKUP(Q97,Store_Dim!A:A,Store_Dim!C:C)} -> East | M97: PROD99 | N97: {=XLOOKUP(M97,Product_Dim!A:A,Product_Dim!C:C)} -> Home | O97: {=XLOOKUP(M97,Product_Dim!A:A,Product_Dim!D:D)} -> Kitchen | P97: Campbell Ltd | Q97: STORE6 | R97: {=XLOOKUP(Q97,Store_Dim!A:A,Store_Dim!B:B)} -> Benson-Elliott | S97: {=XLOOKUP(Q97,Store_Dim!A:A,Store_Dim!E:E)} -> Online | T97: 2 | U97: 68.29 | V97: 0.14 | W97: 146 | X97: COD | Y97: 117.4588 | Z97: {=XLOOKUP(M97,Product_Dim!A:A,Product_Dim!B:B)} -> Stainless Steel Cookware Set
A98: SALE96 | B98: 45523 | C98: August | D98: =YEAR(B98) -> 2024 | E98: CUST1244 | F98: 19 | G98: =IF(F98<18,"Under 18", IF(F98<=25,"18-25", IF(F98<=35,"26-35", IF(F98<=45,"36-45", IF(F98<=55,"46-55", IF(F98<=65,"56-65","65+")))))) -> 18-25 | H98: {=XLOOKUP(E98,Customer_Dim!A:A,Customer_Dim!D:D)} -> Male | I98: {=XLOOKUP(E98,Customer_Dim!A:A,Customer_Dim!H:H)} -> Bronze | J98: {=XLOOKUP(E98,Customer_Dim!A:A,Customer_Dim!E:E)} -> West Julia | K98: {=XLOOKUP(E98,Customer_Dim!A:A,Customer_Dim!F:F)} -> Utah | L98: {=XLOOKUP(Q98,Store_Dim!A:A,Store_Dim!C:C)} -> East | M98: PROD50 | N98: {=XLOOKUP(M98,Product_Dim!A:A,Product_Dim!C:C)} -> Sports | O98: {=XLOOKUP(M98,Product_Dim!A:A,Product_Dim!D:D)} -> Fitness | P98: Smith-King | Q98: STORE10 | R98: {=XLOOKUP(Q98,Store_Dim!A:A,Store_Dim!B:B)} -> Hill, Wagner and Ballard | S98: {=XLOOKUP(Q98,Store_Dim!A:A,Store_Dim!E:E)} -> Online | T98: 1 | U98: 842.9 | V98: 0.06 | W98: 260 | X98: COD | Y98: 792.326 | Z98: {=XLOOKUP(M98,Product_Dim!A:A,Product_Dim!B:B)} -> Boxing Hand Wraps
A99: SALE97 | B99: 45587 | C99: October | D99: =YEAR(B99) -> 2024 | E99: CUST1287 | F99: 22 | G99: =IF(F99<18,"Under 18", IF(F99<=25,"18-25", IF(F99<=35,"26-35", IF(F99<=45,"36-45", IF(F99<=55,"46-55", IF(F99<=65,"56-65","65+")))))) -> 18-25 | H99: {=XLOOKUP(E99,Customer_Dim!A:A,Customer_Dim!D:D)} -> Female | I99: {=XLOOKUP(E99,Customer_Dim!A:A,Customer_Dim!H:H)} -> Gold | J99: {=XLOOKUP(E99,Customer_Dim!A:A,Customer_Dim!E:E)} -> Millerfort | K99: {=XLOOKUP(E99,Customer_Dim!A:A,Customer_Dim!F:F)} -> Vermont | L99: {=XLOOKUP(Q99,Store_Dim!A:A,Store_Dim!C:C)} -> North | M99: PROD3 | N99: {=XLOOKUP(M99,Product_Dim!A:A,Product_Dim!C:C)} -> Clothing | O99: {=XLOOKUP(M99,Product_Dim!A:A,Product_Dim!D:D)} -> Outerwear | P99: Pineda Ltd | Q99: STORE3 | R99: {=XLOOKUP(Q99,Store_Dim!A:A,Store_Dim!B:B)} -> Johnson-Wright | S99: {=XLOOKUP(Q99,Store_Dim!A:A,Store_Dim!E:E)} -> Outlet | T99: 3 | U99: 751.94 | V99: 0.26 | W99: 452 | X99: PayPal | Y99: 1669.3068 | Z99: {=XLOOKUP(M99,Product_Dim!A:A,Product_Dim!B:B)} -> Men's Running Jacket
A100: SALE98 | B100: 45580 | C100: October | D100: =YEAR(B100) -> 2024 | E100: CUST1131 | F100: 34 | G100: =IF(F100<18,"Under 18", IF(F100<=25,"18-25", IF(F100<=35,"26-35", IF(F100<=45,"36-45", IF(F100<=55,"46-55", IF(F100<=65,"56-65","65+")))))) -> 26-35 | H100: {=XLOOKUP(E100,Customer_Dim!A:A,Customer_Dim!D:D)} -> Female | I100: {=XLOOKUP(E100,Customer_Dim!A:A,Customer_Dim!H:H)} -> Bronze | J100: {=XLOOKUP(E100,Customer_Dim!A:A,Customer_Dim!E:E)} -> Wigginsville | K100: {=XLOOKUP(E100,Customer_Dim!A:A,Customer_Dim!F:F)} -> Alabama | L100: {=XLOOKUP(Q100,Store_Dim!A:A,Store_Dim!C:C)} -> South | M100: PROD56 | N100: {=XLOOKUP(M100,Product_Dim!A:A,Product_Dim!C:C)} -> Home | O100: {=XLOOKUP(M100,Product_Dim!A:A,Product_Dim!D:D)} -> Decor | P100: Hernandez, Kennedy and Porter | Q100: STORE7 | R100: {=XLOOKUP(Q100,Store_Dim!A:A,Store_Dim!B:B)} -> Martinez-Mullins | S100: {=XLOOKUP(Q100,Store_Dim!A:A,Store_Dim!E:E)} -> Online | T100: 4 | U100: 476.28 | V100: 0.17 | W100: 190 | X100: Credit Card | Y100: 1581.2496 | Z100: {=XLOOKUP(M100,Product_Dim!A:A,Product_Dim!B:B)} -> Premium Blanket Throw
...

Sheet Sales Pivot 

Sheet All pivots 
F1: Age wise Sales Analysis | K1: Region Based Sales
A2: Gender Wise Sales Analysis
A14: Category Vs % of Sales | H14: Loyalty_Level Sales %
H24: Top 15 Results
H25: No | I25: Brand | J25: SUM of Total_Amount | K25: SUM of Total_Amount | L25: Category | M25: Sub_Category | N25: Store_Name | O25: Product
H26: 1 | I26: Cummings and Sons | J26: 41852.503 | K26: 0.019247887 | L26: {=XLOOKUP(I26,'Sales Analysis Table 1'!P:P,'Sales Analysis Table 1'!N:N)} -> Electronics | M26: {=XLOOKUP(I26,'Sales Analysis Table 1'!P:P,'Sales Analysis Table 1'!O:O)} -> Mobile | N26: {=xlookup(I26,'Sales Analysis Table 1'!P:P,'Sales Analysis Table 1'!R:R)} -> Martinez, Adkins and Johnson | O26: {=XLOOKUP(I26,'Sales Analysis Table 1'!P:P,'Sales Analysis Table 1'!Z:Z)} -> Portable Power Bank
H27: 2 | I27: French Ltd | J27: 38281.015 | K27: 0.017605366 | L27: {=XLOOKUP(I27,'Sales Analysis Table 1'!P:P,'Sales Analysis Table 1'!N:N)} -> Sports | M27: {=XLOOKUP(I27,'Sales Analysis Table 1'!P:P,'Sales Analysis Table 1'!O:O)} -> Team Sports | N27: {=xlookup(I27,'Sales Analysis Table 1'!P:P,'Sales Analysis Table 1'!R:R)} -> Benson-Elliott | O27: {=XLOOKUP(I27,'Sales Analysis Table 1'!P:P,'Sales Analysis Table 1'!Z:Z)} -> Shin Guards – Adult
H28: 3 | I28: Hogan-Lee | J28: 35489.62 | K28: 0.016321609 | L28: {=XLOOKUP(I28,'Sales Analysis Table 1'!P:P,'Sales Analysis Table 1'!N:N)} -> Clothing | M28: {=XLOOKUP(I28,'Sales Analysis Table 1'!P:P,'Sales Analysis Table 1'!O:O)} -> Footwear | N28: {=xlookup(I28,'Sales Analysis Table 1'!P:P,'Sales Analysis Table 1'!R:R)} -> Rivera-Warner | O28: {=XLOOKUP(I28,'Sales Analysis Table 1'!P:P,'Sales Analysis Table 1'!Z:Z)} -> Men's Casual Sneakers
H29: 4 | I29: Lucero LLC | J29: 34699.833 | K29: 0.015958387 | L29: {=XLOOKUP(I29,'Sales Analysis Table 1'!P:P,'Sales Analysis Table 1'!N:N)} -> Electronics | M29: {=XLOOKUP(I29,'Sales Analysis Table 1'!P:P,'Sales Analysis Table 1'!O:O)} -> Computer | N29: {=xlookup(I29,'Sales Analysis Table 1'!P:P,'Sales Analysis Table 1'!R:R)} -> Frederick-Wright | O29: {=XLOOKUP(I29,'Sales Analysis Table 1'!P:P,'Sales Analysis Table 1'!Z:Z)} -> Gaming Mechanical Keyboard
H30: 5 | I30: Smith-Charles | J30: 33993.659 | K30: 0.01563362 | L30: {=XLOOKUP(I30,'Sales Analysis Table 1'!P:P,'Sales Analysis Table 1'!N:N)} -> Clothing | M30: {=XLOOKUP(I30,'Sales Analysis Table 1'!P:P,'Sales Analysis Table 1'!O:O)} -> Footwear | N30: {=xlookup(I30,'Sales Analysis Table 1'!P:P,'Sales Analysis Table 1'!R:R)} -> Holloway Ltd | O30: {=XLOOKUP(I30,'Sales Analysis Table 1'!P:P,'Sales Analysis Table 1'!Z:Z)} -> Women's High Heels
H31: 6 | I31: Larson Ltd | J31: 33566.8 | K31: 0.015437308 | L31: {=XLOOKUP(I31,'Sales Analysis Table 1'!P:P,'Sales Analysis Table 1'!N:N)} -> Electronics | M31: {=XLOOKUP(I31,'Sales Analysis Table 1'!P:P,'Sales Analysis Table 1'!O:O)} -> Computer | N31: {=xlookup(I31,'Sales Analysis Table 1'!P:P,'Sales Analysis Table 1'!R:R)} -> Bean, Jones and Park | O31: {=XLOOKUP(I31,'Sales Analysis Table 1'!P:P,'Sales Analysis Table 1'!Z:Z)} -> Wireless Mouse
H32: 7 | I32: Nolan-Snow | J32: 31070.456 | K32: 0.014289244 | L32: {=XLOOKUP(I32,'Sales Analysis Table 1'!P:P,'Sales Analysis Table 1'!N:N)} -> Sports | M32: {=XLOOKUP(I32,'Sales Analysis Table 1'!P:P,'Sales Analysis Table 1'!O:O)} -> Team Sports | N32: {=xlookup(I32,'Sales Analysis Table 1'!P:P,'Sales Analysis Table 1'!R:R)} -> Hill, Wagner and Ballard | O32: {=XLOOKUP(I32,'Sales Analysis Table 1'!P:P,'Sales Analysis Table 1'!Z:Z)} -> Basketball
H33: 8 | I33: Cline-Mccarthy | J33: 30236.698 | K33: 0.0139058 | L33: {=XLOOKUP(I33,'Sales Analysis Table 1'!P:P,'Sales Analysis Table 1'!N:N)} -> Beauty | M33: {=XLOOKUP(I33,'Sales Analysis Table 1'!P:P,'Sales Analysis Table 1'!O:O)} -> Haircare | N33: {=xlookup(I33,'Sales Analysis Table 1'!P:P,'Sales Analysis Table 1'!R:R)} -> Gray Ltd | O33: {=XLOOKUP(I33,'Sales Analysis Table 1'!P:P,'Sales Analysis Table 1'!Z:Z)} -> Men's Hair Styling Gel
H34: 9 | I34: Phillips and Sons | J34: 28572.692 | K34: 0.013140527 | L34: {=XLOOKUP(I34,'Sales Analysis Table 1'!P:P,'Sales Analysis Table 1'!N:N)} -> Clothing | M34: {=XLOOKUP(I34,'Sales Analysis Table 1'!P:P,'Sales Analysis Table 1'!O:O)} -> Outerwear | N34: {=xlookup(I34,'Sales Analysis Table 1'!P:P,'Sales Analysis Table 1'!R:R)} -> Gray Ltd | O34: {=XLOOKUP(I34,'Sales Analysis Table 1'!P:P,'Sales Analysis Table 1'!Z:Z)} -> Women's Formal Blazer
H35: 10 | I35: Ford, Murphy and Wilson | J35: 28324.049 | K35: 0.013026176 | L35: {=XLOOKUP(I35,'Sales Analysis Table 1'!P:P,'Sales Analysis Table 1'!N:N)} -> Sports | M35: {=XLOOKUP(I35,'Sales Analysis Table 1'!P:P,'Sales Analysis Table 1'!O:O)} -> Accessories | N35: {=xlookup(I35,'Sales Analysis Table 1'!P:P,'Sales Analysis Table 1'!R:R)} -> Guerrero-Schmitt | O35: {=XLOOKUP(I35,'Sales Analysis Table 1'!P:P,'Sales Analysis Table 1'!Z:Z)} -> Soccer Training Cone Set
H36: 11 | I36: Thomas LLC | J36: 28285.614 | K36: 0.0130085 | L36: {=XLOOKUP(I36,'Sales Analysis Table 1'!P:P,'Sales Analysis Table 1'!N:N)} -> Electronics | M36: {=XLOOKUP(I36,'Sales Analysis Table 1'!P:P,'Sales Analysis Table 1'!O:O)} -> Appliances | N36: {=xlookup(I36,'Sales Analysis Table 1'!P:P,'Sales Analysis Table 1'!R:R)} -> Martinez-Mullins | O36: {=XLOOKUP(I36,'Sales Analysis Table 1'!P:P,'Sales Analysis Table 1'!Z:Z)} -> 4K Home Projector
H37: 12 | I37: Taylor-Elliott | J37: 28237.931 | K37: 0.012986571 | L37: {=XLOOKUP(I37,'Sales Analysis Table 1'!P:P,'Sales Analysis Table 1'!N:N)} -> Beauty | M37: {=XLOOKUP(I37,'Sales Analysis Table 1'!P:P,'Sales Analysis Table 1'!O:O)} -> Makeup | N37: {=xlookup(I37,'Sales Analysis Table 1'!P:P,'Sales Analysis Table 1'!R:R)} -> Benson-Elliott | O37: {=XLOOKUP(I37,'Sales Analysis Table 1'!P:P,'Sales Analysis Table 1'!Z:Z)} -> Face Foundation Kit
... H40: 15 | I40: Soto-Ellis | J40: 27622.962 | K40: 0.012703748 | L40: {=XLOOKUP(I40,'Sales Analysis Table 1'!P:P,'Sales Analysis Table 1'!N:N)} -> Sports | M40: {=XLOOKUP(I40,'Sales Analysis Table 1'!P:P,'Sales Analysis Table 1'!O:O)} -> Accessories | N40: {=xlookup(I40,'Sales Analysis Table 1'!P:P,'Sales Analysis Table 1'!R:R)} -> Bean, Jones and Park | O40: {=XLOOKUP(I40,'Sales Analysis Table 1'!P:P,'Sales Analysis Table 1'!Z:Z)} -> Outdoor Sports Water Bottle
A56: Yearly Report
A87: Product_Category | B87: SUM of Total_Amount
A88: Beauty | B88: 0.14788545
A89: Clothing | B89: 0.17440074
A90: Electronics | B90: 0.23193183
A91: Home | B91: 0.19651253
A92: Sports | B92: 0.24926945
A93: Grand Total | B93: 1

Sheet Statistical Analysis
A1: Statistics | B1: Total_Amount | C1: Unit_Price | D1: Discount | E1: Customer_Age | F1: Quantity
A2: Mean | B2: =AVERAGE('Sales Analysis Table 1'!Y:Y) -> 1087.1973 | C2: =AVERAGE('Sales Analysis Table 1'!U:U) -> 513.58279 | D2: =AVERAGE('Sales Analysis Table 1'!V:V) -> 0.14796 | E2: =AVERAGE('Sales Analysis Table 1'!F:F) -> 41.576845 | F2: =AVERAGE('Sales Analysis Table 1'!T:T) -> 2.482
A3: Median | B3: =MEDIAN(A3,'Sales Analysis Table 1'!Y:Y) -> 868.7182 | C3: =MEDIAN(B3,'Sales Analysis Table 1'!U:U) -> 522.69 | D3: =MEDIAN(C3,'Sales Analysis Table 1'!V:V) -> 0.14 | E3: =MEDIAN(D3,'Sales Analysis Table 1'!F:F) -> 42 | F3: =MEDIAN(E3,'Sales Analysis Table 1'!T:T) -> 2
A4: Mode | B4: =MODE('Sales Analysis Table 1'!Y:Y) -> #N/A | C4: =MODE('Sales Analysis Table 1'!U:U) -> 871.34 | D4: =MODE('Sales Analysis Table 1'!V:V) -> 0.1 | E4: =MODE('Sales Analysis Table 1'!F:F) -> 29 | F4: =MODE('Sales Analysis Table 1'!T:T) -> 2
A5: Minimum | B5: =MIN('Sales Analysis Table 1'!Y:Y) -> 18.459 | C5: =MIN('Sales Analysis Table 1'!U:U) -> 20.09 | D5: =MIN('Sales Analysis Table 1'!V:V) -> 0 | E5: =MIN('Sales Analysis Table 1'!F:F) -> 18 | F5: =MIN('Sales Analysis Table 1'!T:T) -> 1
A6: Maximum | B6: =MAX('Sales Analysis Table 1'!Y:Y) -> 3908.2428 | C6: =MAX('Sales Analysis Table 1'!U:U) -> 999.89 | D6: =MAX('Sales Analysis Table 1'!V:V) -> 0.3 | E6: =MAX('Sales Analysis Table 1'!F:F) -> 64 | F6: =MAX('Sales Analysis Table 1'!T:T) -> 4
A7: Count | B7: =COUNT('Sales Analysis Table 1'!Y:Y) -> 2000 | C7: =COUNT('Sales Analysis Table 1'!U:U) -> 2000 | D7: =COUNT('Sales Analysis Table 1'!V:V) -> 2000 | E7: =COUNT('Sales Analysis Table 1'!F:F) -> 2000 | F7: =COUNT('Sales Analysis Table 1'!T:T) -> 2000
A8: Variance (Sample) | B8: =_xlfn.VAR.S('Sales Analysis Table 1'!Y:Y) -> 671775.25 | C8: =_xlfn.VAR.S('Sales Analysis Table 1'!U:U) -> 79720.534 | D8: =_xlfn.VAR.S('Sales Analysis Table 1'!V:V) -> 0.0076820794 | E8: =_xlfn.VAR.S('Sales Analysis Table 1'!F:F) -> 184.28955 | F8: =_xlfn.VAR.S('Sales Analysis Table 1'!T:T) -> 1.2352936
A9: Variance (Population) | B9: =VARP('Sales Analysis Table 1'!Y:Y) -> 671439.36 | C9: =VARP('Sales Analysis Table 1'!U:U) -> 79680.674 | D9: =VARP('Sales Analysis Table 1'!V:V) -> 0.0076782384 | E9: =VARP('Sales Analysis Table 1'!F:F) -> 184.19741 | F9: =VARP('Sales Analysis Table 1'!T:T) -> 1.234676
A10: S.D(Sample) | B10: =_xlfn.STDEV.S('Sales Analysis Table 1'!Y:Y) -> 819.61896 | C10: =_xlfn.STDEV.S('Sales Analysis Table 1'!U:U) -> 282.34825 | D10: =_xlfn.STDEV.S('Sales Analysis Table 1'!V:V) -> 0.087647473 | E10: =_xlfn.STDEV.S('Sales Analysis Table 1'!F:F) -> 13.575329 | F10: =_xlfn.STDEV.S('Sales Analysis Table 1'!T:T) -> 1.1114376
A11: S.D(Population) | B11: =_xlfn.STDEV.P('Sales Analysis Table 1'!Y:Y) -> 819.41403 | C11: =_xlfn.STDEV.P('Sales Analysis Table 1'!U:U) -> 282.27765 | D11: =_xlfn.STDEV.P('Sales Analysis Table 1'!V:V) -> 0.087625558 | E11: =_xlfn.STDEV.P('Sales Analysis Table 1'!F:F) -> 13.571935 | F11: =_xlfn.STDEV.P('Sales Analysis Table 1'!T:T) -> 1.1111598
A12: Kurtosis | B12: =KURT('Sales Analysis Table 1'!Y:Y) -> -42.634788 | C12: =KURT('Sales Analysis Table 1'!U:U) -> -26.537372 | D12: =KURT('Sales Analysis Table 1'!V:V) -> -26.344625 | E12: =KURT('Sales Analysis Table 1'!F:F) -> -26.634223 | F12: =KURT('Sales Analysis Table 1'!T:T) -> -24.576416
A13: Skewness | B13: =SKEW('Sales Analysis Table 1'!Y:Y) -> 0.87904704 | C13: =SKEW('Sales Analysis Table 1'!U:U) -> -0.034813907 | D13: =SKEW('Sales Analysis Table 1'!V:V) -> 0.062951035 | E13: =SKEW('Sales Analysis Table 1'!F:F) -> -0.037467602 | F13: =SKEW('Sales Analysis Table 1'!T:T) -> 0.022378357

Sheet Ecommerce Sales Dashboard
A1: Ecommerce Sales Analysis Dashboard
A39: Top 15 Results
A40: No | B40: Brand | C40: SUM of Total_Amount | D40: SUM of Total_Amount | E40: Category | F40: Sub_Category | G40: Store_Name | H40: Product
A41: 1 | B41: Cummings and Sons | C41: 41852.503 | D41: 0.019247887 | E41: Electronics | F41: Mobile | G41: Martinez, Adkins and Johnson | H41: Portable Power Bank
A42: 2 | B42: French Ltd | C42: 38281.015 | D42: 0.017605366 | E42: Sports | F42: Team Sports | G42: Benson-Elliott | H42: Shin Guards – Adult
A43: 3 | B43: Hogan-Lee | C43: 35489.62 | D43: 0.016321609 | E43: Clothing | F43: Footwear | G43: Rivera-Warner | H43: Men's Casual Sneakers
A44: 4 | B44: Lucero LLC | C44: 34699.833 | D44: 0.015958387 | E44: Electronics | F44: Computer | G44: Frederick-Wright | H44: Gaming Mechanical Keyboard
A45: 5 | B45: Smith-Charles | C45: 33993.659 | D45: 0.01563362 | E45: Clothing | F45: Footwear | G45: Holloway Ltd | H45: Women's High Heels
A46: 6 | B46: Larson Ltd | C46: 33566.8 | D46: 0.015437308 | E46: Electronics | F46: Computer | G46: Bean, Jones and Park | H46: Wireless Mouse
A47: 7 | B47: Nolan-Snow | C47: 31070.456 | D47: 0.014289244 | E47: Sports | F47: Team Sports | G47: Hill, Wagner and Ballard | H47: Basketball
A48: 8 | B48: Cline-Mccarthy | C48: 30236.698 | D48: 0.0139058 | E48: Beauty | F48: Haircare | G48: Gray Ltd | H48: Men's Hair Styling Gel
A49: 9 | B49: Phillips and Sons | C49: 28572.692 | D49: 0.013140527 | E49: Clothing | F49: Outerwear | G49: Gray Ltd | H49: Women's Formal Blazer
A50: 10 | B50: Ford, Murphy and Wilson | C50: 28324.049 | D50: 0.013026176 | E50: Sports | F50: Accessories | G50: Guerrero-Schmitt | H50: Soccer Training Cone Set
A51: 11 | B51: Thomas LLC | C51: 28285.614 | D51: 0.0130085 | E51: Electronics | F51: Appliances | G51: Martinez-Mullins | H51: 4K Home Projector
A52: 12 | B52: Taylor-Elliott | C52: 28237.931 | D52: 0.012986571 | E52: Beauty | F52: Makeup | G52: Benson-Elliott | H52: Face Foundation Kit
... A55: 15 | B55: Soto-Ellis | C55: 27622.962 | D55: 0.012703748 | E55: Sports | F55: Accessories | G55: Bean, Jones and Park | H55: Outdoor Sports Water Bottle
